Workbook
Name ApplicationProfile: List!$E$2:$E$30
Name isAdopted: List!$A$2:$A$11
Name Ontology: List!$B$2:$B$11
Name Predicate: List!$F$2:$F$11
Name Source: List!$D$2:$D$11
Name Type: List!$C$2:$C$11

Sheet Intro
A1: When to use this document? | B1: The Federal Vocabularies (FedVoc) describe semantics in domains commonly used by Belgian government institutions. You can use them • during business analysis, when designing the data model of an application or • when authoring specifications of an API or webservice (OpenAPI, WSDL/XSD, ...). If you can't find a concept that's commonly used by Belgian government institutions, you may open an issue (https://github.com/belgif/fedvoc/issues) to request the concept to be added.
A3: How to read this document? | B3: Explanation of the sheets:
A4: Standard | B4: In the "Standard" sheet, you find the vocabulary entries accepted by the Federal government as standard vocabulary. The column ‘Ontology’ gives the different domains covered by the vocabulary. To find entries more easily, you can filter on ‘Ontology’ or do a full search (Ctrl+F). * The column ‘Name’ provides a short name of the vocabulary entry. It should be used as the basis of technical names for the entry, for instance when the item is used in a REST APIs. * The columns ‘LabelNL’ and ‘LabelFR’ provide translations of this ‘Name’. * The columns ‘Definition’ (DefinitionNL/DefinitionFR) specify a, preferably concise, definition of the entry * The columns ‘Comment’ (CommentNL/CommentFR) may provide additional information * The column ‘inOpenApi’ indicates if the entry has a corresponding OpenAPI data type
A5: Draft | B5: In the "Draft" sheet, you find the vocabulary entries that are still a work in progress.
A6: ChangeLog | B6: In this sheet you can find an overview of changes made to fedvoc.
A7: Government institutions | B7: The “Government institutions” sheet provides the common names for Belgian Government institutions (code = abbreviation, name = full name, status = Draft/Standard)
A8: Vocabulary | B8: The vocabularies coming from 3 sources are present here: Federal Government Services, Flanders, EU The following ontologies are present: Person, Organization, Location, Temporal, Generic, Other Each vocabulary element has a numeric identifier (no meaning attached), a name (camelcase, English) and a definition. A prefix pointing towards the source and the ontology has been defined so that a unique identifier (URI) can be produced. Each vocabulary element has a type associated to it: class, property, association (property linking 2 classes) and conceptscheme. The sheet also contains a column for optional comment.
A9: VocabularyNL | B9: A label and a definition in NL are added to each of the vocabulary elements of sheet Vocabulary.
A10: VocabularyFR | B10: A label and a definition in FR are added to each of the vocabulary elements of sheet Vocabulary.
A11: VocabularyTranslations | B11: This sheet displays the vocabulary elements and definitions in English, Dutch and French. (display only, no updates here)
A12: VocabularyMapping | B12: For each vocabulary element of sheet "Vocabulary" you can find here the links ("sameAs") to vocabulary elements of other sources. E.g. for a vocabulary element defined at federal level, you can see here the corresponding vocabulary elements, if any, defined by EU and by Flanders.
A13: VocabularyAdoption | B13: For each of the vocabulary elements in sheet "Vocabulary" you can find here which elements have been adopted by the various parties such as EU, Federal level, Flanders, Walloon, Brussels, French community, German community. Possible values are: draft, proposed standard, standard
... A16: Principles followed by the workgroup: | B16: The workgroup tries to reuse as much as possible existing vocabularies in order to allocate names, URI's and defintions to vocabulary items. In order of importance, the following priorities are respected: first European vocabularies, then international vocabularies and finally self-defined vocabularies.
B18: US-English or UK-English ? If there is a clear EU/international vocabulary, we use the English terminology used in this standard according to the priorities listed previously. If not, by default US-English will be preferred.
B19: The workgroup also tries to respect the ICEG-standard on URI's that can be found at https://github.com/belgif/thematic/blob/master/URI/iceg_uri_standard.md

Sheet Standard
A1: Id | B1: Source | C1: Ontology | D1: Type | E1: URI | F1: Name | G1: LabelNL | H1: LabelFR | I1: Definition | J1: DefinitionNL | K1: DefinitionFR | L1: Comment | M1: CommentNL | N1: CommentFR | O1: inOpenApi
A2: 101 | B2: EU | C2: Organization | D2: Class | E2: <eu:LegalEntity> | F2: LegalEntity | G2: Rechtspersoon | H2: Personne morale | I2: A self-employed person, company, or organization that has legal rights and obligations. | J2: Een zelfstandige, bedrijf of organisatie met wettelijke rechten en plichten. | K2: Une personne, une entreprise ou une organisation indépendante qui a des droits et des obligations juridiques. | L2: A Legal Entity able to transact business, typically registered with a body able to confer legal status such as a national business register. It is able to trade, is legally liable for its actions, accounts, tax affairs etc. This makes Legal Entities distinct from the concept of organisations or groups. Many organisations exist that are not Legal Entities, yet to the outside world they have staff, hierarchies, locations etc. Other organisations exist that are an umbrella for several Legal Entities (universities are often good examples of this). This vocabulary is concerned solely with registered Legal Entities and does not attempt to cover all possible trading bodies. Belgian legal entities are registered in CBE and have an enterprise number. | M2: Een rechtspersoon die zaken kan doen, doorgaans geregistreerd bij een instantie die een wettelijke status kan verlenen, zoals een nationaal bedrijfsregister. Het kan handelen, is wettelijk aansprakelijk voor zijn acties, rekeningen, belastingzaken, enz. Dit onderscheidt rechtspersonen van het concept van organisaties of groepen. Er bestaan ​​veel organisaties die geen rechtspersonen zijn, maar voor de buitenwereld hebben ze personeel, hiërarchieën, locaties, enz. Er bestaan ​​ook andere organisaties die een paraplu vormen voor verschillende rechtspersonen (universiteiten zijn hier vaak goede voorbeelden van). Deze woordenschat heeft uitsluitend betrekking op geregistreerde rechtspersonen en probeert niet alle mogelijke handelslichamen te dekken. Belgische rechtspersonen worden ingeschreven in de KBO en beschikken over een ondernemingsnummer. | N2: Entité juridique en mesure de réaliser des transactions commerciales, généralement enregistrée auprès d'un organisme habilité à lui conférer un statut juridique, tel qu'un registre national des entreprises. Elle est en mesure de faire du commerce, est juridiquement responsable de ses actes, de ses comptes, de ses affaires fiscales, etc. Cela distingue les entités juridiques du concept d'organisations ou de groupes. De nombreuses organisations ne sont pas des entités juridiques, mais elles ont, aux yeux du monde extérieur, du personnel, des hiérarchies, des locaux, etc. D'autres organisations regroupent plusieurs entités juridiques (les universités en sont souvent de bons exemples). Ce vocabulaire concerne uniquement les entités juridiques enregistrées et ne tente pas de couvrir tous les organismes commerciaux possibles. Les personnes morales belges sont enregistrées à la BCE et disposent d'un numéro d'entreprise. | O2: no
A3: 220 | B3: FED | C3: Organization | D3: Class | E3: <http://www.w3.org/ns/org#OrganizationalUnit> | F3: OrganizationalUnit | G3: Organisatie-eenheid | H3: Unité organisationnelle | I3: An Organization such as a department or support unit which is part of some larger Organization and only has full recognition within the context of that Organization. In particular the unit would not be regarded as a legal entity in its own right. | J3: Een organisatie zoals een afdeling of ondersteuningseenheid die deel uitmaakt van een grotere organisatie en alleen volledige erkenning heeft binnen de context van die organisatie. In het bijzonder zou de eenheid niet als een op zichzelf staande juridische entiteit worden beschouwd. | K3: Une organisation telle qu'un département ou une unité de soutien qui fait partie d'une organisation plus grande et qui n'est pleinement reconnue que dans le contexte de cette organisation. En particulier, l'unité ne serait pas considérée comme une entité juridique à part entière. | O3: no
A4: 221 | B4: FED | C4: Organization | D4: Class | E4: <http://www.w3.org/ns/org#Organization> | F4: Organization | G4: Organisatie | H4: Organisation | I4: Represents a collection of people organized together into a community or other social, commercial or political structure. The group has some common purpose or reason for existence which goes beyond the set of people belonging to it and can act as an Agent. Organizations are often decomposable into hierarchical structures. | J4: Vertegenwoordigt een verzameling mensen die samen zijn georganiseerd in een gemeenschap of een andere sociale, commerciële of politieke structuur. De groep heeft een gemeenschappelijk doel of reden van bestaan die verder gaat dan de groep mensen die erbij horen en kan optreden als een agent. Organisaties zijn vaak te ontleden in hiërarchische structuren. | K4: Représente une collection de personnes organisées ensemble dans une communauté ou une autre structure sociale, commerciale ou politique. Le groupe a un objectif commun ou une raison d'existence qui dépasse le nombre de personnes qui lui appartiennent et peut agir en tant qu'agent. Les organisations sont souvent décomposables en structures hiérarchiques. | O4: no
A5: 222 | B5: FED | C5: Organization | D5: Class | E5: <http://data.europa.eu/m8g/PublicOrganization> | F5: PublicOrganization | G5: Publieke Organisatie | H5: Organisation publique | I5: The Public Organization class represents the organization. One organization may comprise several sub-organizations and any organization may have one or more organizational units. In some cases, albeit rare ones, a Public Organization may not be a legal entity. | J5: De klasse Public Organization vertegenwoordigt de organisatie. Eén organisatie kan meerdere suborganisaties omvatten en elke organisatie kan een of meer organisatie-eenheden hebben. In sommige gevallen, zij het zeldzame, is een openbare organisatie mogelijk geen rechtspersoon. | K5: La classe Organisation publique représente l'organisation. Une organisation peut comprendre plusieurs sous-organisations et toute organisation peut avoir une ou plusieurs unités organisationnelles. Dans certains cas, même rares, une organisation publique peut ne pas être une entité juridique. | O5: no
A6: 223 | B6: FED | C6: Organization | D6: Property | E6: <https://w3id.org/i40/sto#abbreviation> | F6: abbreviatedName | G6: Afgekorte naam | H6: Nom abrégé | I6: Abbreviated name of the thing. | J6: Afgekorte naam. | K6: Nom abrégé. | L6: Abbreviated name of an organization or site. | M6: Afgekorte naam van een organisatie of een site. | N6: Nom abrégé d'une organisation ou d'un site. | O6: no
A7: 224 | B7: FED | C7: Location | D7: Property | E7: <http://www.w3.org/ns/locn#address> | F7: address | G7: Adres | H7: Adresse | I7: Identification of a location. | J7: Identificatie van een locatie. | K7: Identification d'un lieu. | O7: no
A8: 226 | B8: FED | C8: Organization | D8: Property | E8: <altLabel> | F8: commercialName | G8: Handelsnaam | H8: Dénomination commerciale | I8: Alternative label | J8: Alternatieve naam. | K8: Nom alternatif. | L8: A recognized name other than the legal name. | M8: Een erkende naam anders dan de wettelijke naam. | N8: Un nom reconnu autre que le nom légal. | O8: no
A9: 227 | B9: FED | C9: Organization | D9: Property | E9: <http://vocab.belgif.be/ns/organization#economicActivity> | F9: economicActivity | G9: Economische activiteit | H9: Activité économique | I9: The activity of the business. | J9: De economische activiteit van de business. | K9: L'activité économique du business. | L9: See rov:orgActivity (673) | M9: Zie rov:orgActivity (673) | N9: Voir rov:orgActivity (673) | O9: no
A10: 228 | B10: FED | C10: Organization | D10: Property | E10: <http://schema.org/email> | F10: email | G10: E-mail | H10: E-mail | I10: E-mail address. | J10: E-mail adres. | K10: Adresse e-mail. | O10: no
A11: 230 | B11: FED | C11: Organization | D11: Property | E11: <http://vocab.belgif.be/ns/organization#endReason> | F11: endReason | G11: Reden stopzetting | H11: Raison d'arrêt | I11: Reason why an organization or one of its sites has been stopped. | J11: Reden weer waarom een onderneming of één van zijn vestigingseenheden is gestopt. | K11: Raison pour laquelle une entreprise ou une de ses unités d'établissement a été arrêtée. | O11: no
A12: 231 | B12: FED | C12: Organization | D12: Property | E12: <identifier> | F12: enterpriseNumber | G12: Ondernemingsnummer | H12: Numéro d'entreprise | I12: Identifier issued by CBE for a registered organization | J12: Identifier toegekend door KBO aan een geregistreerde organisatie | K12: Identifiant attribué par la BCE à une organisation enregistrée | L12: CBE = Crossroads Bank for Enterprises | M12: KBO = KruispuntBank Ondernemingen | N12: BCE = Banque Carrefour des Entreprises | O12: yes
A13: 232 | B13: FED | C13: Organization | D13: Property | E13: <identifier> | F13: establishmentUnitNumber | G13: Vestigingseenheidsnummer | H13: Numéro d'unité d'établissement | I13: Identifier issued by CBE for a site (establishment) of an organization | J13: Identifier toegekend door KBO voor een vestigingseenheid van een organisatie. | K13: Identifiant attribué par la BCE pour une unité d'établissement d'une organisation | L13: CBE = Crossroads Bank for Enterprises | M13: KBO = KruispuntBank Ondernemingen | N13: BCE = Banque Carrefour des Entreprises | O13: yes
A14: 233 | B14: FED | C14: Organization | D14: Property | E14: <http://schema.org/faxNumber> | F14: faxNumber | G14: Fax-nummer | H14: Numéro de fax | I14: Fax number. | J14: Fax nummer. | K14: Numéro de fax. | O14: no
A15: 235 | B15: FED | C15: Organization | D15: Property | E15: <org:role> | F15: function | G15: Functie | H15: Fonction | I15: Role played by a person or an organization in a given organization. E.g. founder, manager, member of the management committee, ... | J15: Rol gespeeld door een persoon of organisatie in een bepaalde organisatie. Bijv. oprichter, manager, lid van het managementcomité, ... | K15: Rôle joué par une personne ou une organisation dans une organisation donnée. Par exemple: fondateur, dirigeant, membre du comité de direction, ... | O15: no
A16: 236 | B16: FED | C16: Organization | D16: Property | E16: <http://www.w3.org/ns/org#hasEstablishmentUnit> | F16: hasEstablishmentUnit | G16: Heeft vestigingseenheid | H16: A une unité d'établissement | I16: Organizations typically comprise many departments, units, teams ... 'hasEstablishmentUnit' links the parent organization with the underlying unit. | J16: Organisaties bestaan doorgaans uit vele afdelingen, eenheden, teams ... 'hasEstablishmentUnit' verbindt de moederorganisatie met de onderliggende eenheid. | K16: Les organisations comprennent généralement de nombreux départements, unités, équipes ... 'hasEstablishmentUnit' relie l'organisation parente à l'unité sous-jacente. | O16: no
A17: 237 | B17: FED | C17: Organization | D17: Property | E17: <http://www.w3.org/ns/regorg#legalForm> | F17: legalForm | G17: Rechtsvorm | H17: Forme juridique | I17: "legalForm" indicates the type of company that can be established by legal entities and companies without legal personality. The different legal forms for companies set up by legal entities are usually determined by law. Legal forms are maintained for companies without legal personality. An enterprise natural person has no legal form. A legal entity or company without legal personality may change over time from a legal form. | J17: "Rechtsvorm" duidt het soort onderneming aan dat kan opgericht worden door rechtspersonen en ondernemingen zonder rechtspersoonlijkheid. De verschillende rechtsvormen voor ondernemingen opgericht door rechtspersonen zijn meestal bij wet bepaald. Voor ondernemingen zonder rechtspersoonlijkheid worden rechtsvormen bijgehouden. Een onderneming natuurlijke persoon heeft geen rechtsvorm. Een onderneming rechtspersoon of een onderneming zonder rechtpersoonlijkheid kunnen in de loop der tijd veranderen van rechtsvorm. | K17: "Forme juridique" indique le type de société pouvant être créée par des personnes morales et des sociétés sans personnalité juridique. Les différentes formes juridiques des sociétés créées par des personnes morales sont généralement déterminées par la loi. Pour les entreprises sans personnalité juridique, les formes juridiques sont maintenues. Une entreprise personne physique n'a pas de forme juridique. Une personne morale ou une entreprise sans personnalité juridique peut changer au fil du temps d’une forme juridique. | L17: Specialization of <http://www.w3.org/ns/regorg#orgType>. | M17: Specialisatie van <http://www.w3.org/ns/regorg#orgType>. | N17: Spécialisation de <http://www.w3.org/ns/regorg#orgType>. | O17: no
A18: 238 | B18: FED | C18: Organization | D18: Property | E18: <http://www.w3.org/ns/regorg#legalName> | F18: legalName | G18: Maatschappelijke naam | H18: Dénomination sociale | I18: The legal name of the business. | J18: De wettelijke naam van het bedrijf. | K18: Le nom légal de l'entreprise. | L18: (CBE Oct 2018): there will no longer be spoken of social address, social name and social capital but of address, name and capital. | M18: (KBO okt. 2018): er wordt niet langer gesproken over sociaal adres, sociale naam en sociaal kapitaal, maar over adres, naam en kapitaal. | N18: (BCE oct 2018): on ne parlera plus d'adresse sociale, de nom social et de capital social mais d'adresse, de nom et de capital. | O18: no
A19: 239 | B19: FED | C19: Organization | D19: Property | E19: <http://vocab.belgif.be/ns/organization#legalStatus> | F19: legalStatus | G19: Rechtsstatus | H19: Statut légal | I19: The legal status of the registered organization. E.g. normal situation, judicial agreement, opening bankruptcy etc. | J19: De wettelijke status van de geregistreerde organisatie. Bijv. normale situatie, gerechtelijke overeenkomst, opening faillissement etc. | K19: Le statut légal de l'organisation enregistrée. Par exemple: situation normale, accord judiciaire, mise en faillite, etc. | O19: no
A20: 242 | B20: FED | C20: Organization | D20: Property | E20: <http://vocab.belgif.be/ns/organization#organizationType> | F20: organizationType | G20: Organisatietype | H20: Type d'organisation | I20: Type of organization: -natural person or -legal entity/undertaking without legal personality. | J20: Type organisatie: -natuurlijk persoon of -rechtspersoon/onderneming zonder rechtspersoonlijkheid. | K20: Type d'organisation: - une entreprise personne physique ou -une personne morale/entreprise sans personnalité juridique. | O20: no
A21: 244 | B21: FED | C21: Organization | D21: Property | E21: <http://vocab.belgif.be/ns/organization#naturalPerson> | F21: naturalPerson | G21: Natuurlijke persoon | H21: Personne physique | I21: Natural person. | J21: Natuurlijke persoon | K21: Personne physique | O21: no
A22: 245 | B22: FED | C22: Organization | D22: Property | E22: <http://schema.org/telephone> | F22: telephone | G22: Telefoonnummer | H22: Numéro de téléphone | I22: Telephone number. | J22: Telefoonnummer | K22: Numéro de téléphone | L22: Pattern: ^\+[1-9]\d{1,14}$ | M22: Pattern: ^\+[1-9]\d{1,14}$ | N22: Pattern: ^\+[1-9]\d{1,14}$ | O22: no
A23: 248 | B23: FED | C23: Organization | D23: Property | E23: <foaf:homepage> | F23: website | G23: Website | H23: Site web | I23: Website. | J23: Website. | K23: Site web. | O23: no
A24: 249 | B24: FED | C24: Location | D24: Class | E24: <Address> | F24: BelgianAddress | G24: Belgisch adres | H24: Adresse belge | I24: An "address representation" as conceptually defined by the INSPIRE Address Representation data type. | J24: Een "adresrepresentatie" zoals conceptueel gedefinieerd door het gegevenstype INSPIRE Address Representation. | K24: Une "représentation d'adresse" définie conceptuellement par le type de données INSPIRE Address Representation. | L24: A Belgian address representing a location. Information that makes it possible to refer in a structured and unique way to a building unit, a mooring place, a stand or a parcel based on a town name, a street name, a house number and possibly a bus number and a postcode. Alternative address designations other than house number or bus number (eg entrance indication, staircase display, floor display ...) or a building name or room name, etc. are possible through an association with address extension. Exchange of foreign addresses must be done using the address presentation object. | M24: Een Belgisch adres dat een locatie vertegenwoordigt. Informatie die het mogelijk maakt om op een gestructureerde en unieke manier naar een gebouweenheid, een ligplaats, een stand of een perceel te verwijzen op basis van de naam van een stad, een straatnaam, een huisnummer en eventueel een busnummer en een postcode. Alternatieve adresaanduidingen anders dan huisnummer of busnummer (bijv. Ingangsindicatie, trappenhuisweergave, vloerdisplay ...) of een naam van een gebouw of een kamer, enz. Zijn mogelijk via een koppeling met adresuitbreiding. Het uitwisselen van buitenlandse adressen moet gebeuren met behulp van het adrespresentatieobject. | N24: Une adresse belge représentant un emplacement. Informations permettant de faire référence de manière structurée et unique à un bâtiment, un lieu d'amarrage, un stand ou une parcelle en fonction d'un nom de ville, d'un nom de rue, d'un numéro de maison et éventuellement d'un numéro de bus et d'un code postal. Des noms d'adresse autres que le numéro de maison ou le numéro de bus (par exemple, indication d'entrée, affichage d'escalier, affichage au sol ...) ou un nom de bâtiment ou de chambre, etc. sont possibles via une association avec extension d'adresse. L'échange d'adresses étrangères doit être effectué à l'aide de l'objet de présentation d'adresse. | O24: no
A25: 250 | B25: FED | C25: Location | D25: Class | E25: <http://vocab.belgif.be/ns/location#AddressableObject> | F25: AddressableObject | G25: Adresseerbaar object | H25: Objet addressable | I25: Geographical object that can be identified with an address. Is abstract, ie the type of addressable object must always be specified (e.g. building unit, parcel, ..). | J25: Geografisch object dat kan worden geïdentificeerd met een adres. Is abstract, dwz het type adresseerbaar object moet altijd worden gespecificeerd (bijv. Gebouweenheid, perceel, ..). | K25: Objet géographique pouvant être identifié avec une adresse. Est abstrait, c'est-à-dire que le type d'objet adressable doit toujours être spécifié (par exemple: unité de construction, parcelle, ..). | O25: no
A26: 251 | B26: FED | C26: Location | D26: Class | E26: <Address> | F26: Address | G26: Adres | H26: Adresse | I26: An address is an identification of the fixed location of a property. The full address is a hierarchy consisting of components such as geographic names, with an increasing level of detail, e.g. town, then street name, then house number or name. It may also include a post code or other postal descriptors. The address may include a path of access but this depends on the function of the address. | J26: Een adres is een identificatie van de vaste locatie van een goed. Het volledige adres is een hiërarchie die bestaat uit componenten zoals geografische namen, met een toenemend detailniveau, b.v. plaats, dan straatnaam, dan huisnummer of naam. Het kan ook een postcode of andere postbeschrijvingen bevatten. Het adres kan een toegangspad bevatten, maar dit is afhankelijk van de functie van het adres. | K26: Une adresse est une identification de l’emplacement fixe d’une propriété. L'adresse complète est une hiérarchie composée de composants tels que des noms géographiques, avec un niveau de détail croissant, par ex. ville, puis nom de la rue, puis numéro ou nom de la maison. Il peut également inclure un code postal ou d'autres descripteurs postaux. L'adresse peut inclure un chemin d'accès mais cela dépend de la fonction de l'adresse. | L26: An "address representation" as conceptually defined by the INSPIRE Address Representation data type. https://github.com/INSPIRE-MIF/technical-guidelines/blob/main/data/ad/dataspecification_ad.pdf (§2.2) (§2.2) | M26: Een "adresrepresentatie" zoals conceptueel gedefinieerd door het gegevenstype INSPIRE Address Representation. https://github.com/INSPIRE-MIF/technical-guidelines/blob/main/data/ad/dataspecification_ad.pdf (§2.2) | N26: Une "représentation d'adresse" définie conceptuellement par le type de données INSPIRE Address Representation. https://github.com/INSPIRE-MIF/technical-guidelines/blob/main/data/ad/dataspecification_ad.pdf (§2.2) (§2.2) | O26: no
A27: 252 | B27: FED | C27: Location | D27: Class | E27: <http://vocab.belgif.be/ns/location#BuildingUnit> | F27: BuildingUnit | G27: Gebouw | H27: Batiment | I27: The smallest unit within a building that is suitable for residential, commercial or recreational purposes and that can be accessed via its own lockable access from the public road, a yard or a common room. | J27: De kleinste eenheid binnen een gebouw die geschikt is voor woon-,bedrijfsmatige,of recreatieve doeleinden en die ontsloten wordt via een eigen afsluitbare toegang vanaf de openbare weg,een erf of een gemeenschappelijke ruimte. | K27: La plus petite unité à l’intérieur d’un bâtiment convenant à des fins d’habitation,d’entreprise ou de récréation et qui est rendue accessible par le biais de son propre accès délimitable à partir de la voie publique,d’un terrain ou d’un espace commun. | O27: no
A28: 255 | B28: FED | C28: Location | D28: Class | E28: <GeographicPosition> | F28: GeographicPosition | G28: Geografische positie | H28: Position géographique | I28: Geographic position indicated by a point. | J28: Geografische positie aangegeven dmv een punt. | K28: Position géographique indiquée par un point. | O28: no
A29: 256 | B29: FED | C29: Generic | D29: Class | E29: <http://www.w3.org/ns/adms#Identifier> | F29: Identifier | G29: Identifier (complex) | H29: Identifiant (complexe) | I29: This class is based on the UN/CEFACT Identifier complex type defined in See Section 5.8 of Core Components Data Type Catalogue Version 3.1 (http://www.unece.org/fileadmin/DAM/cefact/codesfortrade/CCTS/CCTS-DTCatalogueVersion3p1.pdf) In RDF this is expressed using the following properties: - the content string should be provided using skos:notation, datatyped with the identifier scheme (including the version number if appropriate); - use dcterms:creator to link to a class describing the agency that manages the identifier scheme or adms:schemaAgency to provide the name as a literal. Although not part of the ADMS conceptual model, it may be useful to provide further properties to the Identifier class such as dcterms:created to provide the date on which the identifier was issued. | J29: Deze klasse is gebaseerd op het type UN / CEFACT Identifier-complex dat is gedefinieerd in Zie sectie 5.8 van Core-componenten gegevenstype catalogusversie 3.1 (http://www.unece.org/fileadmin/DAM/cefact/codesfortrade/CCTS/CCTS-DTCatalogueVersion3p1. pdf) In RDF wordt dit uitgedrukt met behulp van de volgende eigenschappen: - de inhoudstring moet worden verstrekt met gebruik van skos:notatie, datatype met het identificatieschema (inclusief het versienummer, indien van toepassing); - gebruik dcterms:creator om te linken naar een klasse die het bureau beschrijft dat het identificatieschema beheert of adms:schemaAgency om de naam als een letterlijke naam te geven. Hoewel het geen deel uitmaakt van het ADMS-conceptuele model, kan het nuttig zijn om verdere eigenschappen aan te brengen in de klasse Identifier, zoals dcterms:created om de datum op te geven waarop de identifier is uitgegeven. | K29: Cette classe est basée sur le type complexe d'identifiant CEFACT-ONU défini dans Voir la section Section 5.8 du Catalogue de types de données des composants centraux, version 3.1 (http://www.unece.org/fileadmin/DAM/cefact/codesfortrade/CCTS/CCTS-DTCatalogueVersion3p1. pdf) En RDF, cela est exprimé à l'aide des propriétés suivantes: - la chaîne de contenu doit être fournie en utilisant skos:notation, dactylographiée avec le schéma d'identificateur (y compris le numéro de version, le cas échéant); - use dcterms:creator pour se connecter à une classe décrivant l'agence qui gère le schéma d'identificateur ou adms:schemaAgency pour fournir le nom sous forme littérale. Bien que cela ne fasse pas partie du modèle conceptuel ADMS, il peut être utile de fournir des propriétés supplémentaires à la classe Identifier, telles que dcterms:created pour fournir la date à laquelle l'identifiant a été émis. | O29: no
A30: 257 | B30: FED | C30: Location | D30: Class | E30: <http://vocab.belgif.be/ns/location#MooringPlace> | F30: MooringPlace | G30: Aanlegplaats | H30: Amarrage | I30: A specifically designated place in the water, whether or not supplemented by a piece of land or a piece of land on the bank, allocated by the competent communal body and intended for the permanent anchorage of a vessel suitable for residential, commercial and recreational purposes | J30: Een door het bevoegde gemeentelijke orgaan als zodanig aangewezen plaats in het water al dan niet aangevuld met een op de oever aanwezig terrein of een gedeelte daarvan, die bestemd is voor het permanent afmeren van een vaartuig voor woon-, bedrijfsmatige of recreatieve doeleinden. | K30: Un endroit spécifiquement désigné dans l’eau, complété ou non par un terrain ou une partie de terrain sur la berge, attribué par l’organisme communal compétent et qui est destiné au mouillage permanent d’un navire adapté à des fins résidentielles, commerciales ou recréationnelles. | O30: no
A31: 258 | B31: FED | C31: Location | D31: Class | E31: <http://vocab.belgif.be/ns/location#Municipality> | F31: Municipality | G31: Gemeente | H31: Commune | I31: Official administrative zone of the Belgian territory. The municipality is the smallest administrative part of the Belgian territory whose boundaries can only be changed by the legislator. | J31: Officiële administratieve zone van het Belgisch grondgebied. De gemeente is het kleinste administratieve deel van het Belgisch grondgebied waarvan de grenzen enkel door de wetgever kunnen worden gewijzigd. | K31: Zone administrative officielle du territoire belge. La commune est la plus petite partie administrative du territoire belge dont les limites ne peuvent être modifiées que par le législateur. | O31: no
A32: 260 | B32: FED | C32: Location | D32: Class | E32: <http://vocab.belgif.be/ns/location#Parcel> | F32: Parcel | G32: Perceel | H32: Parcelle | I32: A "parcel" is a part of the territory officially established with a cadastral or administrative purpose. | J32: Een “perceel” is een deel van het grondgebied officieel vastgesteld met een kadastraal of administratief doel. | K32: Une « parcelle » est une portion du territoire officiellement délimitée dans un but cadastral ou administratif. | O32: no
A33: 262 | B33: FED | C33: Location | D33: Class | E33: <PostalDescriptor> | F33: PostalInfo | G33: Postale info | H33: Info de la poste | I33: Information given by the provider of the universal postal service for the identification of a grouping of addresses in a geographical area for postal purposes. | J33: Informatie toegekend door de aanbieder van de universele postdienst voor de identificatie van een groepering van adressen in een geografisch gebied voor postale doeleinden. | K33: Informations fournies par le fournisseur du service postal universel pour l'identification d'un regroupement d'adresses dans une zone géographique à des fins postales. | O33: no
A34: 263 | B34: FED | C34: Location | D34: Class | E34: <http://vocab.belgif.be/ns/location#Stand> | F34: Stand | G34: Standplaats | H34: Emplacement | I34: "Stand": a site or part thereof designated as such by the competent municipal authority and intended for the permanent installation of an area that is not directly and not permanently connected to the earth and suitable for residential, commercial or recreational purposes. | J34: “Standplaats” : een door het bevoegde gemeentelijke orgaan als zodanig aangewezen terrein of gedeelte daarvan dat bestemd is voor het permanent plaatsen van een niet direct en niet duurzaam met de aarde verbonden en voor woon -, bedrijfsmatige, of recreatieve doeleinden geschikte ruimte. | K34: « Emplacement » : un terrain ou une partie de terrain, attribué par l’organisme communal compétent et qui est destiné au stationnement permanent d’un espace, adapté à des fins résidentielles, commerciale ou récréative et qui n’est pas ancré de façon directe et permanente au sol. | O34: no
A35: 267 | B35: FED | C35: Location | D35: Property | E35: <Address.position> | F35: addressPosition | G35: Positie | H35: Position | I35: Position of a characteristic point that represents the position of the address according to a specific specification and includes information about the origin of the position. | J35: Positie van een karakeristiek punt dat de positie van het adres vertegenwoordigt volgens een bepaalde specificatie en inclusief informatie over de herkomst van de positie. | K35: Position d'un point caractéristique qui représente la position de l'adresse en fonction d'une spécification spécifique et inclut des informations sur l'origine de la position. | O35: no
A36: 268 | B36: FED | C36: Location | D36: Property | E36: <http://vocab.belgif.be/ns/location#addressSortField> | F36: addressSortField | G36: Adres sorteerveld | H36: Adresse champs de triage | I36: Transformation of the original house number & bus number (eg addition of leading zeros) so that this can be sorted. | J36: Transformatie van het oorspronkelijk huisnummer&busnummer (bv toevoeging van voorloopnullen) zodat dit kan worden gesorteerd. | K36: Transformation du numéro de maison d'origine et du numéro de bus (par exemple, ajout de zéros à gauche) afin que cela puisse être trié. | O36: no
A37: 269 | B37: FED | C37: Location | D37: Property | E37: <Address.status> | F37: addressStatus | G37: Adres status | H37: Statut d'adresse | I37: Current status of the address. | J37: Actuele toestand van het adres. | K37: État actuel de l'adresse. | O37: no
A38: 272 | B38: FED | C38: Location | D38: Property | E38: <http://www.w3.org/ns/locn#fullAddress> | F38: fullAddress | G38: Volledig adres | H38: Adresse complète | I38: The complete address in one string, whether or not formatted. Avoids errors due to the splitting of the address in its parts. Displays the prescribed sequence of different parts | J38: Het complete adres in één string, al dan niet geformatteerd. Vermijdt fouten tgv het opsplitsen ve adres in zijn onderdelen. Geeft de voorgeschreven volgorde vd verschillende onderdelen weer | K38: L'adresse complète dans une chaîne, formatée ou non. Évite les erreurs dues à la division de l'adresse dans ses parties. Affiche la séquence prescrite de différentes parties | O38: no
A39: 276 | B39: FED | C39: Location | D39: Property | E39: <Address.component> | F39: hasComponent | G39: Heeft onderdeel | H39: Est composé de | I39: Refers to the various components of a Class. E.g. Address (PostalInfo, Street, Municipality) | J39: Verwijst naar de verschillende componenten van een klasse. Bijv. Adres (PostalInfo, Straat, Gemeente) | K39: Fait référence aux divers composants d’une classe. Par exemple. Adresse (PostalInfo, Rue, Municipalité) | L39: BEST datamodel: hasComponent alternative property names to be checked with BEST: hasStreet, hasMunicipality, hasPartOfMunicipality, hasPostalInfo | M39: BEST datamodel: hasComponent | N39: BEST modèle de données: hasComponent | O39: no
A40: 277 | B40: FED | C40: Location | D40: Property | E40: <http://vocab.belgif.be/ns/location#hasRepresentation> | F40: hasRepresentation | G40: Heeft voorstelling | H40: Est representé par | I40: An object is represented by another. E.g. Address has an AddressRepresentation. | J40: Een object wordt vertegenwoordigd door een ander. Bijv. Adres heeft een adresrepresentatie. | K40: Un objet est représenté par un autre. Par exemple: L'adresse a une représentation d'adresse. | O40: no
A41: 280 | B41: FED | C41: Location | D41: Property | E41: <http://vocab.belgif.be/ns/location#assignedTo> | F41: assignedTo | G41: Is gehecht aan | H41: Est assigné à | I41: Addressable object to which the address has been assigned. | J41: Adresseerbaar object waaraan het adres is toegekend. | K41: Objet adressable auquel l'adresse a été attribuée. | O41: no
A42: 283 | B42: FED | C42: Location | D42: Property | E42: <http://vocab.belgif.be/ns/location#isOfficiallyAssigned> | F42: isOfficiallyAssigned | G42: Is officieel toegekend | H42: Est attribué officiellement | I42: Indicates whether the address has been officially assigned by the address manager. An address is unofficial if its existence was not known from the administrative procedures, but only after it was actually established on the site. | J42: Geeft aan of het adres officieel door de adresbeheerder is toegekend. Een adres is niet-officieel wanneer het bestaan ervan niet gekend was vanuit de administratieve procedures, maar pas nadat nadat het feitelijk is vastgesteld op het terrein. | K42: Indique si l'adresse a été officiellement attribuée par le gestionnaire d'adresses. Une adresse est officieuse si son existence n’était pas connue par les procédures administratives, mais seulement après qu’elle ait été effectivement établie sur le site. | O42: no
A43: 285 | B43: FED | C43: Location | D43: Property | E43: <AddressComponent.situatedWithin> | F43: situatedIn | G43: Is gesitueerd in | H43: Est situé à | I43: Indicator that that says that a location is situated in another location. E.g. an address can be situated in a part of a municipality, a part of a municipality is situated in a municipality | J43: Indicator die aangeeft dat een locatie zich in een andere locatie bevindt. Bijv. een adres ligt in een deel van een gemeente, een deel van een gemeente ligt in een gemeente | K43: Indicateur qui indique qu'un emplacement est situé à un autre endroit. Par exemple. une adresse peut être située dans une partie de la commune, une partie d'une commune est située dans une commune | O43: no
A44: 289 | B44: FED | C44: Location | D44: Property | E44: <http://vocab.belgif.be/ns/location#municipalityName> | F44: municipalityName | G44: Naam gemeente | H44: Nom de la commune | I44: Name of the municipality | J44: Naam van de gemeente. | K44: Nom de la commune. | M44: Zie https://github.com/belgif/fedvoc/wiki/Mapping-of-a-Belgian-(BEST)-address-on-an-international-address | N44: Voir https://github.com/belgif/fedvoc/wiki/Mapping-of-a-Belgian-(BEST)-address-on-an-international-address | O44: no
A45: 298 | B45: FED | C45: Location | D45: Property | E45: <locatorDesignator> | F45: boxNumber | G45: Busnummer | H45: Numéro de boite | I45: An officially assigned alphanumeric code that is added to the house number to distinguish multiple building units, mooring places, stands or parcels that have the same house number. | J45: Officieel toegekende alfanumerieke code die wordt toegevoegd aan het huisnummer om meerdere gebouweenheden, standplaatsen, ligplaatsen of percelen te onderscheiden die hetzelfde huisnummer hebben. | K45: Code alphanumérique, attribué officiellement, qui s’ajoute au numéro de la maison pour distinguer plusieurs unités de bâtiment, postes d’amarrage, emplacements ou parcelles qui portent le même numéro de la maison. | L45: See https://github.com/belgif/fedvoc/wiki/Mapping-of-a-Belgian-(BEST)-address-on-an-international-address | M45: Zie https://github.com/belgif/fedvoc/wiki/Mapping-of-a-Belgian-(BEST)-address-on-an-international-address | N45: Voir https://github.com/belgif/fedvoc/wiki/Mapping-of-a-Belgian-(BEST)-address-on-an-international-address | O45: no
A46: 300 | B46: FED | C46: Location | D46: Property | E46: <GeographicPosition.method> | F46: positionGeometryMethod | G46: Methode positiegeometrie | H46: Méthode position géométrique | I46: The way the point was determined. | J46: De manier waarop het punt werd bepaald. | K46: La façon dont le point a été déterminé. | O46: no
A47: 301 | B47: FED | C47: Location | D47: Property | E47: <GeographicPosition.specification> | F47: positionSpecification | G47: Positie specificatie | H47: Spécification de position | I47: The object on which the point was determined. | J47: Het object op basis waarvan het punt werd bepaald. | K47: L'objet sur lequel le point a été déterminé. | O47: no
A48: 303 | B48: FED | C48: Location | D48: Property | E48: <PostalDescriptor.postCode> | F48: postCode | G48: Postcode | H48: Code postal | I48: The postcode (a.k.a. postal code, zip code etc.) Post codes are common elements in many countries' postal address systems. Code granted by the provider of the universal postal service for the identification of a grouping of addresses in a geographical area for postal purposes. | J48: Postcodes zijn algemene elementen in de postadressystemen van veel landen. Door de aanbieder van de universele postdienst verleende code voor de identificatie van een groep adressen in een geografisch gebied voor postdoeleinden. | K48: Les codes postaux sont des éléments communs dans les systèmes d'adresses postales de nombreux pays. Code accordé par le fournisseur du service postal universel pour l'identification d'un regroupement d'adresses dans une zone géographique à des fins postales. | L48: Belgian postcodes are represented by the BelgianPostCode data type | M48: Belgische postcodes worden weergegeven door het datatype BelgianPostCode | N48: Les codes postaux belges sont représentés par le datatype BelgianPostCode | O48: no
A49: 314 | B49: FED | C49: Person | D49: Class | E49: <http://vocab.belgif.be/ns/person#Cohabitation> | F49: Cohabitation | G49: Samenwoning | H49: Cohabitation | I49: Arrangement whereby two people who are not married live together. Can, just like a marriage, form the basis of a family. Legally registered. | J49: Regeling waarbij twee personen die niet getrouwd zijn samenleven. Kan, net als bv een huwelijk, de basis vormen van een gezin. | K49: Arrangement par lequel deux personnes non mariées vivent ensemble. Peut, tout comme un mariage, former la base d'une famille. | O49: no
A50: 315 | B50: FED | C50: Person | D50: Class | E50: <http://vocab.belgif.be/ns/person#Descent> | F50: Descent | G50: Afstamming | H50: Descendance | I50: Descent is the descending line between different generations. The descent can be biological as well as non-biological, eg adoption. Descent can also be viewed in the ascending line. The concept is narrower than kinship that also includes marriage. There must be a direct link between the persons (no link between child and grandparent). | J50: Afstamming is de dalende lijn van bloedverwantschap tussen verschillende generaties. De afstamming kan ook niet-biologisch zijn, bv adoptie. Afstamming kan ook in opgaande lijn worden bekeken. Het begrip is enger dan verwantschap dat oa ook huwelijk inhoudt. | K50: La descendance est la relation descendante entre les différentes générations. La descendance peut également être non biologique, par exemple l'adoption. La descendance peut également être vue dans la ligne ascendante. Le concept est plus effrayant que la parenté qui inclut également le mariage. | O50: no
A51: 318 | B51: FED | C51: Person | D51: Class | E51: <http://vocab.belgif.be/ns/person#Guardianship> | F51: Guardianship | G51: Voogdij | H51: Tutelle | I51: Situation where a person acting as guardian serves another person and in that capacity is responsible for this person and his goods. This is the case, for example, for minors who have lost their parents or for adults who have lost their intellectual faculties. | J51: Situatie waarbij een persoon die optreedt als voogd ve ander persoon en in die hoedanigheid instaat voor deze persoon en zijn goederen. Dit is bv het geval voor minderjarigen die hun ouders zijn verloren of voor meerderjarigen die hun verstandelijke vermogens zijn verloren. | K51: Situation où une personne agissant en tant que tuteur sert une autre personne et à ce titre est responsable de cette personne et de ses biens. C'est le cas, par exemple, des mineurs ayant perdu leurs parents ou des adultes ayant perdu leurs facultés intellectuelles. | O51: no
A52: 319 | B52: FED | C52: Person | D52: Class | E52: <http://vocab.belgif.be/ns/person#Household> | F52: Household | G52: Gezin | H52: Ménage | I52: Form of cooperation that forms a recognizable social unit (eg through marriage), with persons who are related or not, who have lasting ties and provide mutual support and care. A broader concept than family where the family consists solely of close relatives, eg a single-person family or living separately together. Family members usually have the same whereabouts. | J52: Samenwerkingsvorm die een herkenbare sociale eenheid vormt (bv tgv huwelijk), met al dan niet verwante personen die duurzame banden hebben en elkaar onderling steun en verzorging verlenen. Ruimer begrip dan familie waar het gezin louter bestaat uit nabije bloedverwanten, bv een enpersoonsgezin of living apart together. Gezinsleden hebben doorgaans dezelfde Verblijfplaats. | K52: Forme de coopération qui forme une unité sociale reconnaissable (par exemple par le mariage), avec des personnes apparentées ou non, qui ont des liens durables et se soutiennent mutuellement. Un concept plus large que la famille où la famille est constituée uniquement de parents proches, par exemple une famille monoparentale ou vivant séparément ensemble. Les membres de la famille ont généralement le même endroit. | O52: no
A53: 320 | B53: FED | C53: Person | D53: Class | E53: <http://vocab.belgif.be/ns/person#HouseholdRelation> | F53: HouseholdRelation | G53: Gezinsrelatie | H53: Relation de ménage | I53: Relationship between members of the same family. Eg husband, son, mother-in-law. | J53: Relatie tussen leden van eenzelfde gezin. Bv echtgenoot, zoon, schoonmoeder. | K53: Relation entre membres d'une même famille. Par exemple, mari, fils, belle-mère. | O53: no
A54: 321 | B54: FED | C54: Person | D54: Class | E54: <http://vocab.belgif.be/ns/person#Marriage> | F54: Marriage | G54: Huwelijk | H54: Mariage | I54: A form of cohabitation organized by civil or religious law of two persons. Can, just like living together, form the basis of a family. | J54: Een door burgerlijk of religieus recht geregelde samenlevingsvorm van twee personen. Kan, net als bv samenwonen, de basis vormen van een gezin. | K54: Une forme de cohabitation organisée par la loi civile ou religieuse de deux personnes. Peut, comme vivre ensemble, former la base d'une famille. | O54: no
A55: 323 | B55: FED | C55: Person | D55: Class | E55: <http://www.w3.org/ns/person#Person> | F55: Person | G55: Persoon | H55: Personne | I55: An individual person who may be dead or alive, but not imaginary. It is that restriction that makes <person:Person> a sub class of both <foaf:Person> and <schema:Person> which both cover imaginary characters as well as real people. | J55: Een persoon die dood of levend is, maar niet denkbeeldig. Het is die beperking die <person:Person> maakt tot subklasse van <foaf:Person> en <schema:Person> die allebei zowel denkbeeldige personages als echte mensen bedekken. | K55: Une personne qui est morte ou vivante, mais pas imaginaire. C’est cette limitation qui crée <person:Person> comme sous-classe de <foaf:Person> et <schema:Person> qui couvrent à la fois des personnages imaginaires et des personnes réelles. | O55: no
A56: 324 | B56: FED | C56: Person | D56: Class | E56: <http://vocab.belgif.be/ns/person#PersonRelation> | F56: PersonRelation | G56: Persoonsrelatie | H56: Relation de personne | I56: Relationship between two or more people. Typically these are civil relations (see marital status) but not necessarily limited to this. | J56: Relatie tussen twee of meer personen. Typisch zijn dit burgerrechtelijke relaties (zie burgerlijke staat) maar niet noodzakelijk daartoe beperkt. | K56: Relation entre deux personnes ou plus. Il s’agit généralement de relations civiles (voir statut matrimonial) mais pas nécessairement limitées à cela. | O56: no
A57: 326 | B57: FED | C57: Person | D57: Class | E57: <http://vocab.belgif.be/ns/person#Resident> | F57: Resident | G57: Resident | H57: Résident | I57: Person who lives in a certain place or country. Place or country is represented here by the jurisdiction entity. | J57: Persoon die in een bepaalde plaats of land woont. Plaats of land wordt hier vertegenwoordigd door de entiteit jurisdictie. | K57: Personne qui vit dans un certain endroit ou pays. Le lieu ou le pays est représenté ici par la jurisdiction compétente. | O57: no
A58: 329 | B58: FED | C58: Person | D58: Property | E58: <http://vocab.belgif.be/ns/person#civilStatus> | F58: civilStatus | G58: Burgerlijke staat | H58: Etat civil | I58: Civil status of a person. | J58: Burgerlijke staat van een persoon. | K58: Etat civil d'une personne. | O58: no
A59: 330 | B59: FED | C59: Person | D59: Property | E59: <http://schema.org/birthDate> | F59: birthDate | G59: Geboortedatum | H59: Date de naissance | I59: The date on which the person was born. | J59: De datum waarop de persoon is geboren. | K59: La date à laquelle la personne est née. | O59: no
A60: 331 | B60: FED | C60: Person | D60: Property | E60: <http://schema.org/deathDate> | F60: deathDate | G60: Datum overlijden | H60: Date de décès | I60: The date on which the person deceased. | J60: De datum waarop de persoon is overleden. | K60: La date à laquelle la personne est décédée. | O60: no
A61: 332 | B61: FED | C61: Person | D61: Property | E61: <#term_family_name> | F61: familyName | G61: Familienaam | H61: Nom de famille | I61: A family name is usually shared by members of a family. | J61: Een familienaam wordt meestal gedeeld door leden van een gezin. | K61: Un nom de famille est généralement partagé par les membres d'une famille. | L61: Norm ISA2 | M61: Norm ISA2 | N61: Norme ISA2 | O61: no
A62: 333 | B62: FED | C62: Person | D62: Property | E62: <#term_givenname> | F62: givenName | G62: Eerste voornaam | H62: Premier prénom | I62: Most important of the given names of the person (given name aka first name). | J62: Belangrijkste vd voornamen ve persoon. | K62: Le plus important des prénoms de la personne. | O62: no
A63: 334 | B63: FED | C63: Person | D63: Property | E63: <http://vocab.belgif.be/ns/person#fullName> | F63: fullName | G63: Volledige naam | H63: Nom complet | I63: The full name of the person, usually the combination of given names and family name. | J63: De volledige naam vd persoon, doorgaans de combinatie van voornamen en familienaam. | K63: Le nom complet de la personne, généralement la combinaison des prénoms et du nom de famille. | L63: Norm ISA2 | M63: Norm ISA2 | N63: Norme ISA2 | O63: no
A64: 335 | B64: FED | C64: Person | D64: Property | E64: <http://data.europa.eu/m8g/gender> | F64: gender | G64: Geslacht | H64: Sexe | I64: The administrative gender of the person. | J64: Het administratief geslacht van de persoon. | K64: Le genre administratif de la personne. | O64: no
A65: 336 | B65: FED | C65: Person | D65: Property | E65: <http://vocab.belgif.be/ns/person#givenNames> | F65: givenNames | G65: Voornamen | H65: Prénoms | I65: Given names of the person (given names aka firstnames) concatenated into 1 string. | J65: Eerste voornaam en andere voornamen samengevoegd in 1 string. | K65: Premier prénom et autres prénoms concaténés en 1 string. | O65: no
A66: 338 | B66: FED | C66: Person | D66: Property | E66: <http://vocab.belgif.be/ns/person#householdRelation> | F66: householdRelation | G66: Gezinsrelatie | H66: Relation de ménage | I66: Nature of the relationship. Is typically determined relative to the head of the family. For example, if the father is a head of the family and a family member is a son, then if the grandfather were the head of the household the same family member would be a grandson. | J66: Aard vd relatie. Wordt typisch bepaald tov het gezinshoofd. Bv als de vader gezinshoofd is en een gezinslid is zoon, dan zou als de grootvader gezinshoofd was datzelfde gezinslid kleinzoon zijn. | K66: Nature de la relation Est généralement déterminé par rapport au chef de famille. Par exemple, si le père est un chef de famille et un membre de la famille est un fils, alors, si le grand-père était le chef de famille, le même membre de la famille serait un petit-fils. | O66: no
A67: 339 | B67: FED | C67: Person | D67: Property | E67: <http://vocab.belgif.be/ns/person#person1> | F67: person1 | G67: Persoon 1 | H67: Personne 1 | I67: First person in a relation of 2 persons. | J67: Eerste persoon in een relatie van 2 personen. | K67: Première personne dans une relation de 2 personnes. | O67: no
A68: 344 | B68: FED | C68: Person | D68: Property | E68: <identifier> | F68: nrn | G68: Rijksregisternummer | H68: Numéro de registre national | I68: Recommended best practice is to identify the resource by means of a string conforming to a formal identification system. An unambiguous reference to the resource within a given context. | J68: Aanbevolen beste praktijk is om de bron te identificeren door middel van een string die overeenkomt met een formeel identificatiesysteem. Een eenduidige verwijzing naar de bron binnen een bepaalde context. | K68: La meilleure pratique recommandée consiste à identifier la ressource à l'aide d'une chaîne conforme à un système d'identification formel. Une référence non ambiguë à la ressource dans un contexte donné. | L68: Identification code of the person in the National Register (local identifier). The person can be radiated. Special case of ssin number. (ssin = social security identification number) | M68: Identificatiecode van de persoon in het Rijksregister (lokale identificator). De persoon kan geradieerd zijn. Speciaal geval van een insz-nummer. (insz = identificatienummer sociale zekerheid) | N68: Code d'identification de la personne dans le registre national (identifiant local). La personne peut être radiée. Cas spécial d'un numéro niss. (niss = numéro d'identification de la sécurité sociale) | O68: no
A69: 345 | B69: FED | C69: Person | D69: Property | E69: <http://www.w3.org/ns/person#placeOfBirth> | F69: placeOfBirth | G69: Plaats geboorte | H69: Lieu de naissance | I69: A person's place of birth (city). | J69: De plaats (stad) waar de persoon is geboren. | K69: L'endroit (ville) où la personne est née. | L69: CBSS: country (NIS code) + municipality (string) NR: NIS code municipality/country | M69: KSZ: land (NIS-code) + gemeente (string) RR: NIS-code gemeente / land | N69: BCSS: pays (code INS) + municipalité (string) Registre National: code de la commune INS / pays | O69: no
A70: 346 | B70: FED | C70: Person | D70: Property | E70: <http://www.w3.org/ns/person#placeOfDeath> | F70: placeOfDeath | G70: Plaats overlijden | H70: Lieu de décès | I70: A person's place of death (city). | J70: De plaats (stad) waar de persoon is overleden. | K70: L'endroit (ville) où la personne est décédée. | L70: CBSS: country (NIS code) + municipality (string) NR: NIS code municipality/country | M70: KSZ: land (NIS-code) + gemeente (string) RR: NIS-code gemeente / land | N70: BCSS: pays (code INS) + municipalité (string) Registre National: code de la commune INS / pays | O70: no
A71: 349 | B71: FED | C71: Person | D71: Property | E71: <identifier> | F71: ssin | G71: INSZ | H71: NISS | I71: Social Security Identification Number issued by the National Register or CBSS | J71: Identificatienummer Sociale Zekerheid uitgegeven door het Rijksregister of door KSZ | K71: Numéro d'identification de la sécurité sociale attribué par le Registre National ou par la BCSS | L71: Either a national register number or a BIS number (issued by CBSS) (ssin = social security identification number) | M71: Kan ofwel een rijksregisternummer zijn of een BIS-nummer (uitgegeven door KSZ) (INSZ = Identificatienummer van de sociale zekerheid ) | N71: Numéro de registre national ou bien un numéro BIS (créé par la BCSS) (NISS = Numéro d'Identification de la Sécurité Sociale) | O71: yes
A72: 350 | B72: FED | C72: Temporal | D72: Class | E72: <http://vocab.belgif.be/ns/temporal#Period> | F72: Period | G72: Periode | H72: Période | I72: A period of time composed by a start date and an optional end date | J72: Een tijdsperiode samengesteld uit een startdatum en een optionele einddatum | K72: Une période composée d'une date de début et d'une date de fin facultative | O72: no
A73: 352 | B73: FED | C73: Temporal | D73: Property | E73: <http://schema.org/endDate> | F73: endDate | G73: Einddatum | H73: Date de fin | I73: The end date and time of the item (in ISO 8601 date format). | J73: De einddatum en -tijd van het item (in ISO 8601-datumformaat). | K73: Date et heure de fin de l'élément (au format de date ISO 8601). | O73: no
A74: 355 | B74: FED | C74: Temporal | D74: Property | E74: <http://schema.org/startDate> | F74: startDate | G74: Startdatum | H74: Date de début | I74: The start date and time of the item (in ISO 8601 date format). | J74: De startdatum en -tijd van het artikel (in ISO 8601-datumformaat). | K74: Date et heure de début de l'élément (au format de date ISO 8601). | O74: no
A75: 362 | B75: FED | C75: Person | D75: ConceptScheme | E75: <http://vocab.belgif.be/auth/civilstatustype> | F75: CivilStatusType | G75: Burgerlijke staat | H75: Etat civil | I75: The type of civil status of a person represented by a code assigned by the National Register. | J75: Het type burgerlijke staat van een persoon vertegenwoordigd door een code toegekend door het Rijksregister. | K75: Le type d'état civil d'une personne représenté par un code attribué par le Registre national. | L75: Definition see https://www.ibz.rrn.fgov.be/fileadmin/user_upload/nl/rr/instructies/IT-lijst/IT120_Burgerlijke_Staat_20210106.pdf | M75: Definitie: zie Rijksregister https://www.ibz.rrn.fgov.be/fileadmin/user_upload/nl/rr/instructies/IT-lijst/IT120_Burgerlijke_Staat_20210106.pdf | N75: Définition: voir Registre National https://www.ibz.rrn.fgov.be/fileadmin/user_upload/fr/rn/instructions/liste-TI/TI120_Etatcivil_20210106.pdf | O75: yes
A76: 366 | B76: FED | C76: Person | D76: ConceptScheme | E76: <http://vocab.belgif.be/auth/householdrelationtype> | F76: HouseholdRelationType | G76: Gezinsrelatie type | H76: Type de relation de ménage | I76: The type of relation of a household member to the household reference person, represented by a code assigned by the National Register. | J76: Het type relatie van een lid van het huishouden tot de referentiepersoon van het huishouden, vertegenwoordigd door een code toegekend door het Rijksregister. | K76: Le type de relation d'un membre du ménage à la personne de référence du ménage, représenté par un code attribué par le Registre national. | L76: The household relation type is always relative to the reference person of the household. For example, if the father is the reference person and a household member is a son, then if the grandfather were the reference person of the household the same household member would be a grandson. For possible values, see: https://www.ibz.rrn.fgov.be/fileadmin/user_upload/nl/rr/instructies/IT-lijst/IT141_Gezinslid_20171030.pdf | M76: Het type huishoudrelatie is altijd relatief ten opzichte van de referentiepersoon van het huishouden. Als de vader bijvoorbeeld de referentiepersoon is en een lid van het huishouden een zoon is, dan zou als de grootvader de referentiepersoon van het huishouden was, hetzelfde lid van het huishouden een kleinzoon zijn. Voor mogelijke waarden, zie: https://www.ibz.rrn.fgov.be/fileadmin/user_upload/nl/rr/instructies/IT-lijst/IT141_Gezinslid_20171030.pdf | N76: Le type de relation du ménage est toujours relatif à la personne de référence du ménage. Par exemple, si le père est la personne de référence et qu'un membre du ménage est un fils, alors si le grand-père était la personne de référence du ménage, ce même membre du ménage serait un petit-fils. Pour les valeurs possibles, voir : https://www.ibz.rrn.fgov.be/fileadmin/user_upload/nl/rr/instructies/IT-lijst/IT141_Gezinslid_20171030.pdf | O76: yes
A77: 367 | B77: FED | C77: Organization | D77: ConceptScheme | E77: <http://vocab.belgif.be/auth/function> | F77: Function | G77: Functie | H77: Fonction | I77: The conceptscheme "Function" contains the possible functions that natural persons and/or companies perform in the company. Natural persons in their own name OR natural persons who represent an enterprise OR another company as such, can perform functions in a company. It concerns persons who are authorized to represent the company (eg: administrator, curator ...). | J77: Het conceptscheme "Functie" bevat de mogelijke functies die natuurlijke personen en/of ondernemingen uitoefenen in de onderneming. Natuurlijke personen in eigen naam OF natuurlijke personen die een onderneming vertegenwoordigen OF een andere onderneming op zich, kunnen functies vervullen in een onderneming. Het gaat om personen die bevoegd zijn om de onderneming te vertegenwoordigen (bv.: beheerder, curator…). | K77: Le conceptscheme "Fonction" contient les fonctions possibles que des personnes physiques et/ou des entreprises exercent dans l'entreprise. Des personnes physiques en leur propre nom OU des personnes physiques qui représentent une entreprise OU une autre entreprise en tant que telle peuvent exercer des fonctions dans une entreprise. Il concerne les personnes autorisées à représenter la société (ex: administrateur, curateur ...). | L77: see https://economie.fgov.be/en/themes/enterprises/crossroads-bank-enterprises/services-administrations/tables-codes (KBO-codes-legal.xls tab Function) | M77: zie https://economie.fgov.be/nl/themas/ondernemingen/kruispuntbank-van/diensten-voor-administraties/codetabellen (KBO-codes-legal.xls tab Functie) | N77: voir https://economie.fgov.be/fr/themes/entreprises/banque-carrefour-des/services-pour-les/tables-de-codes (KBO-codes-legal.xls, onglet Function) | O77: no
A78: 368 | B78: FED | C78: Person | D78: ConceptScheme | E78: <http://vocab.belgif.be/auth/gendercode> | F78: GenderCode | G78: Geslacht | H78: Sexe | I78: Gender of a person: 0 = unknown, 1 = male, 2 = female | J78: Geslacht van een persoon: 0 = onbekend, 1 = mannelijk, 2 = vrouwelijk | K78: Le sexe d'une personne: 0 = inconnu, 1 = masculin, 2 = féminin | L78: The definition is aligned with the National Register and with CBSS. It focuses on the administrative gender, not on the biological sex. | M78: De definitie is afgestemd op het Nationaal Register en op KSZ. De focus ligt op het administratieve geslacht, niet op het biologische geslacht. | N78: Cette définition est conforme au Registre national et aux données de la BCSS. Elle porte sur le genre administratif, et non sur le sexe biologique. | O78: yes
A79: 372 | B79: FED | C79: Organization | D79: ConceptScheme | E79: <http://vocab.belgif.be/auth/legalform> | F79: LegalForm | G79: Rechtsvorm | H79: Forme juridique | I79: The conceptscheme "LegalForm" indicates the type of company that can be established by legal entities and companies without legal personality. The different legal forms for companies set up by legal entities are usually determined by law. Legal forms are maintained for companies without legal personality. An enterprise natural person has no legal form. A legal entity or company without legal personality may change over time from a legal form. | J79: Het conceptscheme "Rechtsvorm" duidt het soort onderneming aan dat kan opgericht worden door rechtspersonen en ondernemingen zonder rechtspersoonlijkheid. De verschillende rechtsvormen voor ondernemingen opgericht door rechtspersonen zijn meestal bij wet bepaald. Voor ondernemingen zonder rechtspersoonlijkheid worden rechtsvormen bijgehouden. Een onderneming natuurlijke persoon heeft geen rechtsvorm. Een onderneming rechtspersoon of een onderneming zonder rechtpersoonlijkheid kunnen in de loop der tijd veranderen van rechtsvorm. | K79: Le conceptscheme "Forme juridique" indique le type de société pouvant être créée par des personnes morales et des sociétés sans personnalité juridique. Les différentes formes juridiques des sociétés créées par des personnes morales sont généralement déterminées par la loi. Pour les entreprises sans personnalité juridique, les formes juridiques sont maintenues. Une entreprise personne physique n'a pas de forme juridique. Une personne morale ou une entreprise sans personnalité juridique peut changer au fil du temps d’une forme juridique. | L79: see https://economie.fgov.be/en/themes/enterprises/crossroads-bank-enterprises/services-administrations/tables-codes (KBO-codes-legal.xls tab JuridicalForm) | M79: zie https://economie.fgov.be/nl/themas/ondernemingen/kruispuntbank-van/diensten-voor-administraties/codetabellen (KBO-codes-legal.xls tab JuridicalForm) | N79: voir https://economie.fgov.be/fr/themes/entreprises/banque-carrefour-des/services-pour-les/tables-de-codes (KBO-codes-legal.xls, onglet JuridicalForm) | O79: no
A80: 373 | B80: FED | C80: Organization | D80: ConceptScheme | E80: <http://vocab.belgif.be/auth/legalstatus> | F80: LegalStatus | G80: Rechtstoestand | H80: Statut juridique | I80: The conceptscheme "LegalStatus" indicates in which legal situation the company is at any moment in its life cycle. Legal status of a company may change over time. | J80: Het conceptscheme "Rechtstoestand" geeft aan in welke rechtstoestand de onderneming is op elk ogenblik in zijn levenscyclus. Rechtstoestanden van een onderneming kunnen in de loop van de tijd wijzigen. | K80: Le conceptscheme "Statut juridique" indique dans quelle situation juridique se trouve la société à tout moment de son cycle de vie. Le statut juridique d'une entreprise peut changer avec le temps. | L80: see https://economie.fgov.be/en/themes/enterprises/crossroads-bank-enterprises/services-administrations/tables-codes (KBO-codes-legal.xls tab JuridicalSituation) | M80: zie https://economie.fgov.be/nl/themas/ondernemingen/kruispuntbank-van/diensten-voor-administraties/codetabellen (KBO-codes-legal.xls tab JuridicalSituation) | N80: voir https://economie.fgov.be/fr/themes/entreprises/banque-carrefour-des/services-pour-les/tables-de-codes ( KBO-codes-legal.xls, onglet JuridicalSituation) | O80: no
A81: 376 | B81: FED | C81: Organization | D81: ConceptScheme | E81: <http://vocab.belgif.be/auth/organizationtype> | F81: OrganizationType | G81: OrganisatieType | H81: Type d'organisation | I81: The conceptscheme "OrganizationType" specifies whether the company is - an enterprise natural person or - a legal entity/undertaking without legal personality. | J81: Het conceptscheme "OrganisatieType" geeft aan of de onderneming -een onderneming natuurlijke persoon is of -een rechtspersoon/onderneming zonder rechtspersoonlijkheid. | K81: Le conceptscheme "OrganizationType" spécifie si la société est - une entreprise personne physique ou -une personne morale/entreprise sans personnalité juridique. | L81: see https://economie.fgov.be/en/themes/enterprises/crossroads-bank-enterprises/services-administrations/tables-codes (KBO-codes-legal.xls tab TypeOfEnterprise) | M81: zie https://economie.fgov.be/nl/themas/ondernemingen/kruispuntbank-van/diensten-voor-administraties/codetabellen (KBO-codes-legal.xls-tabblad TypeOfEnterprise) | N81: voir https://economie.fgov.be/fr/themes/entreprises/banque-carrefour-des/services-pour-les/tables-de-codes (onglet TypeOfEnterprise des codes KBO-codes-legal.xls) | O81: no
A82: 377 | B82: FED | C82: Organization | D82: ConceptScheme | E82: <http://vocab.belgif.be/auth/authorization> | F82: Authorization | G82: Toelating | H82: Autorisation | I82: The conceptscheme "Authorization" contains the various authorizations allowed by an administration to the company. By authorizations we mean approvals, permits, licenses, ... that can be issued with the intention of carrying out certain activities. | J82: Het conceptscheme "Toelating" bevat de verschillende toelatingen die toegestaan zijn door een administratie aan de onderneming. Onder toelatingen verstaan we erkenningen, vergunningen, licenties, ... die uitgereikt kunnen worden met de bedoeling bepaalde activiteiten te mogen uitvoeren. | K82: Le conceptscheme "Autorisation" contient les différentes autorisations autorisées par une administration à la société. Par autorisations, nous entendons les approbations, permis, licences, ... pouvant être délivrés dans l’intention de réaliser certaines activités. | L82: see https://economie.fgov.be/en/themes/enterprises/crossroads-bank-enterprises/services-administrations/tables-codes (KBO-codes-quality-aut-activities.xls tab 'Permission' ) | M82: zie https://economie.fgov.be/nl/themas/ondernemingen/kruispuntbank-van/diensten-voor-administraties/codetabellen (KBO-codes-kwaliteit-aut-activities.xls tab 'Permission') | N82: voir https://economie.fgov.be/fr/themes/entreprises/banque-carrefour-des/services-pour-les/tables-de-codes (codes KBO-qualité-aut-activités.xls, onglet 'Permission') | O82: no
A83: 378 | B83: FED | C83: Location | D83: ConceptScheme | E83: <https://inspire.ec.europa.eu/codelist/GeometryMethodValue> | F83: PositionGeometryMethod | G83: Methode geometrische positie | H83: Méthode position géométrique | I83: Conceptscheme with Position geometry method values. | J83: Conceptscheme met waarden voor de positiegeometriewerkwijze. | K83: Conceptscheme avec les valeurs de la méthodeposition géométrique. | O83: no
A84: 379 | B84: FED | C84: Location | D84: ConceptScheme | E84: <https://inspire.ec.europa.eu/codelist/GeometrySpecificationValue> | F84: PositionSpecification | G84: Specificatie positie | H84: Spécification de position | I84: Conceptscheme with position specification values. | J84: Conceptscheme met waarden voor positiebepaling. | K84: Conceptscheme avec les valeurs de spécification de position. | O84: no
A85: 380 | B85: FED | C85: Organization | D85: ConceptScheme | E85: <http://vocab.belgif.be/auth/endreason> | F85: EndReason | G85: Reden stopzetting | H85: Raison d'arrêt | I85: The conceptscheme "EndReason" gives the reason why an organization or one of its sites has been stopped. | J85: Het conceptscheme "Reden stopzetting" geeft de reden weer waarom een onderneming of één van zijn vestigingseenheden is gestopt. | K85: Le conceptscheme "Raison d'arrêt" donne la raison pour laquelle une entreprise ou une de ses unités d'établissement a été arrêtée. | L85: see https://economie.fgov.be/en/themes/enterprises/crossroads-bank-enterprises/services-administrations/tables-codes (KBO-codes-legal.xls tab StopReasonEnterprise) | M85: zie https://economie.fgov.be/nl/themas/ondernemingen/kruispuntbank-van/diensten-voor-administraties/codetabellen (KBO-codes-legal.xls tab StopReasonEnterprise) | N85: voir https://economie.fgov.be/fr/themes/entreprises/banque-carrefour-des/services-pour-les/tables-de-codes (KBO-codes-legal.xls, onglet StopReasonEnterprise ) | O85: no
A86: 644 | B86: FED | C86: Person | D86: Property | E86: <http://vocab.belgif.be/ns/person#person2> | F86: person2 | G86: Persoon 2 | H86: Personne 2 | I86: Second person in a relation of 2 persons. | J86: Tweede persoon in een relatie van 2 personen. | K86: Seconde personne dans une relation de 2 personnes. | O86: no
A87: 645 | B87: FED | C87: Location | D87: Class | E87: <http://purl.org/dc/terms/Location> | F87: Location | G87: Plaats | H87: Lieu | I87: An identifiable geographic place. | J87: Een identificeerbare geografische plaats. | K87: Un lieu géographiquement identifiable. | O87: no
A88: 649 | B88: FED | C88: Location | D88: Property | E88: <PostalDescriptor.postName> | F88: postName | G88: Postnaam | H88: Nom postal | I88: The key postal division of the address, usually the city. (INSPIRE's definition is "One or more names created and maintained for postal purposes to identify a subdivision of addresses and postal delivery points."). Name with which the geographical area that groups the addresses for postal purposes can be indicated. | J88: De belangrijkste postafdeling van het adres, meestal de stad. (De definitie van INSPIRE is "Eén of meer namen gemaakt en onderhouden voor postdoeleinden om een onderverdeling van adressen en postbezorgingspunten te identificeren."). Naam waarmee het geografisch gebied dat de adressen voor postale doeleinden groepeert kan worden aangeduid. | K88: La division postale clé de l'adresse, généralement la ville. (La définition d'INSPIRE est "Un ou plusieurs noms créés et gérés à des fins postales pour identifier une subdivision des adresses et des points de livraison postaux"). Nom avec lequel la zone géographique qui regroupe les adresses à des fins postales peut être indiquée. | L88: examples from BEST: Brussels region: 1030: "Schaerbeek + Bruxelles (Pont Van Praet, Teichmann)" 1030: "Schaarbeek + Brussel (Van Praet, Teichmann Brug)" Flanders: 1730: "Asse/Bekkerzeel/Kobbegem/Mollem" Wallonia: 6000: postcodes are used in Addresses, however the postname is not filled by Wallonia (note that Wallonia makes use of PartOfMunicipalities which are not used by neither the Brussels region nor Flanders) See https://github.com/belgif/fedvoc/wiki/Mapping-of-a-Belgian-(BEST)-address-on-an-international-address | M88: Voorbeelden van BEST: Brussels gewest: 1030: "Schaerbeek + Bruxelles (Pont Van Praet, Teichmann)" 1030: "Schaarbeek + Brussel (Van Praet, Teichmann Brug)" Vlaanderen: 1730: "Asse/Bekkerzeel/Kobbegem/Mollem" Wallonië: 6000: postcodes worden gebruikt in Addressen, maar de Postnaam is niet ingevuld door Wallonië (noteer dat Wallonië gebruik maakt van PartOfMunicipalities die noch door het Brussels gewest noch door Vlaanderen gebruikt worden) Zie https://github.com/belgif/fedvoc/wiki/Mapping-of-a-Belgian-(BEST)-address-on-an-international-address | N88: exemples de BEST: région Bruxelles: 1030: "Schaerbeek + Bruxelles (Pont Van Praet, Teichmann)" 1030: "Schaarbeek + Brussel (Van Praet, Teichmann Brug)" Flandre: 1730: "Asse/Bekkerzeel/Kobbegem/Mollem" Wallonie: 6000: des codes postaux sont utilisés dans les Addresses, mais le nom postal n'est pas rempli en Wallonie (notez que la Wallonie se sert de PartOfMunicipalities qui ne sont pas utilisés dans la région bruxelloise ni en Flandre) Voir https://github.com/belgif/fedvoc/wiki/Mapping-of-a-Belgian-(BEST)-address-on-an-international-address | O88: no
A89: 650 | B89: FED | C89: Location | D89: Property | E89: <http://www.w3.org/ns/locn#geographicName> | F89: geographicName | G89: Geografische naam | H89: Nom géographique | I89: A proper noun applied to a spatial object. | J89: Een naam toegepast op een ruimtelijk object. | K89: Un nom propre appliqué à un objet spatial. | O89: no
A90: 651 | B90: FED | C90: Location | D90: Property | E90: <http://www.w3.org/ns/locn#adminUnitL1> | F90: adminUnitL1 | G90: Administratieve eenheid L1 | H90: Unité administrative L1 | I90: The uppermost administrative unit for the address, almost always a country. | J90: De bovenste administratieve eenheid voor het adres, bijna altijd een land. | K90: L'unité administrative la plus élevée pour l'adresse, presque toujours un pays. | O90: no
A91: 652 | B91: FED | C91: Location | D91: Property | E91: <http://www.w3.org/ns/locn#adminUnitL2> | F91: adminUnitL2 | G91: Administratieve eenheid L2 | H91: Unité administrative L2 | I91: The region of the address, usually a county, state or other such area that typically encompasses several localities. | J91: De regio van het adres, meestal een provincie, staat of een ander dergelijk gebied dat doorgaans meerdere plaatsen omvat. | K91: La région de l'adresse, généralement un comté, un état ou une autre zone, qui englobe généralement plusieurs localités. | O91: no
A92: 655 | B92: FED | C92: Organization | D92: Property | E92: <http://www.w3.org/ns/org#establishmentUnitOf> | F92: establishmentUnitOf | G92: Is vestigingseenheid van | H92: Est unité d'établissement de | I92: Indicates an Organization which has some presence at the given site. This is the inverse of `org:hasEstablishmentUnit`. | J92: Geeft een organisatie aan die aanwezig is op de betreffende site. Dit is het omgekeerde van `org:hasEstablishmentUnit`. | K92: Indique une organisation qui a une présence sur le site donné. C'est l'inverse de `org:hasEstablishmentUnit`. | O92: no
A93: 656 | B93: FED | C93: Organization | D93: Property | E93: <http://www.w3.org/ns/org#subOrganizationOf> | F93: subOrganizationOf | G93: Is dochtermaatschappij van | H93: Est société fille de | I93: Represents hierarchical containment of Organizations or OrganizationalUnits; indicates an Organization which contains this Organization. Inverse of `org:hasSubOrganization`. (context: relation between mother and daughter companies) | J93: Vertegenwoordigt hiërarchische insluiting van Organisaties of OrganizationalUnits; geeft een organisatie aan die deze organisatie bevat. Inverse van `org: hasSubOrganization`. (context: relatie tussen moeder- en dochterbedrijven) | K93: Représente le confinement hiérarchique des organisations ou des unités organisationnelles; indique une organisation qui contient cette organisation. Inverse de `org: hasSubOrganization`. (contexte: relation entre les sociétés mères et filles) | O93: no
A94: 657 | B94: FED | C94: Organization | D94: Property | E94: <http://www.w3.org/ns/org#hasSubOrganization> | F94: hasSubOrganization | G94: Heeft dochtermaatschappij | H94: A une société fille | I94: Represents hierarchical containment of Organizations or Organizational Units; indicates an organization which is a sub-part or child of this organization. Inverse of `org:subOrganizationOf`. (context: relation between mother and daughter companies) | J94: Vertegenwoordigt hiërarchische insluiting van organisaties of organisatie-eenheden; geeft een organisatie aan die een subpartij of een kind van deze organisatie is. Inverse van `org: subOrganizationOf`. (context: relatie tussen moeder- en dochterbedrijven) | K94: Représente le confinement hiérarchique des organisations ou des unités organisationnelles; indique une organisation qui est une sous-partie ou un enfant de cette organisation. Inverse de `org: subOrganizationOf`. (contexte: relation entre les sociétés mères et filles) | O94: no
A95: 658 | B95: FED | C95: Organization | D95: Class | E95: <http://www.w3.org/ns/org#FormalOrganization> | F95: FormalOrganization | G95: Formele Organisatie | H95: Organisation formelle | I95: An Organization which is recognized in the world at large, in particular in legal jurisdictions, with associated rights and responsibilities. Examples include a Corporation, Charity, Government or Church. | J95: Een organisatie die wordt erkend in de wereld als geheel, met name in juridische jurisdicties, met bijbehorende rechten en verantwoordelijkheden. Voorbeelden zijn een bedrijf, liefdadigheidsinstelling, regering of kerk. | K95: Une organisation reconnue dans le monde entier, en particulier dans les juridictions, avec des droits et des responsabilités associés. Les exemples incluent une corporation, une charité, un gouvernement ou une église. | O95: no
A96: 660 | B96: FED | C96: Organization | D96: Property | E96: <http://www.w3.org/ns/org#hasUnit> | F96: hasUnit | G96: Heeft eenheid | H96: A une unité | I96: Indicates a unit which is part of this Organization, e.g. a Department within a larger FormalOrganization. Inverse of `org:unitOf`. | J96: Geeft een eenheid aan die deel uitmaakt van deze organisatie, b.v. een afdeling binnen een grotere FormalOrganization. Inverse van `org: unitOf`. | K96: Indique une unité faisant partie de cette organisation, par ex. un département au sein d'une organisation formelle plus grande. Inverse de `org: unitOf`. | O96: no
A97: 661 | B97: FED | C97: Organization | D97: Property | E97: <http://www.w3.org/ns/org#unitOf> | F97: unitOf | G97: Is eenheid van | H97: Est unité de | I97: Indicates an Organization of which this Unit is a part, e.g. a Department within a larger FormalOrganization. This is the inverse of `org:hasUnit`. | J97: Geeft een organisatie aan waarvan deze eenheid een onderdeel is, bijvoorbeeld een afdeling binnen een grotere FormalOrganization. Dit is het omgekeerde van `org: hasUnit`. | K97: Indique une organisation dont cette unité fait partie, par ex. un département au sein d'une organisation formelle plus grande. C'est l'inverse de `org: hasUnit`. | O97: no
A98: 662 | B98: FED | C98: Location | D98: Class | E98: <ThoroughfareName> | F98: StreetName | G98: Straatnaam | H98: Nom de la rue | I98: An address component that represents the name of a passage or way through from one location to another. A thoroughfare is not necessarily a road, it might be a waterway or some other feature. | J98: Een adrescomponent die de naam is van een passage of een weg door de ene locatie naar de andere. Een verkeersweg is niet noodzakelijkerwijs een weg, het kan een waterweg zijn of een andere functie. | K98: Un composant d'adresse qui est le nom d'un passage ou d'une route passant d'un endroit à un autre. Une route n'est pas nécessairement une route, elle peut être une voie navigable ou une fonction différente. | L98: BEST: Address component with the name officially assigned to a street (runway, passage, square) or to a hamlet and to which addresses can be linked. BEST = Belgian standard for adresses. (also see <locn:Thoroughfare>) | M98: BEST: Adrescomponent met de naam die officieel werd toegekend aan een straat (baan, doorgang, plein) of aan een gehucht en waaraan adressen kunnen zijn gekoppeld. BEST = Belgische standaard voor adressen. (zie ook <locn:Thoroughfare>) | N98: BEST: Composant d'adresse avec le nom attribué officiellement à une rue (piste, passage, carré) ou à un hameau et auquel des adresses peuvent être liées. BEST = standard belge pour les adresses (voir également <locn:Thoroughfare>) | O98: no
A99: 663 | B99: FED | C99: Location | D99: Property | E99: <locatorDesignator> | F99: houseNumber | G99: Huisnummer | H99: Numéro de la maison | I99: A number or a sequence of characters that uniquely identifies the locator within the relevant scope(s). The full identification of the locator could include one or more locator designators. | J99: Een aantal of een reeks tekens die de locator op unieke wijze identificeert binnen de relevante scope (s). De volledige identificatie van de locator kan een of meer locator-aanduidingen bevatten. | K99: Un nombre ou une séquence de caractères identifiant de manière unique le localisateur dans la ou les portées pertinentes. L’identification complète du localisateur pourrait inclure un ou plusieurs indicateurs de localisateur. | L99: Alphanumeric code officially assigned to building units (house number), mooring places, stands or parcels. See https://github.com/belgif/fedvoc/wiki/Mapping-of-a-Belgian-(BEST)-address-on-an-international-address | M99: Alfanumerieke code officieel toegekend aan gebouweenheden, ligplaatsen, standplaatsen of percelen. Zie https://github.com/belgif/fedvoc/wiki/Mapping-of-a-Belgian-(BEST)-address-on-an-international-address | N99: Code alphanumérique attribué officiellement à des unités de bâtiment, postes d’amarrage, emplacements ou parcelles. Voir https://github.com/belgif/fedvoc/wiki/Mapping-of-a-Belgian-(BEST)-address-on-an-international-address | O99: no
A100: 664 | B100: FED | C100: Location | D100: Property | E100: <ThoroughfareName.name> | F100: streetName | G100: Straatnaam | H100: Nom de la rue | I100: The name of a passage or way through from one location to another. A thoroughfare is not necessarily a road, it might be a waterway or some other feature. Name of the street (in the sense of spelling, possibly in several languages). | J100: De naam van een passage of een doorgang van de ene naar de andere locatie. Niet noodzakelijkerwijs een weg, het kan een waterweg zijn of een andere functie. Naam van de straat (in de betekenis van spelling, eventueel in meerdere talen). | K100: Le nom d'un passage ou chemin d'un endroit à un autre. Pas nécessairement une route, il peut s'agir d'une voie navigable ou d'une autre caractéristique. Nom de la rue (dans le sens de l'orthographe, éventuellement en plusieurs langues). | L100: Name of the street (in the sense of spelling, possibly in several languages). See https://github.com/belgif/fedvoc/wiki/Mapping-of-a-Belgian-(BEST)-address-on-an-international-address | M100: Naam van de straat (in de betekenis van spelling, eventueel in meerdere talen). Zie https://github.com/belgif/fedvoc/wiki/Mapping-of-a-Belgian-(BEST)-address-on-an-international-address | N100: Nom de la rue (dans le sens de l'orthographe, éventuellement en plusieurs langues). Voir https://github.com/belgif/fedvoc/wiki/Mapping-of-a-Belgian-(BEST)-address-on-an-international-address | O100: no
...

Sheet Draft
A1: Id | B1: Source | C1: Ontology | D1: Type | E1: URI | F1: Name | G1: LabelNL | H1: LabelFR | I1: Definition | J1: DefinitionNL | K1: DefinitionFR | L1: Comment | M1: CommentNL | N1: CommentFR | O1: inOpenApi
A2: 243 | B2: FED | C2: Organization | D2: Property | E2: <http://vocab.belgif.be/ns/organization#authorization> | F2: authorization | G2: Toelating | H2: Autorisation | I2: Authorization allowed by an administration to the company. By authorizations we mean approvals, permits, licenses, ... that can be issued with the intention of carrying out certain activities. | J2: Toelating toegestaan zijn door een administratie aan de onderneming. Onder toelatingen verstaan we erkenningen, vergunningen, licenties, ... die uitgereikt kunnen worden met de bedoeling bepaalde activiteiten te mogen uitvoeren. | K2: Autorisation autorisée par une administration à la société. Par autorisations, nous entendons les approbations, permis, licences, ... pouvant être délivrés dans l’intention de réaliser certaines activités. | O2: no
A3: 261 | B3: FED | C3: Location | D3: Class | E3: <http://vocab.belgif.be/ns/location#PartOfMunicipality> | F3: PartOfMunicipality | G3: Deelgemeente | H3: Sous-municipalité | I3: A part of a municipality, such as a former municipality (prior to the merger of the municipalities), or a neighborhood. | J3: Een deel van een gemeente, zoals een voormalige gemeente (voorafgaand aan de fusie van de gemeenten), of een wijk. | K3: Une partie du territoire d’une commune, telle qu’une ancienne commune (préalable à la fusion des communes) ou un quartier. | L3: Context BEST: Part of Municipality is a class defined by the Walloon region. It does not exist in Flanders nor in the Brussels region. | M3: Context BEST: Een deelgemeente is een klasse gedefinieerd door het Waalse Gewest. Het bestaat niet in Vlaanderen, noch in het Brussels Gewest. | N3: Contexte BEST: Une sous-municipalité est une classe définie par la région wallonne. Elle n'existe pas en Flandre ni en région bruxelloise. | O3: no
A4: 278 | B4: FED | C4: Location | D4: Property | E4: <http://vocab.belgif.be/ns/location#homonymAddition> | F4: homonymAddition | G4: Homoniemtoevoeging | H4: Addition homonyme | I4: Addition to distinguish double street names (street names with the same name but different location in the municipality and their own addresses). | J4: Toevoeging om dubbele straatnamen (straatnamen met dezelfde naam maar andere ligging in de gemeente en eigen adressen) van elkaar te onderscheiden. | K4: Ajout pour distinguer les noms de rues doubles (noms de rues avec le même nom mais emplacement différent dans la municipalité et leurs propres adresses). | L4: See https://github.com/belgif/fedvoc/wiki/Mapping-of-a-Belgian-(BEST)-address-on-an-international-address | M4: Zie https://github.com/belgif/fedvoc/wiki/Mapping-of-a-Belgian-(BEST)-address-on-an-international-address | N4: Voir https://github.com/belgif/fedvoc/wiki/Mapping-of-a-Belgian-(BEST)-address-on-an-international-address | O4: no
A5: 297 | B5: FED | C5: Location | D5: Property | E5: <http://vocab.belgif.be/ns/location#partOfMunicipalityName> | F5: partOfMunicipalityName | G5: Naam deelgemeente | H5: Nom de la sous-municipalité | I5: Name of the part of the municipality | J5: Naam van de deelgemeente | K5: Nom de la partie de la commune | L5: Context BEST: Part of Municipality is a class defined by the Walloon region. It does not exist in Flanders nor in the Brussels region. See https://github.com/belgif/fedvoc/wiki/Mapping-of-a-Belgian-(BEST)-address-on-an-international-address | M5: Context BEST: Een deelgemeente is een klasse gedefinieerd door het Waalse Gewest. Het bestaat niet in Vlaanderen, noch in het Brussels Gewest. Zie https://github.com/belgif/fedvoc/wiki/Mapping-of-a-Belgian-(BEST)-address-on-an-international-address | N5: Contexte BEST: Une sous-municipalité est une classe définie par la région wallonne. Elle n'existe pas en Flandre ni en région bruxelloise. Voir https://github.com/belgif/fedvoc/wiki/Mapping-of-a-Belgian-(BEST)-address-on-an-international-address | O5: no
A6: 299 | B6: FED | C6: Location | D6: Property | E6: <http://vocab.belgif.be/ns/location#pointGeometry> | F6: pointGeometry | G6: Geometrisch punt | H6: Point géométrique | I6: The cartographic coordinates of the point. | J6: De cartografische coordinaten van het punt. | K6: Les coordonnées cartographiques du point. | O6: no
A7: 337 | B7: FED | C7: Person | D7: Property | E7: <http://vocab.belgif.be/ns/person#headOf> | F7: headOf | G7: Hoofd van | H7: Chef de | I7: Person who represents the household by default. | J7: Persoon die standaard het gezin vertegenwoordigt. | K7: Personne qui représente le ménage par défaut. | O7: no
A8: 341 | B8: FED | C8: Person | D8: Property | E8: <http://vocab.belgif.be/ns/person#memberOf> | F8: memberOf | G8: Lid van | H8: Membre de | I8: Person who belongs to a household. | J8: Persoon die tot een gezin behoort. | K8: Personne qui appartient à un ménage. | O8: no
A9: 343 | B9: FED | C9: Person | D9: Property | E9: <http://vocab.belgif.be/ns/person#nationality> | F9: nationality | G9: Nationaliteit | H9: Nationalité | I9: The relationship between a person and a state, culture or loyalty. Note that this concept is broader than citizenship (which is limited to the relationship with a state). Anyone who has the nationality of a particular country is usually automatically a citizen. Nationality is usually obtained automatically by birth: one gets either the nationality of his parents or one gets the vv country where one is a Resident. One can also obtain a certain nationality through naturalization. In principle, people lose their original nationality, but that is not always the case (multiple nationality). | J9: De relatie tussen een persoon en een staat, cultuur of loyaliteit. Merk op dat dit begrip ruimer is dan staatsburgerschap (dat zich beperkt tot de relatie met een staat). Wie de nationaliteit ve bepaald land heeft is er doorgaans ook automatisch staatsburger van. Nationaliteit wordt doorgaans autamatisch verkregen door geboorte: men krijgt hetzij de nationaliteit van zijn ouders of men krijgt deze vh land waar men Inwoner van is. Men kan een bepaalde nationaliteit ook verkrijgen door naturalisatie. In principe verliest men dan zijn oorspronkelijke nationaliteit, maar dat is niet altijd zo (meervoudige nationaliteit). | K9: La relation entre une personne et un État, la culture ou la loyauté. Notez que ce concept est plus large que la citoyenneté (qui se limite à la relation avec un État). Quiconque a la nationalité d'un pays particulier est généralement automatiquement citoyen. La nationalité est généralement obtenue automatiquement à la naissance: on obtient soit la nationalité de ses parents, soit on obtient le pays où on est résident. On peut aussi obtenir une certaine nationalité par naturalisation. En principe, les personnes perdent leur nationalité d'origine, mais ce n'est pas toujours le cas (pluralité de nationalités). | O9: no
A10: 348 | B10: FED | C10: Person | D10: Property | E10: <http://vocab.belgif.be/ns/person#residenceAddress> | F10: residenceAddress | G10: Adres hoofdverblijf | H10: Adresse de résidence | I10: Place where a person lives or stays temporarily. | J10: Plaats waar een persoon woont of logeert. | K10: Lieu où une personne vit ou reste temporairement. | O10: no
A11: 359 | B11: FED | C11: Location | D11: Class | E11: <http://vocab.belgif.be/ns/location#GM_Point> | F11: GM_Point | G11: GM_Point | H11: GM_Point | I11: GM_Point is the basic data type for a geometric object consisting of one and only one point. | J11: GM_Point is het elementaire gegevenstype voor een meetkundig object bestaande uit één en slechts één punt. | K11: GM_Point est le type de données de base pour un objet géométrique consistant en un et un seul point. | L11: http://inspire-regadmin.jrc.ec.europa.eu/dataspecification/ScopeObjectDetail.action?objectDetailId=11377 | M11: http://inspire-regadmin.jrc.ec.europa.eu/dataspecification/ScopeObjectDetail.action?objectDetailId=11377 | N11: http://inspire-regadmin.jrc.ec.europa.eu/dataspecification/ScopeObjectDetail.action?objectDetailId=11377 | O11: no
A12: 360 | B12: FED | C12: Location | D12: ConceptScheme | E12: <http://vocab.belgif.be/auth/addressstatus> | F12: AddressStatus | G12: Status adres | H12: Statut d'adresse | I12: Conceptscheme with possible status values for a BEST address. | J12: Conceptscheme met mogelijke statuswaarden voor een BEST-adres. | K12: Conceptscheme avec les valeurs d'état possibles pour une adresse BEST. | O12: no
A13: 361 | B13: FED | C13: Person | D13: ConceptScheme | E13: <http://vocab.belgif.be/auth/administrativestatus> | F13: AdministrativeStatus | G13: Administratieve status | H13: Statut administratif | I13: Conceptscheme with the values of an administrative status. | J13: Conceptscheme met de waarden van een administratieve status. | K13: Statut administratif. | O13: no
A14: 363 | B14: FED | C14: Person | D14: ConceptScheme | E14: <http://vocab.belgif.be/auth/descent> | F14: Descent | G14: Afstamming | H14: Descendance | I14: Conceptscheme with the values for the descent of a person. Descent is the descending line of blood relationship between different generations. The descent can also be non-biological, eg adoption. Descent can also be viewed in the ascending line. The concept is scarier than kinship that also includes marriage. | J14: Conceptscheme met de waarden voor de afstamming van een persoon. Afstamming is de dalende lijn van bloedverwantschap tussen verschillende generaties. De afstamming kan ook niet-biologisch zijn, bv adoptie. Afstamming kan ook in opgaande lijn worden bekeken. Het begrip is enger dan verwantschap dat oa ook huwelijk inhoudt. | K14: Conceptscheme avec les valeurs pour la descendance d'une personne. La descendance est la relation descendante entre les différentes générations. La descendance peut également être non biologique, par exemple l'adoption. La descendance peut également être vue dans la ligne ascendante. Le concept est plus effrayant que la parenté qui inclut également le mariage. | L14: CONCEPTSCHEME DEFINITION to be done | M14: CONCEPTSCHEME DEFINITION to do | N14: CONCEPTSCHEME DEFINITION to do | O14: no
A15: 653 | B15: FED | C15: Location | D15: Property | E15: <http://www.w3.org/ns/locn#addressArea> | F15: addressArea | G15: Adresgebied | H15: Zone d'adresse | I15: The name or names of a geographic area or locality that groups a number of addressable objects for addressing purposes, without being an administrative unit. This would typically be part of a city, a neighbourhood or village. | J15: De naam of namen van een geografisch gebied of een geografische locatie die een aantal adresseerbare objecten groepeert voor adresdoeleinden, zonder een administratieve eenheid te zijn. Dit zou typisch onderdeel zijn van een stad, een buurt of een dorp. | K15: Le ou les noms d'une zone géographique ou d'une localité regroupant un certain nombre d'objets adressables à des fins d'adressage, sans être une unité administrative. Cela ferait typiquement partie d'une ville, d'un quartier ou d'un village. | O15: no
A16: 654 | B16: FED | C16: Location | D16: Property | E16: <http://www.w3.org/ns/locn#locatorName> | F16: locatorName | G16: Locatienaam | H16: Nom de la localisation | I16: Proper noun(s) applied to the real world entity identified by the locator. The locator name could be the name of the property or complex, of the building or part of the building, or it could be the name of a room inside a building. | J16: Naam toegepast op de entiteit in de echte wereld geïdentificeerd door de locator. De locatornaam kan de naam zijn van het pand of complex, van het gebouw of een deel van het gebouw, of het kan de naam zijn van een kamer in een gebouw. | K16: Nom (s) approprié (s) appliqué (s) à l'entité du monde réel identifiée par le localisateur. Le nom du localisateur pourrait être le nom de la propriété ou du complexe, du bâtiment ou d’une partie du bâtiment, ou le nom d’une pièce à l’intérieur d’un bâtiment. | O16: no
A17: 674 | B17: FED | C17: Person | D17: Property | E17: <http://www.w3.org/ns/person#residency> | F17: residency | G17: Resident van | H17: Résident de | I17: Residency typically provides an individual with a subset of the rights of a citizen. | J17: Residentie (inwonerschap) biedt een individu typisch een deelverzameling van de rechten van een burger. | K17: La résidence fournit généralement à un individu un sous-ensemble des droits d'un citoyen. | O17: no
A18: 675 | B18: FED | C18: Person | D18: Property | E18: <http://www.w3.org/ns/person#citizenship> | F18: citizenship | G18: Burger van | H18: Citoyen de | I18: The citizenship relationship links a Person to a Jurisdiction that has conferred citizenship rights on the individual such as the right to vote, to receive certain protection from the community or the issuance of a passport. Multiple citizenships are recorded as multiple instances of the citizenship relationship. | J18: De burgerschapsrelatie (staatsburgerschap) verbindt een persoon met een rechtsgebied dat burgerschapsrechten heeft verleend aan het individu, zoals het stemrecht, bepaalde bescherming van de gemeenschap of de uitgifte van een paspoort. Meer nationaliteiten worden geregistreerd als meer instanties van de relatie tussen staatsburgerschap. | K18: La relation de citoyenneté lie une personne à une juridiction qui lui a conféré des droits, tels que le droit de voter, le droit de recevoir une certaine protection de la communauté ou la délivrance d'un passeport. Les citoyennetés multiples sont enregistrées en tant qu'exemples multiples de la relation de citoyenneté. | O18: no
A19: 676 | B19: FED | C19: Person | D19: Class | E19: <http://purl.org/dc/terms/Jurisdiction> | F19: Jurisdiction | G19: Jurisdictie | H19: Juridiction | I19: The extent or range of judicial, law enforcement, or other authority. | J19: De omvang of het bereik van juridische, wetshandhaving of andere autoriteit. | K19: L'étendue ou la gamme des autorités judiciaires, des forces de l'ordre ou autres. | O19: no
A20: 682 | B20: FED | C20: Organization | D20: Property | E20: <http://vocab.belgif.be/auth/quality> | F20: quality | G20: hoedanigheid | H20: qualité | I20: A qualities is allowed by the administration to a company. A quality that the company is known to, can be VAT-liable, "Employer"... The quality can be in different stages: 'in application', 'refused', 'awarded', ... | J20: Een hoedanigheid is door de administratie toegestaan aan een bedrijf. Het gaat om hoedanigheden waaronder de onderneming gekend is, zoals 'BTW-plichtige’, ‘Werkgever’. De hoedanigheid kan zich in verschillende stadia bevinden: 'in aanvraag', 'geweigerd', 'toegekend', ... | K20: Une qualité est autorisée par l'administration à l'entreprise. Ce sont des qualités que l’entreprise connaît, telles que «assujetti à la TVA», «employeur». La qualité peut être à différentes étapes: "en application", "refusée", "attribuée", ... | O20: no
A21: 683 | B21: FED | C21: Person | D21: Property | E21: <http://vocab.belgif.be/ns/person#administrativeStatus> | F21: administrativeStatus | G21: administratieve status | H21: statut administratif | I21: Administrative status. | J21: Administratieve status. | K21: Conceptscheme avec les valeurs d'un statut administratif. | O21: no
A22: 696 | B22: FED | C22: Other | D22: Property | E22: <identifier> | F22: plateNumber | G22: Nummerplaat | H22: Plaque d'immatriculation | I22: Recommended best practice is to identify the resource by means of a string conforming to a formal identification system. An unambiguous reference to the resource within a given context. | J22: Aanbevolen beste praktijk is om de bron te identificeren door middel van een string die overeenkomt met een formeel identificatiesysteem. Een eenduidige verwijzing naar de bron binnen een bepaalde context. | K22: La meilleure pratique recommandée consiste à identifier la ressource à l'aide d'une chaîne conforme à un système d'identification formel. Une référence non ambiguë à la ressource dans un contexte donné. | L22: The official set of numbers and letters shown on the front and back of a road vehicle | M22: De officiële reeks cijfers en letters op de voor- en achterkant van een wegvoertuig | N22: L'ensemble officiel de chiffres et de lettres figurant à l'avant et à l'arrière d'un véhicule routier | O22: no
A23: 697 | B23: FED | C23: Other | D23: Property | E23: <identifier> | F23: ipAddress | G23: IP-adres | H23: Adresse IP | I23: Recommended best practice is to identify the resource by means of a string conforming to a formal identification system. An unambiguous reference to the resource within a given context. | J23: Aanbevolen beste praktijk is om de bron te identificeren door middel van een string die overeenkomt met een formeel identificatiesysteem. Een eenduidige verwijzing naar de bron binnen een bepaalde context. | K23: La meilleure pratique recommandée consiste à identifier la ressource à l'aide d'une chaîne conforme à un système d'identification formel. Une référence non ambiguë à la ressource dans un contexte donné. | L23: An Internet Protocol address (IP address) is a numerical label assigned to each device connected to a computer network that uses the Internet Protocol for communication. | M23: Een internetprotocoladres (IP-adres) is een numeriek label dat wordt toegewezen aan elk apparaat dat is aangesloten op een computernetwerk dat het internetprotocol gebruikt voor communicatie. | N23: Une adresse de protocole Internet (adresse IP) est une étiquette numérique attribuée à chaque périphérique connecté à un réseau informatique qui utilise le protocole Internet pour la communication. | O23: no
A24: 710 | B24: FED | C24: Location | D24: Class | E24: <http://vocab.belgif.be/ns/location#Country> | F24: Country | G24: Land | H24: Pays | I24: A country is a political state, nation, or territory which is controlled. It is often referred to as the land of an individual's birth, residence, or citizenship. | J24: Een land is een politieke staat, natie of territorium dat wordt gecontroleerd. Het wordt vaak het land van iemands geboorte, verblijf of staatsburgerschap genoemd. | K24: Un pays est un État, une nation ou un territoire politique qui est contrôlé. On l'appelle souvent le pays de naissance, de résidence ou de citoyenneté d'un individu. | O24: no
A25: 713 | B25: FED | C25: Location | D25: ConceptScheme | E25: <http://vocab.belgif.be/auth/municipalitycode> | F25: MunicipalityCode | G25: NIS code gemeente | H25: Code commune NIS | I25: The conceptscheme "MunicipalityCode" contains municipalities represented by a NIS code. | J25: Het conceptschema "GemeenteCode" bevat gemeenten die worden weergegeven door een NIS-code. | K25: Le schéma de concepts "MunicipalityCode" contient des municipalités représentées par un code NIS. | O25: no
A26: 741 | B26: FED | C26: Location | D26: Property | E26: <identifier> | F26: bestIdentifier | G26: BEST identifier | H26: Identifiant BEST | I26: Identifier of a BEST address or a BEST address component. | J26: Identifier van een BEST-adres of een BEST-adrescomponent. | K26: Identifiant d'une adresse BEST ou d'un composant d'adresse BEST. | L26: BEST = Belgian Streets and Addresses, a standard for Belgian addresses and address components. Address component = Municipality, PostalInfo, PartOfMunicipality, Streetname A BEST identifier consists of a namespace, an object identifier and a version. | M26: BEST = Belgian Streets and Addresses, een standaard voor Belgische adressen en adrescomponenten. Adrescomponent = Gemeente, PostInfo, PartOfMunicipality, Straatnaam Een BEST-identifier bestaat uit een naamruimte, een object-identifier en een versie. | N26: BEST = Belgian Streets and Addresses, un standard pour les adresses et composants d'adresses belges. Composant d'adresse = Municipalité, PostalInfo, PartOfMunicipality, Streetname Un identifiant BEST se compose d'un espace de noms, d'un identifiant d'objet et d'une version. | O26: no
A27: 745 | B27: FED | C27: Other | D27: Property | E27: <http://vocab.belgif.be/ns/other#preferredLanguage> | F27: preferredLanguage | G27: Voorkeurtaal | H27: Langue préférée | I27: Language that an agent wants to use preferrably in his contacts with another agent. | J27: Taal die een agent bij voorkeur wil gebruiken in zijn contacten met een andere agent. | K27: Langue qu'un agent souhaite utiliser de préférence dans ses contacts avec un autre agent. | O27: no
A28: 748 | B28: FED | C28: Person | D28: Property | E28: <http://vocab.belgif.be/auth/community> | F28: community | G28: Gemeenschap | H28: Communauté | I28: Concept corresponding to a community code in Belgium. | J28: Concept dat overeenkomt met een gemeenschapscode in België. | K28: Concept correspondant à un code communautaire en Belgique. | L28: See CommunityCode | M28: Zie CommunityCode | N28: Voir CommunityCode | O28: no

Sheet ChangeLog
A1: Date | B1: CAUD | C1: Id | D1: StatusUpdate | E1: Name | F1: OldName | G1: Status | H1: Ontology | I1: Type | J1: Comment
A2: 45310 | B2: Add | C2: 732 | E2: =IF(OR(Table11[[#This Row],[CAUD]]="Add", Table11[[#This Row],[CAUD]]="Update"),VLOOKUP(Table11[[#This Row],[Id]],Table1[#All],2,),"") -> Nationality | G2: =IF(OR(Table11[[#This Row],[CAUD]]="Add", Table11[[#This Row],[CAUD]]="Update"),VLOOKUP(Table11[[#This Row],[Id]],Table6[#All],8,),"") -> Proposed standard | H2: =IF(OR(Table11[[#This Row],[CAUD]]="Add", Table11[[#This Row],[CAUD]]="Update"),VLOOKUP(Table11[[#This Row],[Id]],Table1[#All],4,),"") -> Location | I2: =IF(OR(Table11[[#This Row],[CAUD]]="Add", Table11[[#This Row],[CAUD]]="Update"),VLOOKUP(Table11[[#This Row],[Id]],Table1[#All],5,),"") -> ConceptScheme
A3: 45310 | B3: Add | C3: 733 | E3: Country | J3: Country has multiple ConceptScheme implementations.
A4: 45310 | B4: Comment | E4: =IF(OR(Table11[[#This Row],[CAUD]]="Add", Table11[[#This Row],[CAUD]]="Update"),VLOOKUP(Table11[[#This Row],[Id]],Table1[#All],2,),"") | G4: =IF(OR(Table11[[#This Row],[CAUD]]="Add", Table11[[#This Row],[CAUD]]="Update"),VLOOKUP(Table11[[#This Row],[Id]],Table6[#All],8,),"") | H4: =IF(OR(Table11[[#This Row],[CAUD]]="Add", Table11[[#This Row],[CAUD]]="Update"),VLOOKUP(Table11[[#This Row],[Id]],Table1[#All],4,),"") | I4: =IF(OR(Table11[[#This Row],[CAUD]]="Add", Table11[[#This Row],[CAUD]]="Update"),VLOOKUP(Table11[[#This Row],[Id]],Table1[#All],5,),"") | J4: Introduction of Datatypes + updated Datamodels sheet
A5: 45310 | B5: Delete | C5: 365 | E5: =IF(OR(Table11[[#This Row],[CAUD]]="Add", Table11[[#This Row],[CAUD]]="Update"),VLOOKUP(Table11[[#This Row],[Id]],Table1[#All],2,),"") | F5: TerritoryOfNationality | G5: =IF(OR(Table11[[#This Row],[CAUD]]="Add", Table11[[#This Row],[CAUD]]="Update"),VLOOKUP(Table11[[#This Row],[Id]],Table6[#All],8,),"") | H5: =IF(OR(Table11[[#This Row],[CAUD]]="Add", Table11[[#This Row],[CAUD]]="Update"),VLOOKUP(Table11[[#This Row],[Id]],Table1[#All],4,),"") | I5: =IF(OR(Table11[[#This Row],[CAUD]]="Add", Table11[[#This Row],[CAUD]]="Update"),VLOOKUP(Table11[[#This Row],[Id]],Table1[#All],5,),"")
A6: 45310 | B6: Delete | C6: 369 | E6: =IF(OR(Table11[[#This Row],[CAUD]]="Add", Table11[[#This Row],[CAUD]]="Update"),VLOOKUP(Table11[[#This Row],[Id]],Table1[#All],2,),"") | F6: TerritoryOfAddress | G6: =IF(OR(Table11[[#This Row],[CAUD]]="Add", Table11[[#This Row],[CAUD]]="Update"),VLOOKUP(Table11[[#This Row],[Id]],Table6[#All],8,),"") | H6: =IF(OR(Table11[[#This Row],[CAUD]]="Add", Table11[[#This Row],[CAUD]]="Update"),VLOOKUP(Table11[[#This Row],[Id]],Table1[#All],4,),"") | I6: =IF(OR(Table11[[#This Row],[CAUD]]="Add", Table11[[#This Row],[CAUD]]="Update"),VLOOKUP(Table11[[#This Row],[Id]],Table1[#All],5,),"")
A7: 45310 | B7: Delete | C7: 370 | E7: =IF(OR(Table11[[#This Row],[CAUD]]="Add", Table11[[#This Row],[CAUD]]="Update"),VLOOKUP(Table11[[#This Row],[Id]],Table1[#All],2,),"") | F7: TerritoryOfPlace | G7: =IF(OR(Table11[[#This Row],[CAUD]]="Add", Table11[[#This Row],[CAUD]]="Update"),VLOOKUP(Table11[[#This Row],[Id]],Table6[#All],8,),"") | H7: =IF(OR(Table11[[#This Row],[CAUD]]="Add", Table11[[#This Row],[CAUD]]="Update"),VLOOKUP(Table11[[#This Row],[Id]],Table1[#All],4,),"") | I7: =IF(OR(Table11[[#This Row],[CAUD]]="Add", Table11[[#This Row],[CAUD]]="Update"),VLOOKUP(Table11[[#This Row],[Id]],Table1[#All],5,),"")
A8: 45310 | B8: Delete | C8: 711 | E8: =IF(OR(Table11[[#This Row],[CAUD]]="Add", Table11[[#This Row],[CAUD]]="Update"),VLOOKUP(Table11[[#This Row],[Id]],Table1[#All],2,),"") | F8: countryNisCode | G8: =IF(OR(Table11[[#This Row],[CAUD]]="Add", Table11[[#This Row],[CAUD]]="Update"),VLOOKUP(Table11[[#This Row],[Id]],Table6[#All],8,),"") | H8: =IF(OR(Table11[[#This Row],[CAUD]]="Add", Table11[[#This Row],[CAUD]]="Update"),VLOOKUP(Table11[[#This Row],[Id]],Table1[#All],4,),"") | I8: =IF(OR(Table11[[#This Row],[CAUD]]="Add", Table11[[#This Row],[CAUD]]="Update"),VLOOKUP(Table11[[#This Row],[Id]],Table1[#All],5,),"") | J8: Replaced by 1 property named "country"
A9: 45310 | B9: Delete | C9: 712 | E9: =IF(OR(Table11[[#This Row],[CAUD]]="Add", Table11[[#This Row],[CAUD]]="Update"),VLOOKUP(Table11[[#This Row],[Id]],Table1[#All],2,),"") | F9: countryIsoCode | G9: =IF(OR(Table11[[#This Row],[CAUD]]="Add", Table11[[#This Row],[CAUD]]="Update"),VLOOKUP(Table11[[#This Row],[Id]],Table6[#All],8,),"") | H9: =IF(OR(Table11[[#This Row],[CAUD]]="Add", Table11[[#This Row],[CAUD]]="Update"),VLOOKUP(Table11[[#This Row],[Id]],Table1[#All],4,),"") | I9: =IF(OR(Table11[[#This Row],[CAUD]]="Add", Table11[[#This Row],[CAUD]]="Update"),VLOOKUP(Table11[[#This Row],[Id]],Table1[#All],5,),"") | J9: Replaced by 1 property named "country"
A10: 45310 | B10: Delete | C10: 714 | E10: =IF(OR(Table11[[#This Row],[CAUD]]="Add", Table11[[#This Row],[CAUD]]="Update"),VLOOKUP(Table11[[#This Row],[Id]],Table1[#All],2,),"") | F10: countryWithHistoryIsoCode | G10: =IF(OR(Table11[[#This Row],[CAUD]]="Add", Table11[[#This Row],[CAUD]]="Update"),VLOOKUP(Table11[[#This Row],[Id]],Table6[#All],8,),"") | H10: =IF(OR(Table11[[#This Row],[CAUD]]="Add", Table11[[#This Row],[CAUD]]="Update"),VLOOKUP(Table11[[#This Row],[Id]],Table1[#All],4,),"") | I10: =IF(OR(Table11[[#This Row],[CAUD]]="Add", Table11[[#This Row],[CAUD]]="Update"),VLOOKUP(Table11[[#This Row],[Id]],Table1[#All],5,),"") | J10: Replaced by 1 property named "country"
A11: 45310 | B11: Delete | C11: 717 | E11: =IF(OR(Table11[[#This Row],[CAUD]]="Add", Table11[[#This Row],[CAUD]]="Update"),VLOOKUP(Table11[[#This Row],[Id]],Table1[#All],2,),"") | F11: countryIsoAlpha3Code | G11: =IF(OR(Table11[[#This Row],[CAUD]]="Add", Table11[[#This Row],[CAUD]]="Update"),VLOOKUP(Table11[[#This Row],[Id]],Table6[#All],8,),"") | H11: =IF(OR(Table11[[#This Row],[CAUD]]="Add", Table11[[#This Row],[CAUD]]="Update"),VLOOKUP(Table11[[#This Row],[Id]],Table1[#All],4,),"") | I11: =IF(OR(Table11[[#This Row],[CAUD]]="Add", Table11[[#This Row],[CAUD]]="Update"),VLOOKUP(Table11[[#This Row],[Id]],Table1[#All],5,),"") | J11: Replaced by 1 property named "country"
A12: 45310 | B12: Delete | C12: 719 | E12: =IF(OR(Table11[[#This Row],[CAUD]]="Add", Table11[[#This Row],[CAUD]]="Update"),VLOOKUP(Table11[[#This Row],[Id]],Table1[#All],2,),"") | F12: countryIsoNum3Code | G12: =IF(OR(Table11[[#This Row],[CAUD]]="Add", Table11[[#This Row],[CAUD]]="Update"),VLOOKUP(Table11[[#This Row],[Id]],Table6[#All],8,),"") | H12: =IF(OR(Table11[[#This Row],[CAUD]]="Add", Table11[[#This Row],[CAUD]]="Update"),VLOOKUP(Table11[[#This Row],[Id]],Table1[#All],4,),"") | I12: =IF(OR(Table11[[#This Row],[CAUD]]="Add", Table11[[#This Row],[CAUD]]="Update"),VLOOKUP(Table11[[#This Row],[Id]],Table1[#All],5,),"") | J12: Replaced by 1 property named "country"
A13: 45310 | B13: Delete | C13: 732 | E13: =IF(OR(Table11[[#This Row],[CAUD]]="Add", Table11[[#This Row],[CAUD]]="Update"),VLOOKUP(Table11[[#This Row],[Id]],Table1[#All],2,),"") | F13: Territory | G13: =IF(OR(Table11[[#This Row],[CAUD]]="Add", Table11[[#This Row],[CAUD]]="Update"),VLOOKUP(Table11[[#This Row],[Id]],Table6[#All],8,),"") | H13: =IF(OR(Table11[[#This Row],[CAUD]]="Add", Table11[[#This Row],[CAUD]]="Update"),VLOOKUP(Table11[[#This Row],[Id]],Table1[#All],4,),"") | I13: =IF(OR(Table11[[#This Row],[CAUD]]="Add", Table11[[#This Row],[CAUD]]="Update"),VLOOKUP(Table11[[#This Row],[Id]],Table1[#All],5,),"")
A14: 45310 | B14: Update | C14: 701 | E14: =IF(OR(Table11[[#This Row],[CAUD]]="Add", Table11[[#This Row],[CAUD]]="Update"),VLOOKUP(Table11[[#This Row],[Id]],Table1[#All],2,),"") -> CountryNisCode | G14: =IF(OR(Table11[[#This Row],[CAUD]]="Add", Table11[[#This Row],[CAUD]]="Update"),VLOOKUP(Table11[[#This Row],[Id]],Table6[#All],8,),"") -> Proposed standard | H14: =IF(OR(Table11[[#This Row],[CAUD]]="Add", Table11[[#This Row],[CAUD]]="Update"),VLOOKUP(Table11[[#This Row],[Id]],Table1[#All],4,),"") -> Location | I14: =IF(OR(Table11[[#This Row],[CAUD]]="Add", Table11[[#This Row],[CAUD]]="Update"),VLOOKUP(Table11[[#This Row],[Id]],Table1[#All],5,),"") -> DataType | J14: Changed Type
A15: 45310 | B15: Update | C15: 707 | E15: =IF(OR(Table11[[#This Row],[CAUD]]="Add", Table11[[#This Row],[CAUD]]="Update"),VLOOKUP(Table11[[#This Row],[Id]],Table1[#All],2,),"") -> CountryIsoCode | G15: =IF(OR(Table11[[#This Row],[CAUD]]="Add", Table11[[#This Row],[CAUD]]="Update"),VLOOKUP(Table11[[#This Row],[Id]],Table6[#All],8,),"") -> Proposed standard | H15: =IF(OR(Table11[[#This Row],[CAUD]]="Add", Table11[[#This Row],[CAUD]]="Update"),VLOOKUP(Table11[[#This Row],[Id]],Table1[#All],4,),"") -> Location | I15: =IF(OR(Table11[[#This Row],[CAUD]]="Add", Table11[[#This Row],[CAUD]]="Update"),VLOOKUP(Table11[[#This Row],[Id]],Table1[#All],5,),"") -> DataType | J15: Changed Type
A16: 45310 | B16: Update | C16: 708 | E16: =IF(OR(Table11[[#This Row],[CAUD]]="Add", Table11[[#This Row],[CAUD]]="Update"),VLOOKUP(Table11[[#This Row],[Id]],Table1[#All],2,),"") -> CountryWithHistoricIsoCode | G16: =IF(OR(Table11[[#This Row],[CAUD]]="Add", Table11[[#This Row],[CAUD]]="Update"),VLOOKUP(Table11[[#This Row],[Id]],Table6[#All],8,),"") -> Proposed standard | H16: =IF(OR(Table11[[#This Row],[CAUD]]="Add", Table11[[#This Row],[CAUD]]="Update"),VLOOKUP(Table11[[#This Row],[Id]],Table1[#All],4,),"") -> Location | I16: =IF(OR(Table11[[#This Row],[CAUD]]="Add", Table11[[#This Row],[CAUD]]="Update"),VLOOKUP(Table11[[#This Row],[Id]],Table1[#All],5,),"") -> DataType | J16: Changed Type
A17: 45310 | B17: Update | C17: 716 | E17: =IF(OR(Table11[[#This Row],[CAUD]]="Add", Table11[[#This Row],[CAUD]]="Update"),VLOOKUP(Table11[[#This Row],[Id]],Table1[#All],2,),"") -> CountryIsoAlpha3Code | G17: =IF(OR(Table11[[#This Row],[CAUD]]="Add", Table11[[#This Row],[CAUD]]="Update"),VLOOKUP(Table11[[#This Row],[Id]],Table6[#All],8,),"") -> Proposed standard | H17: =IF(OR(Table11[[#This Row],[CAUD]]="Add", Table11[[#This Row],[CAUD]]="Update"),VLOOKUP(Table11[[#This Row],[Id]],Table1[#All],4,),"") -> Location | I17: =IF(OR(Table11[[#This Row],[CAUD]]="Add", Table11[[#This Row],[CAUD]]="Update"),VLOOKUP(Table11[[#This Row],[Id]],Table1[#All],5,),"") -> DataType | J17: Changed Type
A18: 45310 | B18: Update | C18: 718 | E18: =IF(OR(Table11[[#This Row],[CAUD]]="Add", Table11[[#This Row],[CAUD]]="Update"),VLOOKUP(Table11[[#This Row],[Id]],Table1[#All],2,),"") -> CountryIsoNum3Code | G18: =IF(OR(Table11[[#This Row],[CAUD]]="Add", Table11[[#This Row],[CAUD]]="Update"),VLOOKUP(Table11[[#This Row],[Id]],Table6[#All],8,),"") -> Proposed standard | H18: =IF(OR(Table11[[#This Row],[CAUD]]="Add", Table11[[#This Row],[CAUD]]="Update"),VLOOKUP(Table11[[#This Row],[Id]],Table1[#All],4,),"") -> Location | I18: =IF(OR(Table11[[#This Row],[CAUD]]="Add", Table11[[#This Row],[CAUD]]="Update"),VLOOKUP(Table11[[#This Row],[Id]],Table1[#All],5,),"") -> DataType | J18: Changed Type
A19: 45310 | B19: Update | C19: 729 | E19: =IF(OR(Table11[[#This Row],[CAUD]]="Add", Table11[[#This Row],[CAUD]]="Update"),VLOOKUP(Table11[[#This Row],[Id]],Table1[#All],2,),"") -> country | G19: =IF(OR(Table11[[#This Row],[CAUD]]="Add", Table11[[#This Row],[CAUD]]="Update"),VLOOKUP(Table11[[#This Row],[Id]],Table6[#All],8,),"") -> Proposed standard | H19: =IF(OR(Table11[[#This Row],[CAUD]]="Add", Table11[[#This Row],[CAUD]]="Update"),VLOOKUP(Table11[[#This Row],[Id]],Table1[#All],4,),"") -> Location | I19: =IF(OR(Table11[[#This Row],[CAUD]]="Add", Table11[[#This Row],[CAUD]]="Update"),VLOOKUP(Table11[[#This Row],[Id]],Table1[#All],5,),"") -> Property | J19: Refers to multiple ConceptScheme implementations.
A20: 45198 | B20: Update | C20: 298 | E20: =IF(OR(Table11[[#This Row],[CAUD]]="Add", Table11[[#This Row],[CAUD]]="Update"),VLOOKUP(Table11[[#This Row],[Id]],Table1[#All],2,),"") -> boxNumber | G20: =IF(OR(Table11[[#This Row],[CAUD]]="Add", Table11[[#This Row],[CAUD]]="Update"),VLOOKUP(Table11[[#This Row],[Id]],Table6[#All],8,),"") -> Proposed standard | H20: =IF(OR(Table11[[#This Row],[CAUD]]="Add", Table11[[#This Row],[CAUD]]="Update"),VLOOKUP(Table11[[#This Row],[Id]],Table1[#All],4,),"") -> Location | I20: =IF(OR(Table11[[#This Row],[CAUD]]="Add", Table11[[#This Row],[CAUD]]="Update"),VLOOKUP(Table11[[#This Row],[Id]],Table1[#All],5,),"") -> Property | J20: URI aligned with Europe.
A21: 45198 | B21: Update | C21: 731 | E21: =IF(OR(Table11[[#This Row],[CAUD]]="Add", Table11[[#This Row],[CAUD]]="Update"),VLOOKUP(Table11[[#This Row],[Id]],Table1[#All],2,),"") -> remittanceInformation | G21: =IF(OR(Table11[[#This Row],[CAUD]]="Add", Table11[[#This Row],[CAUD]]="Update"),VLOOKUP(Table11[[#This Row],[Id]],Table6[#All],8,),"") -> Proposed standard | H21: =IF(OR(Table11[[#This Row],[CAUD]]="Add", Table11[[#This Row],[CAUD]]="Update"),VLOOKUP(Table11[[#This Row],[Id]],Table1[#All],4,),"") -> Generic | I21: =IF(OR(Table11[[#This Row],[CAUD]]="Add", Table11[[#This Row],[CAUD]]="Update"),VLOOKUP(Table11[[#This Row],[Id]],Table1[#All],5,),"") -> Property
A22: 45086 | B22: Add | C22: 730 | D22: Yes | E22: =IF(OR(Table11[[#This Row],[CAUD]]="Add", Table11[[#This Row],[CAUD]]="Update"),VLOOKUP(Table11[[#This Row],[Id]],Table1[#All],2,),"") -> Language | G22: =IF(OR(Table11[[#This Row],[CAUD]]="Add", Table11[[#This Row],[CAUD]]="Update"),VLOOKUP(Table11[[#This Row],[Id]],Table6[#All],8,),"") -> Standard | H22: =IF(OR(Table11[[#This Row],[CAUD]]="Add", Table11[[#This Row],[CAUD]]="Update"),VLOOKUP(Table11[[#This Row],[Id]],Table1[#All],4,),"") -> Generic | I22: =IF(OR(Table11[[#This Row],[CAUD]]="Add", Table11[[#This Row],[CAUD]]="Update"),VLOOKUP(Table11[[#This Row],[Id]],Table1[#All],5,),"") -> ConceptScheme | J22: Draft to Standard.
A23: 45086 | B23: Comment | E23: =IF(OR(Table11[[#This Row],[CAUD]]="Add", Table11[[#This Row],[CAUD]]="Update"),VLOOKUP(Table11[[#This Row],[Id]],Table1[#All],2,),"") | G23: =IF(OR(Table11[[#This Row],[CAUD]]="Add", Table11[[#This Row],[CAUD]]="Update"),VLOOKUP(Table11[[#This Row],[Id]],Table6[#All],8,),"") | H23: =IF(OR(Table11[[#This Row],[CAUD]]="Add", Table11[[#This Row],[CAUD]]="Update"),VLOOKUP(Table11[[#This Row],[Id]],Table1[#All],4,),"") | I23: =IF(OR(Table11[[#This Row],[CAUD]]="Add", Table11[[#This Row],[CAUD]]="Update"),VLOOKUP(Table11[[#This Row],[Id]],Table1[#All],5,),"") | J23: New column "Publish YN" + rename column inSwagger to inOpenApi
A24: 45086 | B24: Update | C24: 362 | E24: =IF(OR(Table11[[#This Row],[CAUD]]="Add", Table11[[#This Row],[CAUD]]="Update"),VLOOKUP(Table11[[#This Row],[Id]],Table1[#All],2,),"") -> CivilStatusType | G24: =IF(OR(Table11[[#This Row],[CAUD]]="Add", Table11[[#This Row],[CAUD]]="Update"),VLOOKUP(Table11[[#This Row],[Id]],Table6[#All],8,),"") -> Proposed standard | H24: =IF(OR(Table11[[#This Row],[CAUD]]="Add", Table11[[#This Row],[CAUD]]="Update"),VLOOKUP(Table11[[#This Row],[Id]],Table1[#All],4,),"") -> Person | I24: =IF(OR(Table11[[#This Row],[CAUD]]="Add", Table11[[#This Row],[CAUD]]="Update"),VLOOKUP(Table11[[#This Row],[Id]],Table1[#All],5,),"") -> ConceptScheme
A25: 45086 | B25: Update | C25: 366 | E25: =IF(OR(Table11[[#This Row],[CAUD]]="Add", Table11[[#This Row],[CAUD]]="Update"),VLOOKUP(Table11[[#This Row],[Id]],Table1[#All],2,),"") -> HouseholdRelationType | G25: =IF(OR(Table11[[#This Row],[CAUD]]="Add", Table11[[#This Row],[CAUD]]="Update"),VLOOKUP(Table11[[#This Row],[Id]],Table6[#All],8,),"") -> Proposed standard | H25: =IF(OR(Table11[[#This Row],[CAUD]]="Add", Table11[[#This Row],[CAUD]]="Update"),VLOOKUP(Table11[[#This Row],[Id]],Table1[#All],4,),"") -> Person | I25: =IF(OR(Table11[[#This Row],[CAUD]]="Add", Table11[[#This Row],[CAUD]]="Update"),VLOOKUP(Table11[[#This Row],[Id]],Table1[#All],5,),"") -> ConceptScheme
A26: 45086 | B26: Update | C26: 702 | E26: =IF(OR(Table11[[#This Row],[CAUD]]="Add", Table11[[#This Row],[CAUD]]="Update"),VLOOKUP(Table11[[#This Row],[Id]],Table1[#All],2,),"") -> StreetRrnCode | G26: =IF(OR(Table11[[#This Row],[CAUD]]="Add", Table11[[#This Row],[CAUD]]="Update"),VLOOKUP(Table11[[#This Row],[Id]],Table6[#All],8,),"") -> Proposed standard | H26: =IF(OR(Table11[[#This Row],[CAUD]]="Add", Table11[[#This Row],[CAUD]]="Update"),VLOOKUP(Table11[[#This Row],[Id]],Table1[#All],4,),"") -> Location | I26: =IF(OR(Table11[[#This Row],[CAUD]]="Add", Table11[[#This Row],[CAUD]]="Update"),VLOOKUP(Table11[[#This Row],[Id]],Table1[#All],5,),"") -> DataType
A27: 45086 | B27: Update | C27: 722 | E27: =IF(OR(Table11[[#This Row],[CAUD]]="Add", Table11[[#This Row],[CAUD]]="Update"),VLOOKUP(Table11[[#This Row],[Id]],Table1[#All],2,),"") -> Currency | G27: =IF(OR(Table11[[#This Row],[CAUD]]="Add", Table11[[#This Row],[CAUD]]="Update"),VLOOKUP(Table11[[#This Row],[Id]],Table6[#All],8,),"") -> Proposed standard | H27: =IF(OR(Table11[[#This Row],[CAUD]]="Add", Table11[[#This Row],[CAUD]]="Update"),VLOOKUP(Table11[[#This Row],[Id]],Table1[#All],4,),"") -> Generic | I27: =IF(OR(Table11[[#This Row],[CAUD]]="Add", Table11[[#This Row],[CAUD]]="Update"),VLOOKUP(Table11[[#This Row],[Id]],Table1[#All],5,),"") -> ConceptScheme
A28: 45086 | B28: Update | C28: 724 | E28: =IF(OR(Table11[[#This Row],[CAUD]]="Add", Table11[[#This Row],[CAUD]]="Update"),VLOOKUP(Table11[[#This Row],[Id]],Table1[#All],2,),"") -> MonetaryAmount | G28: =IF(OR(Table11[[#This Row],[CAUD]]="Add", Table11[[#This Row],[CAUD]]="Update"),VLOOKUP(Table11[[#This Row],[Id]],Table6[#All],8,),"") -> Proposed standard | H28: =IF(OR(Table11[[#This Row],[CAUD]]="Add", Table11[[#This Row],[CAUD]]="Update"),VLOOKUP(Table11[[#This Row],[Id]],Table1[#All],4,),"") -> Generic | I28: =IF(OR(Table11[[#This Row],[CAUD]]="Add", Table11[[#This Row],[CAUD]]="Update"),VLOOKUP(Table11[[#This Row],[Id]],Table1[#All],5,),"") -> Class
A29: 44987 | B29: Update | C29: 362 | E29: =IF(OR(Table11[[#This Row],[CAUD]]="Add", Table11[[#This Row],[CAUD]]="Update"),VLOOKUP(Table11[[#This Row],[Id]],Table1[#All],2,),"") -> CivilStatusType | F29: CivilState | G29: =IF(OR(Table11[[#This Row],[CAUD]]="Add", Table11[[#This Row],[CAUD]]="Update"),VLOOKUP(Table11[[#This Row],[Id]],Table6[#All],8,),"") -> Proposed standard | H29: =IF(OR(Table11[[#This Row],[CAUD]]="Add", Table11[[#This Row],[CAUD]]="Update"),VLOOKUP(Table11[[#This Row],[Id]],Table1[#All],4,),"") -> Person | I29: =IF(OR(Table11[[#This Row],[CAUD]]="Add", Table11[[#This Row],[CAUD]]="Update"),VLOOKUP(Table11[[#This Row],[Id]],Table1[#All],5,),"") -> ConceptScheme
A30: 44987 | B30: Update | C30: 730 | E30: =IF(OR(Table11[[#This Row],[CAUD]]="Add", Table11[[#This Row],[CAUD]]="Update"),VLOOKUP(Table11[[#This Row],[Id]],Table1[#All],2,),"") -> Language | G30: =IF(OR(Table11[[#This Row],[CAUD]]="Add", Table11[[#This Row],[CAUD]]="Update"),VLOOKUP(Table11[[#This Row],[Id]],Table6[#All],8,),"") -> Standard | H30: =IF(OR(Table11[[#This Row],[CAUD]]="Add", Table11[[#This Row],[CAUD]]="Update"),VLOOKUP(Table11[[#This Row],[Id]],Table1[#All],4,),"") -> Generic | I30: =IF(OR(Table11[[#This Row],[CAUD]]="Add", Table11[[#This Row],[CAUD]]="Update"),VLOOKUP(Table11[[#This Row],[Id]],Table1[#All],5,),"") -> ConceptScheme
A31: 45397 | B31: Update | C31: 695 | E31: =IF(OR(Table11[[#This Row],[CAUD]]="Add", Table11[[#This Row],[CAUD]]="Update"),VLOOKUP(Table11[[#This Row],[Id]],Table1[#All],2,),"") -> vatNumber | G31: =IF(OR(Table11[[#This Row],[CAUD]]="Add", Table11[[#This Row],[CAUD]]="Update"),VLOOKUP(Table11[[#This Row],[Id]],Table6[#All],8,),"") -> Proposed standard | H31: =IF(OR(Table11[[#This Row],[CAUD]]="Add", Table11[[#This Row],[CAUD]]="Update"),VLOOKUP(Table11[[#This Row],[Id]],Table1[#All],4,),"") -> Organization | I31: =IF(OR(Table11[[#This Row],[CAUD]]="Add", Table11[[#This Row],[CAUD]]="Update"),VLOOKUP(Table11[[#This Row],[Id]],Table1[#All],5,),"") -> Property
A32: 45397 | B32: Delete | C32: 364 | E32: Nace2008 | G32: =IF(OR(Table11[[#This Row],[CAUD]]="Add", Table11[[#This Row],[CAUD]]="Update"),VLOOKUP(Table11[[#This Row],[Id]],Table6[#All],8,),"") | H32: =IF(OR(Table11[[#This Row],[CAUD]]="Add", Table11[[#This Row],[CAUD]]="Update"),VLOOKUP(Table11[[#This Row],[Id]],Table1[#All],4,),"") | I32: =IF(OR(Table11[[#This Row],[CAUD]]="Add", Table11[[#This Row],[CAUD]]="Update"),VLOOKUP(Table11[[#This Row],[Id]],Table1[#All],5,),"")
A33: 45397 | B33: Delete | C33: 700 | E33: nace2008 | G33: =IF(OR(Table11[[#This Row],[CAUD]]="Add", Table11[[#This Row],[CAUD]]="Update"),VLOOKUP(Table11[[#This Row],[Id]],Table6[#All],8,),"") | H33: =IF(OR(Table11[[#This Row],[CAUD]]="Add", Table11[[#This Row],[CAUD]]="Update"),VLOOKUP(Table11[[#This Row],[Id]],Table1[#All],4,),"") | I33: =IF(OR(Table11[[#This Row],[CAUD]]="Add", Table11[[#This Row],[CAUD]]="Update"),VLOOKUP(Table11[[#This Row],[Id]],Table1[#All],5,),"")
A34: 45397 | B34: Add | C34: 734 | E34: =IF(OR(Table11[[#This Row],[CAUD]]="Add", Table11[[#This Row],[CAUD]]="Update"),VLOOKUP(Table11[[#This Row],[Id]],Table1[#All],2,),"") -> NaceEuRev2 | G34: =IF(OR(Table11[[#This Row],[CAUD]]="Add", Table11[[#This Row],[CAUD]]="Update"),VLOOKUP(Table11[[#This Row],[Id]],Table6[#All],8,),"") -> Proposed standard | H34: =IF(OR(Table11[[#This Row],[CAUD]]="Add", Table11[[#This Row],[CAUD]]="Update"),VLOOKUP(Table11[[#This Row],[Id]],Table1[#All],4,),"") -> Organization | I34: =IF(OR(Table11[[#This Row],[CAUD]]="Add", Table11[[#This Row],[CAUD]]="Update"),VLOOKUP(Table11[[#This Row],[Id]],Table1[#All],5,),"") -> ConceptScheme
A35: 45397 | B35: Add | C35: 735 | E35: =IF(OR(Table11[[#This Row],[CAUD]]="Add", Table11[[#This Row],[CAUD]]="Update"),VLOOKUP(Table11[[#This Row],[Id]],Table1[#All],2,),"") -> NaceEuRev2_1 | G35: =IF(OR(Table11[[#This Row],[CAUD]]="Add", Table11[[#This Row],[CAUD]]="Update"),VLOOKUP(Table11[[#This Row],[Id]],Table6[#All],8,),"") -> Proposed standard | H35: =IF(OR(Table11[[#This Row],[CAUD]]="Add", Table11[[#This Row],[CAUD]]="Update"),VLOOKUP(Table11[[#This Row],[Id]],Table1[#All],4,),"") -> Organization | I35: =IF(OR(Table11[[#This Row],[CAUD]]="Add", Table11[[#This Row],[CAUD]]="Update"),VLOOKUP(Table11[[#This Row],[Id]],Table1[#All],5,),"") -> ConceptScheme
A36: 45397 | B36: Add | C36: 736 | E36: =IF(OR(Table11[[#This Row],[CAUD]]="Add", Table11[[#This Row],[CAUD]]="Update"),VLOOKUP(Table11[[#This Row],[Id]],Table1[#All],2,),"") -> NaceBel2008 | G36: =IF(OR(Table11[[#This Row],[CAUD]]="Add", Table11[[#This Row],[CAUD]]="Update"),VLOOKUP(Table11[[#This Row],[Id]],Table6[#All],8,),"") -> Proposed standard | H36: =IF(OR(Table11[[#This Row],[CAUD]]="Add", Table11[[#This Row],[CAUD]]="Update"),VLOOKUP(Table11[[#This Row],[Id]],Table1[#All],4,),"") -> Organization | I36: =IF(OR(Table11[[#This Row],[CAUD]]="Add", Table11[[#This Row],[CAUD]]="Update"),VLOOKUP(Table11[[#This Row],[Id]],Table1[#All],5,),"") -> ConceptScheme
A37: 45397 | B37: Add | C37: 737 | E37: =IF(OR(Table11[[#This Row],[CAUD]]="Add", Table11[[#This Row],[CAUD]]="Update"),VLOOKUP(Table11[[#This Row],[Id]],Table1[#All],2,),"") -> NaceRev2Code | G37: =IF(OR(Table11[[#This Row],[CAUD]]="Add", Table11[[#This Row],[CAUD]]="Update"),VLOOKUP(Table11[[#This Row],[Id]],Table6[#All],8,),"") -> Proposed standard | H37: =IF(OR(Table11[[#This Row],[CAUD]]="Add", Table11[[#This Row],[CAUD]]="Update"),VLOOKUP(Table11[[#This Row],[Id]],Table1[#All],4,),"") -> Organization | I37: =IF(OR(Table11[[#This Row],[CAUD]]="Add", Table11[[#This Row],[CAUD]]="Update"),VLOOKUP(Table11[[#This Row],[Id]],Table1[#All],5,),"") -> DataType
A38: 45397 | B38: Add | C38: 738 | E38: =IF(OR(Table11[[#This Row],[CAUD]]="Add", Table11[[#This Row],[CAUD]]="Update"),VLOOKUP(Table11[[#This Row],[Id]],Table1[#All],2,),"") -> NaceBel2008Code | G38: =IF(OR(Table11[[#This Row],[CAUD]]="Add", Table11[[#This Row],[CAUD]]="Update"),VLOOKUP(Table11[[#This Row],[Id]],Table6[#All],8,),"") -> Proposed standard | H38: =IF(OR(Table11[[#This Row],[CAUD]]="Add", Table11[[#This Row],[CAUD]]="Update"),VLOOKUP(Table11[[#This Row],[Id]],Table1[#All],4,),"") -> Organization | I38: =IF(OR(Table11[[#This Row],[CAUD]]="Add", Table11[[#This Row],[CAUD]]="Update"),VLOOKUP(Table11[[#This Row],[Id]],Table1[#All],5,),"") -> DataType
A39: 45397 | B39: Add | C39: 739 | E39: =IF(OR(Table11[[#This Row],[CAUD]]="Add", Table11[[#This Row],[CAUD]]="Update"),VLOOKUP(Table11[[#This Row],[Id]],Table1[#All],2,),"") -> NaceBel2008Length5Code | G39: =IF(OR(Table11[[#This Row],[CAUD]]="Add", Table11[[#This Row],[CAUD]]="Update"),VLOOKUP(Table11[[#This Row],[Id]],Table6[#All],8,),"") -> Proposed standard | H39: =IF(OR(Table11[[#This Row],[CAUD]]="Add", Table11[[#This Row],[CAUD]]="Update"),VLOOKUP(Table11[[#This Row],[Id]],Table1[#All],4,),"") -> Organization | I39: =IF(OR(Table11[[#This Row],[CAUD]]="Add", Table11[[#This Row],[CAUD]]="Update"),VLOOKUP(Table11[[#This Row],[Id]],Table1[#All],5,),"") -> DataType
A40: 45397 | B40: Add | C40: 740 | E40: =IF(OR(Table11[[#This Row],[CAUD]]="Add", Table11[[#This Row],[CAUD]]="Update"),VLOOKUP(Table11[[#This Row],[Id]],Table1[#All],2,),"") -> nihdiNumber | G40: =IF(OR(Table11[[#This Row],[CAUD]]="Add", Table11[[#This Row],[CAUD]]="Update"),VLOOKUP(Table11[[#This Row],[Id]],Table6[#All],8,),"") -> Proposed standard | H40: =IF(OR(Table11[[#This Row],[CAUD]]="Add", Table11[[#This Row],[CAUD]]="Update"),VLOOKUP(Table11[[#This Row],[Id]],Table1[#All],4,),"") -> Healthcare | I40: =IF(OR(Table11[[#This Row],[CAUD]]="Add", Table11[[#This Row],[CAUD]]="Update"),VLOOKUP(Table11[[#This Row],[Id]],Table1[#All],5,),"") -> Property
A41: 45397 | B41: Update | C41: 303 | E41: =IF(OR(Table11[[#This Row],[CAUD]]="Add", Table11[[#This Row],[CAUD]]="Update"),VLOOKUP(Table11[[#This Row],[Id]],Table1[#All],2,),"") -> postCode | G41: =IF(OR(Table11[[#This Row],[CAUD]]="Add", Table11[[#This Row],[CAUD]]="Update"),VLOOKUP(Table11[[#This Row],[Id]],Table6[#All],8,),"") -> Proposed standard | H41: =IF(OR(Table11[[#This Row],[CAUD]]="Add", Table11[[#This Row],[CAUD]]="Update"),VLOOKUP(Table11[[#This Row],[Id]],Table1[#All],4,),"") -> Location | I41: =IF(OR(Table11[[#This Row],[CAUD]]="Add", Table11[[#This Row],[CAUD]]="Update"),VLOOKUP(Table11[[#This Row],[Id]],Table1[#All],5,),"") -> Property
A42: 45397 | B42: Delete | C42: 733 | E42: Country | G42: =IF(OR(Table11[[#This Row],[CAUD]]="Add", Table11[[#This Row],[CAUD]]="Update"),VLOOKUP(Table11[[#This Row],[Id]],Table6[#All],8,),"") | H42: =IF(OR(Table11[[#This Row],[CAUD]]="Add", Table11[[#This Row],[CAUD]]="Update"),VLOOKUP(Table11[[#This Row],[Id]],Table1[#All],4,),"") | I42: =IF(OR(Table11[[#This Row],[CAUD]]="Add", Table11[[#This Row],[CAUD]]="Update"),VLOOKUP(Table11[[#This Row],[Id]],Table1[#All],5,),"")
A43: 45471 | B43: Add | C43: 741 | E43: =IF(OR(Table11[[#This Row],[CAUD]]="Add", Table11[[#This Row],[CAUD]]="Update"),VLOOKUP(Table11[[#This Row],[Id]],Table1[#All],2,),"") -> bestIdentifier | G43: =IF(OR(Table11[[#This Row],[CAUD]]="Add", Table11[[#This Row],[CAUD]]="Update"),VLOOKUP(Table11[[#This Row],[Id]],Table6[#All],8,),"") -> Draft | H43: =IF(OR(Table11[[#This Row],[CAUD]]="Add", Table11[[#This Row],[CAUD]]="Update"),VLOOKUP(Table11[[#This Row],[Id]],Table1[#All],4,),"") -> Location | I43: =IF(OR(Table11[[#This Row],[CAUD]]="Add", Table11[[#This Row],[CAUD]]="Update"),VLOOKUP(Table11[[#This Row],[Id]],Table1[#All],5,),"") -> Property
A44: 45471 | B44: Add | C44: 742 | E44: =IF(OR(Table11[[#This Row],[CAUD]]="Add", Table11[[#This Row],[CAUD]]="Update"),VLOOKUP(Table11[[#This Row],[Id]],Table1[#All],2,),"") -> BelgianPostCode | G44: =IF(OR(Table11[[#This Row],[CAUD]]="Add", Table11[[#This Row],[CAUD]]="Update"),VLOOKUP(Table11[[#This Row],[Id]],Table6[#All],8,),"") -> Standard | H44: =IF(OR(Table11[[#This Row],[CAUD]]="Add", Table11[[#This Row],[CAUD]]="Update"),VLOOKUP(Table11[[#This Row],[Id]],Table1[#All],4,),"") -> Location | I44: =IF(OR(Table11[[#This Row],[CAUD]]="Add", Table11[[#This Row],[CAUD]]="Update"),VLOOKUP(Table11[[#This Row],[Id]],Table1[#All],5,),"") -> DataType
A45: 45471 | B45: Update | C45: 303 | E45: =IF(OR(Table11[[#This Row],[CAUD]]="Add", Table11[[#This Row],[CAUD]]="Update"),VLOOKUP(Table11[[#This Row],[Id]],Table1[#All],2,),"") -> postCode | G45: =IF(OR(Table11[[#This Row],[CAUD]]="Add", Table11[[#This Row],[CAUD]]="Update"),VLOOKUP(Table11[[#This Row],[Id]],Table6[#All],8,),"") -> Proposed standard | H45: =IF(OR(Table11[[#This Row],[CAUD]]="Add", Table11[[#This Row],[CAUD]]="Update"),VLOOKUP(Table11[[#This Row],[Id]],Table1[#All],4,),"") -> Location | I45: =IF(OR(Table11[[#This Row],[CAUD]]="Add", Table11[[#This Row],[CAUD]]="Update"),VLOOKUP(Table11[[#This Row],[Id]],Table1[#All],5,),"") -> Property
A46: 45471 | B46: Update | C46: 734 | E46: =IF(OR(Table11[[#This Row],[CAUD]]="Add", Table11[[#This Row],[CAUD]]="Update"),VLOOKUP(Table11[[#This Row],[Id]],Table1[#All],2,),"") -> NaceEuRev2 | G46: =IF(OR(Table11[[#This Row],[CAUD]]="Add", Table11[[#This Row],[CAUD]]="Update"),VLOOKUP(Table11[[#This Row],[Id]],Table6[#All],8,),"") -> Proposed standard | H46: =IF(OR(Table11[[#This Row],[CAUD]]="Add", Table11[[#This Row],[CAUD]]="Update"),VLOOKUP(Table11[[#This Row],[Id]],Table1[#All],4,),"") -> Organization | I46: =IF(OR(Table11[[#This Row],[CAUD]]="Add", Table11[[#This Row],[CAUD]]="Update"),VLOOKUP(Table11[[#This Row],[Id]],Table1[#All],5,),"") -> ConceptScheme
A47: 45471 | B47: Update | C47: 735 | E47: =IF(OR(Table11[[#This Row],[CAUD]]="Add", Table11[[#This Row],[CAUD]]="Update"),VLOOKUP(Table11[[#This Row],[Id]],Table1[#All],2,),"") -> NaceEuRev2_1 | G47: =IF(OR(Table11[[#This Row],[CAUD]]="Add", Table11[[#This Row],[CAUD]]="Update"),VLOOKUP(Table11[[#This Row],[Id]],Table6[#All],8,),"") -> Proposed standard | H47: =IF(OR(Table11[[#This Row],[CAUD]]="Add", Table11[[#This Row],[CAUD]]="Update"),VLOOKUP(Table11[[#This Row],[Id]],Table1[#All],4,),"") -> Organization | I47: =IF(OR(Table11[[#This Row],[CAUD]]="Add", Table11[[#This Row],[CAUD]]="Update"),VLOOKUP(Table11[[#This Row],[Id]],Table1[#All],5,),"") -> ConceptScheme
A48: 45471 | B48: Update | C48: 736 | E48: =IF(OR(Table11[[#This Row],[CAUD]]="Add", Table11[[#This Row],[CAUD]]="Update"),VLOOKUP(Table11[[#This Row],[Id]],Table1[#All],2,),"") -> NaceBel2008 | G48: =IF(OR(Table11[[#This Row],[CAUD]]="Add", Table11[[#This Row],[CAUD]]="Update"),VLOOKUP(Table11[[#This Row],[Id]],Table6[#All],8,),"") -> Proposed standard | H48: =IF(OR(Table11[[#This Row],[CAUD]]="Add", Table11[[#This Row],[CAUD]]="Update"),VLOOKUP(Table11[[#This Row],[Id]],Table1[#All],4,),"") -> Organization | I48: =IF(OR(Table11[[#This Row],[CAUD]]="Add", Table11[[#This Row],[CAUD]]="Update"),VLOOKUP(Table11[[#This Row],[Id]],Table1[#All],5,),"") -> ConceptScheme
A49: 45471 | B49: Update | C49: 737 | E49: =IF(OR(Table11[[#This Row],[CAUD]]="Add", Table11[[#This Row],[CAUD]]="Update"),VLOOKUP(Table11[[#This Row],[Id]],Table1[#All],2,),"") -> NaceRev2Code | G49: =IF(OR(Table11[[#This Row],[CAUD]]="Add", Table11[[#This Row],[CAUD]]="Update"),VLOOKUP(Table11[[#This Row],[Id]],Table6[#All],8,),"") -> Proposed standard | H49: =IF(OR(Table11[[#This Row],[CAUD]]="Add", Table11[[#This Row],[CAUD]]="Update"),VLOOKUP(Table11[[#This Row],[Id]],Table1[#All],4,),"") -> Organization | I49: =IF(OR(Table11[[#This Row],[CAUD]]="Add", Table11[[#This Row],[CAUD]]="Update"),VLOOKUP(Table11[[#This Row],[Id]],Table1[#All],5,),"") -> DataType
A50: 45471 | B50: Update | C50: 738 | E50: =IF(OR(Table11[[#This Row],[CAUD]]="Add", Table11[[#This Row],[CAUD]]="Update"),VLOOKUP(Table11[[#This Row],[Id]],Table1[#All],2,),"") -> NaceBel2008Code | G50: =IF(OR(Table11[[#This Row],[CAUD]]="Add", Table11[[#This Row],[CAUD]]="Update"),VLOOKUP(Table11[[#This Row],[Id]],Table6[#All],8,),"") -> Proposed standard | H50: =IF(OR(Table11[[#This Row],[CAUD]]="Add", Table11[[#This Row],[CAUD]]="Update"),VLOOKUP(Table11[[#This Row],[Id]],Table1[#All],4,),"") -> Organization | I50: =IF(OR(Table11[[#This Row],[CAUD]]="Add", Table11[[#This Row],[CAUD]]="Update"),VLOOKUP(Table11[[#This Row],[Id]],Table1[#All],5,),"") -> DataType
A51: 45471 | B51: Update | C51: 739 | E51: =IF(OR(Table11[[#This Row],[CAUD]]="Add", Table11[[#This Row],[CAUD]]="Update"),VLOOKUP(Table11[[#This Row],[Id]],Table1[#All],2,),"") -> NaceBel2008Length5Code | G51: =IF(OR(Table11[[#This Row],[CAUD]]="Add", Table11[[#This Row],[CAUD]]="Update"),VLOOKUP(Table11[[#This Row],[Id]],Table6[#All],8,),"") -> Proposed standard | H51: =IF(OR(Table11[[#This Row],[CAUD]]="Add", Table11[[#This Row],[CAUD]]="Update"),VLOOKUP(Table11[[#This Row],[Id]],Table1[#All],4,),"") -> Organization | I51: =IF(OR(Table11[[#This Row],[CAUD]]="Add", Table11[[#This Row],[CAUD]]="Update"),VLOOKUP(Table11[[#This Row],[Id]],Table1[#All],5,),"") -> DataType
A52: 45471 | B52: Update | C52: 740 | E52: =IF(OR(Table11[[#This Row],[CAUD]]="Add", Table11[[#This Row],[CAUD]]="Update"),VLOOKUP(Table11[[#This Row],[Id]],Table1[#All],2,),"") -> nihdiNumber | G52: =IF(OR(Table11[[#This Row],[CAUD]]="Add", Table11[[#This Row],[CAUD]]="Update"),VLOOKUP(Table11[[#This Row],[Id]],Table6[#All],8,),"") -> Proposed standard | H52: =IF(OR(Table11[[#This Row],[CAUD]]="Add", Table11[[#This Row],[CAUD]]="Update"),VLOOKUP(Table11[[#This Row],[Id]],Table1[#All],4,),"") -> Healthcare | I52: =IF(OR(Table11[[#This Row],[CAUD]]="Add", Table11[[#This Row],[CAUD]]="Update"),VLOOKUP(Table11[[#This Row],[Id]],Table1[#All],5,),"") -> Property
A53: 45471 | B53: Update | C53: 292 | E53: =IF(OR(Table11[[#This Row],[CAUD]]="Add", Table11[[#This Row],[CAUD]]="Update"),VLOOKUP(Table11[[#This Row],[Id]],Table1[#All],2,),"") -> #N/A | F53: nameSpace | G53: =IF(OR(Table11[[#This Row],[CAUD]]="Add", Table11[[#This Row],[CAUD]]="Update"),VLOOKUP(Table11[[#This Row],[Id]],Table6[#All],8,),"") -> #N/A | H53: =IF(OR(Table11[[#This Row],[CAUD]]="Add", Table11[[#This Row],[CAUD]]="Update"),VLOOKUP(Table11[[#This Row],[Id]],Table1[#All],4,),"") -> #N/A | I53: =IF(OR(Table11[[#This Row],[CAUD]]="Add", Table11[[#This Row],[CAUD]]="Update"),VLOOKUP(Table11[[#This Row],[Id]],Table1[#All],5,),"") -> #N/A | J53: moved to draft
A54: 45471 | B54: Update | C54: 294 | E54: =IF(OR(Table11[[#This Row],[CAUD]]="Add", Table11[[#This Row],[CAUD]]="Update"),VLOOKUP(Table11[[#This Row],[Id]],Table1[#All],2,),"") -> #N/A | F54: objectId | G54: =IF(OR(Table11[[#This Row],[CAUD]]="Add", Table11[[#This Row],[CAUD]]="Update"),VLOOKUP(Table11[[#This Row],[Id]],Table6[#All],8,),"") -> #N/A | H54: =IF(OR(Table11[[#This Row],[CAUD]]="Add", Table11[[#This Row],[CAUD]]="Update"),VLOOKUP(Table11[[#This Row],[Id]],Table1[#All],4,),"") -> #N/A | I54: =IF(OR(Table11[[#This Row],[CAUD]]="Add", Table11[[#This Row],[CAUD]]="Update"),VLOOKUP(Table11[[#This Row],[Id]],Table1[#All],5,),"") -> #N/A | J54: moved to draft
A55: 45562 | B55: Add | C55: 743 | E55: =IF(OR(Table11[[#This Row],[CAUD]]="Add", Table11[[#This Row],[CAUD]]="Update"),VLOOKUP(Table11[[#This Row],[Id]],Table1[#All],2,),"") -> legalRepresentative | G55: =IF(OR(Table11[[#This Row],[CAUD]]="Add", Table11[[#This Row],[CAUD]]="Update"),VLOOKUP(Table11[[#This Row],[Id]],Table6[#All],8,),"") -> Standard | H55: =IF(OR(Table11[[#This Row],[CAUD]]="Add", Table11[[#This Row],[CAUD]]="Update"),VLOOKUP(Table11[[#This Row],[Id]],Table1[#All],4,),"") -> Organization | I55: =IF(OR(Table11[[#This Row],[CAUD]]="Add", Table11[[#This Row],[CAUD]]="Update"),VLOOKUP(Table11[[#This Row],[Id]],Table1[#All],5,),"") -> Property
A56: 45562 | B56: Add | C56: 744 | E56: =IF(OR(Table11[[#This Row],[CAUD]]="Add", Table11[[#This Row],[CAUD]]="Update"),VLOOKUP(Table11[[#This Row],[Id]],Table1[#All],2,),"") -> linguisticRegime | G56: =IF(OR(Table11[[#This Row],[CAUD]]="Add", Table11[[#This Row],[CAUD]]="Update"),VLOOKUP(Table11[[#This Row],[Id]],Table6[#All],8,),"") -> Standard | H56: =IF(OR(Table11[[#This Row],[CAUD]]="Add", Table11[[#This Row],[CAUD]]="Update"),VLOOKUP(Table11[[#This Row],[Id]],Table1[#All],4,),"") -> Other | I56: =IF(OR(Table11[[#This Row],[CAUD]]="Add", Table11[[#This Row],[CAUD]]="Update"),VLOOKUP(Table11[[#This Row],[Id]],Table1[#All],5,),"") -> Property
A57: 45562 | B57: Add | C57: 745 | E57: =IF(OR(Table11[[#This Row],[CAUD]]="Add", Table11[[#This Row],[CAUD]]="Update"),VLOOKUP(Table11[[#This Row],[Id]],Table1[#All],2,),"") -> preferredLanguage | G57: =IF(OR(Table11[[#This Row],[CAUD]]="Add", Table11[[#This Row],[CAUD]]="Update"),VLOOKUP(Table11[[#This Row],[Id]],Table6[#All],8,),"") -> Draft | H57: =IF(OR(Table11[[#This Row],[CAUD]]="Add", Table11[[#This Row],[CAUD]]="Update"),VLOOKUP(Table11[[#This Row],[Id]],Table1[#All],4,),"") -> Other | I57: =IF(OR(Table11[[#This Row],[CAUD]]="Add", Table11[[#This Row],[CAUD]]="Update"),VLOOKUP(Table11[[#This Row],[Id]],Table1[#All],5,),"") -> Property
A58: 45562 | B58: Add | C58: 746 | E58: =IF(OR(Table11[[#This Row],[CAUD]]="Add", Table11[[#This Row],[CAUD]]="Update"),VLOOKUP(Table11[[#This Row],[Id]],Table1[#All],2,),"") -> NihdiCompetenceCode | G58: =IF(OR(Table11[[#This Row],[CAUD]]="Add", Table11[[#This Row],[CAUD]]="Update"),VLOOKUP(Table11[[#This Row],[Id]],Table6[#All],8,),"") -> Proposed standard | H58: =IF(OR(Table11[[#This Row],[CAUD]]="Add", Table11[[#This Row],[CAUD]]="Update"),VLOOKUP(Table11[[#This Row],[Id]],Table1[#All],4,),"") -> Healthcare | I58: =IF(OR(Table11[[#This Row],[CAUD]]="Add", Table11[[#This Row],[CAUD]]="Update"),VLOOKUP(Table11[[#This Row],[Id]],Table1[#All],5,),"") -> ConceptScheme
A59: 45562 | B59: Update | C59: 742 | E59: =IF(OR(Table11[[#This Row],[CAUD]]="Add", Table11[[#This Row],[CAUD]]="Update"),VLOOKUP(Table11[[#This Row],[Id]],Table1[#All],2,),"") -> BelgianPostCode | G59: =IF(OR(Table11[[#This Row],[CAUD]]="Add", Table11[[#This Row],[CAUD]]="Update"),VLOOKUP(Table11[[#This Row],[Id]],Table6[#All],8,),"") -> Standard | H59: =IF(OR(Table11[[#This Row],[CAUD]]="Add", Table11[[#This Row],[CAUD]]="Update"),VLOOKUP(Table11[[#This Row],[Id]],Table1[#All],4,),"") -> Location | I59: =IF(OR(Table11[[#This Row],[CAUD]]="Add", Table11[[#This Row],[CAUD]]="Update"),VLOOKUP(Table11[[#This Row],[Id]],Table1[#All],5,),"") -> DataType
A60: 45562 | B60: Update | C60: 303 | E60: =IF(OR(Table11[[#This Row],[CAUD]]="Add", Table11[[#This Row],[CAUD]]="Update"),VLOOKUP(Table11[[#This Row],[Id]],Table1[#All],2,),"") -> postCode | G60: =IF(OR(Table11[[#This Row],[CAUD]]="Add", Table11[[#This Row],[CAUD]]="Update"),VLOOKUP(Table11[[#This Row],[Id]],Table6[#All],8,),"") -> Proposed standard | H60: =IF(OR(Table11[[#This Row],[CAUD]]="Add", Table11[[#This Row],[CAUD]]="Update"),VLOOKUP(Table11[[#This Row],[Id]],Table1[#All],4,),"") -> Location | I60: =IF(OR(Table11[[#This Row],[CAUD]]="Add", Table11[[#This Row],[CAUD]]="Update"),VLOOKUP(Table11[[#This Row],[Id]],Table1[#All],5,),"") -> Property
A61: 45562 | B61: Update | C61: 736 | E61: =IF(OR(Table11[[#This Row],[CAUD]]="Add", Table11[[#This Row],[CAUD]]="Update"),VLOOKUP(Table11[[#This Row],[Id]],Table1[#All],2,),"") -> NaceBel2008 | G61: =IF(OR(Table11[[#This Row],[CAUD]]="Add", Table11[[#This Row],[CAUD]]="Update"),VLOOKUP(Table11[[#This Row],[Id]],Table6[#All],8,),"") -> Proposed standard | H61: =IF(OR(Table11[[#This Row],[CAUD]]="Add", Table11[[#This Row],[CAUD]]="Update"),VLOOKUP(Table11[[#This Row],[Id]],Table1[#All],4,),"") -> Organization | I61: =IF(OR(Table11[[#This Row],[CAUD]]="Add", Table11[[#This Row],[CAUD]]="Update"),VLOOKUP(Table11[[#This Row],[Id]],Table1[#All],5,),"") -> ConceptScheme | J61: URI
A62: 45562 | B62: Comment | E62: =IF(OR(Table11[[#This Row],[CAUD]]="Add", Table11[[#This Row],[CAUD]]="Update"),VLOOKUP(Table11[[#This Row],[Id]],Table1[#All],2,),"") | G62: =IF(OR(Table11[[#This Row],[CAUD]]="Add", Table11[[#This Row],[CAUD]]="Update"),VLOOKUP(Table11[[#This Row],[Id]],Table6[#All],8,),"") | H62: =IF(OR(Table11[[#This Row],[CAUD]]="Add", Table11[[#This Row],[CAUD]]="Update"),VLOOKUP(Table11[[#This Row],[Id]],Table1[#All],4,),"") | I62: =IF(OR(Table11[[#This Row],[CAUD]]="Add", Table11[[#This Row],[CAUD]]="Update"),VLOOKUP(Table11[[#This Row],[Id]],Table1[#All],5,),"") | J62: modif URI for federal conceptschemes: systematic use of prefix fed-thesaurus + removal of #id
A63: 45646 | B63: Update | C63: 303 | E63: =IF(OR(Table11[[#This Row],[CAUD]]="Add", Table11[[#This Row],[CAUD]]="Update"),VLOOKUP(Table11[[#This Row],[Id]],Table1[#All],2,),"") -> postCode | G63: =IF(OR(Table11[[#This Row],[CAUD]]="Add", Table11[[#This Row],[CAUD]]="Update"),VLOOKUP(Table11[[#This Row],[Id]],Table6[#All],8,),"") -> Proposed standard | H63: =IF(OR(Table11[[#This Row],[CAUD]]="Add", Table11[[#This Row],[CAUD]]="Update"),VLOOKUP(Table11[[#This Row],[Id]],Table1[#All],4,),"") -> Location | I63: =IF(OR(Table11[[#This Row],[CAUD]]="Add", Table11[[#This Row],[CAUD]]="Update"),VLOOKUP(Table11[[#This Row],[Id]],Table1[#All],5,),"") -> Property | J63: definition was updated
A64: 45646 | B64: Update | C64: 742 | E64: =IF(OR(Table11[[#This Row],[CAUD]]="Add", Table11[[#This Row],[CAUD]]="Update"),VLOOKUP(Table11[[#This Row],[Id]],Table1[#All],2,),"") -> BelgianPostCode | G64: =IF(OR(Table11[[#This Row],[CAUD]]="Add", Table11[[#This Row],[CAUD]]="Update"),VLOOKUP(Table11[[#This Row],[Id]],Table6[#All],8,),"") -> Standard | H64: =IF(OR(Table11[[#This Row],[CAUD]]="Add", Table11[[#This Row],[CAUD]]="Update"),VLOOKUP(Table11[[#This Row],[Id]],Table1[#All],4,),"") -> Location | I64: =IF(OR(Table11[[#This Row],[CAUD]]="Add", Table11[[#This Row],[CAUD]]="Update"),VLOOKUP(Table11[[#This Row],[Id]],Table1[#All],5,),"") -> DataType | J64: definition was updated
A65: 45646 | B65: Update | C65: 737 | E65: =IF(OR(Table11[[#This Row],[CAUD]]="Add", Table11[[#This Row],[CAUD]]="Update"),VLOOKUP(Table11[[#This Row],[Id]],Table1[#All],2,),"") -> NaceRev2Code | G65: =IF(OR(Table11[[#This Row],[CAUD]]="Add", Table11[[#This Row],[CAUD]]="Update"),VLOOKUP(Table11[[#This Row],[Id]],Table6[#All],8,),"") -> Proposed standard | H65: =IF(OR(Table11[[#This Row],[CAUD]]="Add", Table11[[#This Row],[CAUD]]="Update"),VLOOKUP(Table11[[#This Row],[Id]],Table1[#All],4,),"") -> Organization | I65: =IF(OR(Table11[[#This Row],[CAUD]]="Add", Table11[[#This Row],[CAUD]]="Update"),VLOOKUP(Table11[[#This Row],[Id]],Table1[#All],5,),"") -> DataType | J65: KBO/BCE also uses the first digit of the Nacebel code.
A66: 45646 | B66: Update | C66: 738 | E66: =IF(OR(Table11[[#This Row],[CAUD]]="Add", Table11[[#This Row],[CAUD]]="Update"),VLOOKUP(Table11[[#This Row],[Id]],Table1[#All],2,),"") -> NaceBel2008Code | G66: =IF(OR(Table11[[#This Row],[CAUD]]="Add", Table11[[#This Row],[CAUD]]="Update"),VLOOKUP(Table11[[#This Row],[Id]],Table6[#All],8,),"") -> Proposed standard | H66: =IF(OR(Table11[[#This Row],[CAUD]]="Add", Table11[[#This Row],[CAUD]]="Update"),VLOOKUP(Table11[[#This Row],[Id]],Table1[#All],4,),"") -> Organization | I66: =IF(OR(Table11[[#This Row],[CAUD]]="Add", Table11[[#This Row],[CAUD]]="Update"),VLOOKUP(Table11[[#This Row],[Id]],Table1[#All],5,),"") -> DataType | J66: KBO/BCE also uses the first digit of the Nacebel code.
A67: 45646 | B67: Delete | C67: 292 | E67: =IF(OR(Table11[[#This Row],[CAUD]]="Add", Table11[[#This Row],[CAUD]]="Update"),VLOOKUP(Table11[[#This Row],[Id]],Table1[#All],2,),"") | F67: nameSpace | G67: =IF(OR(Table11[[#This Row],[CAUD]]="Add", Table11[[#This Row],[CAUD]]="Update"),VLOOKUP(Table11[[#This Row],[Id]],Table6[#All],8,),"") | H67: =IF(OR(Table11[[#This Row],[CAUD]]="Add", Table11[[#This Row],[CAUD]]="Update"),VLOOKUP(Table11[[#This Row],[Id]],Table1[#All],4,),"") | I67: =IF(OR(Table11[[#This Row],[CAUD]]="Add", Table11[[#This Row],[CAUD]]="Update"),VLOOKUP(Table11[[#This Row],[Id]],Table1[#All],5,),"") | J67: BEST
A68: 45646 | B68: Delete | C68: 294 | E68: =IF(OR(Table11[[#This Row],[CAUD]]="Add", Table11[[#This Row],[CAUD]]="Update"),VLOOKUP(Table11[[#This Row],[Id]],Table1[#All],2,),"") | F68: objectId | G68: =IF(OR(Table11[[#This Row],[CAUD]]="Add", Table11[[#This Row],[CAUD]]="Update"),VLOOKUP(Table11[[#This Row],[Id]],Table6[#All],8,),"") | H68: =IF(OR(Table11[[#This Row],[CAUD]]="Add", Table11[[#This Row],[CAUD]]="Update"),VLOOKUP(Table11[[#This Row],[Id]],Table1[#All],4,),"") | I68: =IF(OR(Table11[[#This Row],[CAUD]]="Add", Table11[[#This Row],[CAUD]]="Update"),VLOOKUP(Table11[[#This Row],[Id]],Table1[#All],5,),"") | J68: BEST
A69: 45646 | B69: Delete | C69: 311 | E69: =IF(OR(Table11[[#This Row],[CAUD]]="Add", Table11[[#This Row],[CAUD]]="Update"),VLOOKUP(Table11[[#This Row],[Id]],Table1[#All],2,),"") | F69: versionId | G69: =IF(OR(Table11[[#This Row],[CAUD]]="Add", Table11[[#This Row],[CAUD]]="Update"),VLOOKUP(Table11[[#This Row],[Id]],Table6[#All],8,),"") | H69: =IF(OR(Table11[[#This Row],[CAUD]]="Add", Table11[[#This Row],[CAUD]]="Update"),VLOOKUP(Table11[[#This Row],[Id]],Table1[#All],4,),"") | I69: =IF(OR(Table11[[#This Row],[CAUD]]="Add", Table11[[#This Row],[CAUD]]="Update"),VLOOKUP(Table11[[#This Row],[Id]],Table1[#All],5,),"") | J69: BEST
A70: 45646 | B70: Update | C70: 740 | E70: =IF(OR(Table11[[#This Row],[CAUD]]="Add", Table11[[#This Row],[CAUD]]="Update"),VLOOKUP(Table11[[#This Row],[Id]],Table1[#All],2,),"") -> nihdiNumber | G70: =IF(OR(Table11[[#This Row],[CAUD]]="Add", Table11[[#This Row],[CAUD]]="Update"),VLOOKUP(Table11[[#This Row],[Id]],Table6[#All],8,),"") -> Proposed standard | H70: =IF(OR(Table11[[#This Row],[CAUD]]="Add", Table11[[#This Row],[CAUD]]="Update"),VLOOKUP(Table11[[#This Row],[Id]],Table1[#All],4,),"") -> Healthcare | I70: =IF(OR(Table11[[#This Row],[CAUD]]="Add", Table11[[#This Row],[CAUD]]="Update"),VLOOKUP(Table11[[#This Row],[Id]],Table1[#All],5,),"") -> Property | J70: moved to standard
A71: 45646 | B71: Update | C71: 746 | E71: =IF(OR(Table11[[#This Row],[CAUD]]="Add", Table11[[#This Row],[CAUD]]="Update"),VLOOKUP(Table11[[#This Row],[Id]],Table1[#All],2,),"") -> NihdiCompetenceCode | G71: =IF(OR(Table11[[#This Row],[CAUD]]="Add", Table11[[#This Row],[CAUD]]="Update"),VLOOKUP(Table11[[#This Row],[Id]],Table6[#All],8,),"") -> Proposed standard | H71: =IF(OR(Table11[[#This Row],[CAUD]]="Add", Table11[[#This Row],[CAUD]]="Update"),VLOOKUP(Table11[[#This Row],[Id]],Table1[#All],4,),"") -> Healthcare | I71: =IF(OR(Table11[[#This Row],[CAUD]]="Add", Table11[[#This Row],[CAUD]]="Update"),VLOOKUP(Table11[[#This Row],[Id]],Table1[#All],5,),"") -> ConceptScheme | J71: moved to standard
A72: 45646 | B72: Update | C72: 101 | E72: =IF(OR(Table11[[#This Row],[CAUD]]="Add", Table11[[#This Row],[CAUD]]="Update"),VLOOKUP(Table11[[#This Row],[Id]],Table1[#All],2,),"") -> LegalEntity | G72: =IF(OR(Table11[[#This Row],[CAUD]]="Add", Table11[[#This Row],[CAUD]]="Update"),VLOOKUP(Table11[[#This Row],[Id]],Table6[#All],8,),"") -> Standard | H72: =IF(OR(Table11[[#This Row],[CAUD]]="Add", Table11[[#This Row],[CAUD]]="Update"),VLOOKUP(Table11[[#This Row],[Id]],Table1[#All],4,),"") -> Organization | I72: =IF(OR(Table11[[#This Row],[CAUD]]="Add", Table11[[#This Row],[CAUD]]="Update"),VLOOKUP(Table11[[#This Row],[Id]],Table1[#All],5,),"") -> Class
A73: 45646 | B73: Delete | C73: 659 | E73: =IF(OR(Table11[[#This Row],[CAUD]]="Add", Table11[[#This Row],[CAUD]]="Update"),VLOOKUP(Table11[[#This Row],[Id]],Table1[#All],2,),"") | F73: RegisteredOrganization | G73: =IF(OR(Table11[[#This Row],[CAUD]]="Add", Table11[[#This Row],[CAUD]]="Update"),VLOOKUP(Table11[[#This Row],[Id]],Table6[#All],8,),"") | H73: =IF(OR(Table11[[#This Row],[CAUD]]="Add", Table11[[#This Row],[CAUD]]="Update"),VLOOKUP(Table11[[#This Row],[Id]],Table1[#All],4,),"") | I73: =IF(OR(Table11[[#This Row],[CAUD]]="Add", Table11[[#This Row],[CAUD]]="Update"),VLOOKUP(Table11[[#This Row],[Id]],Table1[#All],5,),"") | J73: replaced by LegalEntity
A74: 45748 | B74: Add | C74: 747 | E74: =IF(OR(Table11[[#This Row],[CAUD]]="Add", Table11[[#This Row],[CAUD]]="Update"),VLOOKUP(Table11[[#This Row],[Id]],Table1[#All],2,),"") -> CommunityCode | G74: =IF(OR(Table11[[#This Row],[CAUD]]="Add", Table11[[#This Row],[CAUD]]="Update"),VLOOKUP(Table11[[#This Row],[Id]],Table6[#All],8,),"") -> Proposed standard | H74: =IF(OR(Table11[[#This Row],[CAUD]]="Add", Table11[[#This Row],[CAUD]]="Update"),VLOOKUP(Table11[[#This Row],[Id]],Table1[#All],4,),"") -> Person | I74: =IF(OR(Table11[[#This Row],[CAUD]]="Add", Table11[[#This Row],[CAUD]]="Update"),VLOOKUP(Table11[[#This Row],[Id]],Table1[#All],5,),"") -> ConceptScheme
A75: 45748 | B75: Add | C75: 748 | E75: =IF(OR(Table11[[#This Row],[CAUD]]="Add", Table11[[#This Row],[CAUD]]="Update"),VLOOKUP(Table11[[#This Row],[Id]],Table1[#All],2,),"") -> community | G75: =IF(OR(Table11[[#This Row],[CAUD]]="Add", Table11[[#This Row],[CAUD]]="Update"),VLOOKUP(Table11[[#This Row],[Id]],Table6[#All],8,),"") -> Draft | H75: =IF(OR(Table11[[#This Row],[CAUD]]="Add", Table11[[#This Row],[CAUD]]="Update"),VLOOKUP(Table11[[#This Row],[Id]],Table1[#All],4,),"") -> Person | I75: =IF(OR(Table11[[#This Row],[CAUD]]="Add", Table11[[#This Row],[CAUD]]="Update"),VLOOKUP(Table11[[#This Row],[Id]],Table1[#All],5,),"") -> Property
A76: 45905 | B76: Add | C76: 749 | E76: =IF(OR(Table11[[#This Row],[CAUD]]="Add", Table11[[#This Row],[CAUD]]="Update"),VLOOKUP(Table11[[#This Row],[Id]],Table1[#All],2,),"") -> isCanceled | G76: =IF(OR(Table11[[#This Row],[CAUD]]="Add", Table11[[#This Row],[CAUD]]="Update"),VLOOKUP(Table11[[#This Row],[Id]],Table6[#All],8,),"") -> Proposed standard | H76: =IF(OR(Table11[[#This Row],[CAUD]]="Add", Table11[[#This Row],[CAUD]]="Update"),VLOOKUP(Table11[[#This Row],[Id]],Table1[#All],4,),"") -> Generic | I76: =IF(OR(Table11[[#This Row],[CAUD]]="Add", Table11[[#This Row],[CAUD]]="Update"),VLOOKUP(Table11[[#This Row],[Id]],Table1[#All],5,),"") -> Property
A77: 45905 | B77: Add | C77: 750 | E77: =IF(OR(Table11[[#This Row],[CAUD]]="Add", Table11[[#This Row],[CAUD]]="Update"),VLOOKUP(Table11[[#This Row],[Id]],Table1[#All],2,),"") -> replacedBy | G77: =IF(OR(Table11[[#This Row],[CAUD]]="Add", Table11[[#This Row],[CAUD]]="Update"),VLOOKUP(Table11[[#This Row],[Id]],Table6[#All],8,),"") -> Proposed standard | H77: =IF(OR(Table11[[#This Row],[CAUD]]="Add", Table11[[#This Row],[CAUD]]="Update"),VLOOKUP(Table11[[#This Row],[Id]],Table1[#All],4,),"") -> Generic | I77: =IF(OR(Table11[[#This Row],[CAUD]]="Add", Table11[[#This Row],[CAUD]]="Update"),VLOOKUP(Table11[[#This Row],[Id]],Table1[#All],5,),"") -> Property
A78: 45905 | B78: Add | C78: 751 | E78: =IF(OR(Table11[[#This Row],[CAUD]]="Add", Table11[[#This Row],[CAUD]]="Update"),VLOOKUP(Table11[[#This Row],[Id]],Table1[#All],2,),"") -> replaces | G78: =IF(OR(Table11[[#This Row],[CAUD]]="Add", Table11[[#This Row],[CAUD]]="Update"),VLOOKUP(Table11[[#This Row],[Id]],Table6[#All],8,),"") -> Proposed standard | H78: =IF(OR(Table11[[#This Row],[CAUD]]="Add", Table11[[#This Row],[CAUD]]="Update"),VLOOKUP(Table11[[#This Row],[Id]],Table1[#All],4,),"") -> Generic | I78: =IF(OR(Table11[[#This Row],[CAUD]]="Add", Table11[[#This Row],[CAUD]]="Update"),VLOOKUP(Table11[[#This Row],[Id]],Table1[#All],5,),"") -> Property
A79: 45905 | B79: Update | C79: 747 | E79: =IF(OR(Table11[[#This Row],[CAUD]]="Add", Table11[[#This Row],[CAUD]]="Update"),VLOOKUP(Table11[[#This Row],[Id]],Table1[#All],2,),"") -> CommunityCode | G79: =IF(OR(Table11[[#This Row],[CAUD]]="Add", Table11[[#This Row],[CAUD]]="Update"),VLOOKUP(Table11[[#This Row],[Id]],Table6[#All],8,),"") -> Proposed standard | H79: =IF(OR(Table11[[#This Row],[CAUD]]="Add", Table11[[#This Row],[CAUD]]="Update"),VLOOKUP(Table11[[#This Row],[Id]],Table1[#All],4,),"") -> Person | I79: =IF(OR(Table11[[#This Row],[CAUD]]="Add", Table11[[#This Row],[CAUD]]="Update"),VLOOKUP(Table11[[#This Row],[Id]],Table1[#All],5,),"") -> ConceptScheme | J79: Code gemeenschap
A80: 45905 | B80: Delete | C80: 693 | E80: =IF(OR(Table11[[#This Row],[CAUD]]="Add", Table11[[#This Row],[CAUD]]="Update"),VLOOKUP(Table11[[#This Row],[Id]],Table1[#All],2,),"") | F80: pplNumber | G80: =IF(OR(Table11[[#This Row],[CAUD]]="Add", Table11[[#This Row],[CAUD]]="Update"),VLOOKUP(Table11[[#This Row],[Id]],Table6[#All],8,),"") | H80: =IF(OR(Table11[[#This Row],[CAUD]]="Add", Table11[[#This Row],[CAUD]]="Update"),VLOOKUP(Table11[[#This Row],[Id]],Table1[#All],4,),"") | I80: =IF(OR(Table11[[#This Row],[CAUD]]="Add", Table11[[#This Row],[CAUD]]="Update"),VLOOKUP(Table11[[#This Row],[Id]],Table1[#All],5,),"") | J80: deprecated
A81: 45905 | B81: Delete | C81: 316 | E81: =IF(OR(Table11[[#This Row],[CAUD]]="Add", Table11[[#This Row],[CAUD]]="Update"),VLOOKUP(Table11[[#This Row],[Id]],Table1[#All],2,),"") | F81: EmbassyResident | G81: =IF(OR(Table11[[#This Row],[CAUD]]="Add", Table11[[#This Row],[CAUD]]="Update"),VLOOKUP(Table11[[#This Row],[Id]],Table6[#All],8,),"") | H81: =IF(OR(Table11[[#This Row],[CAUD]]="Add", Table11[[#This Row],[CAUD]]="Update"),VLOOKUP(Table11[[#This Row],[Id]],Table1[#All],4,),"") | I81: =IF(OR(Table11[[#This Row],[CAUD]]="Add", Table11[[#This Row],[CAUD]]="Update"),VLOOKUP(Table11[[#This Row],[Id]],Table1[#All],5,),"") | J81: refer to Person
A82: 45905 | B82: Delete | C82: 317 | E82: =IF(OR(Table11[[#This Row],[CAUD]]="Add", Table11[[#This Row],[CAUD]]="Update"),VLOOKUP(Table11[[#This Row],[Id]],Table1[#All],2,),"") | F82: ForeignResident | G82: =IF(OR(Table11[[#This Row],[CAUD]]="Add", Table11[[#This Row],[CAUD]]="Update"),VLOOKUP(Table11[[#This Row],[Id]],Table6[#All],8,),"") | H82: =IF(OR(Table11[[#This Row],[CAUD]]="Add", Table11[[#This Row],[CAUD]]="Update"),VLOOKUP(Table11[[#This Row],[Id]],Table1[#All],4,),"") | I82: =IF(OR(Table11[[#This Row],[CAUD]]="Add", Table11[[#This Row],[CAUD]]="Update"),VLOOKUP(Table11[[#This Row],[Id]],Table1[#All],5,),"") | J82: refer to Person
A83: 45905 | B83: Delete | C83: 312 | E83: =IF(OR(Table11[[#This Row],[CAUD]]="Add", Table11[[#This Row],[CAUD]]="Update"),VLOOKUP(Table11[[#This Row],[Id]],Table1[#All],2,),"") | F83: AsylumSeeker | G83: =IF(OR(Table11[[#This Row],[CAUD]]="Add", Table11[[#This Row],[CAUD]]="Update"),VLOOKUP(Table11[[#This Row],[Id]],Table6[#All],8,),"") | H83: =IF(OR(Table11[[#This Row],[CAUD]]="Add", Table11[[#This Row],[CAUD]]="Update"),VLOOKUP(Table11[[#This Row],[Id]],Table1[#All],4,),"") | I83: =IF(OR(Table11[[#This Row],[CAUD]]="Add", Table11[[#This Row],[CAUD]]="Update"),VLOOKUP(Table11[[#This Row],[Id]],Table1[#All],5,),"") | J83: refer to Person
A84: 45905 | B84: Delete | C84: 313 | E84: =IF(OR(Table11[[#This Row],[CAUD]]="Add", Table11[[#This Row],[CAUD]]="Update"),VLOOKUP(Table11[[#This Row],[Id]],Table1[#All],2,),"") | F84: BelgianResident | G84: =IF(OR(Table11[[#This Row],[CAUD]]="Add", Table11[[#This Row],[CAUD]]="Update"),VLOOKUP(Table11[[#This Row],[Id]],Table6[#All],8,),"") | H84: =IF(OR(Table11[[#This Row],[CAUD]]="Add", Table11[[#This Row],[CAUD]]="Update"),VLOOKUP(Table11[[#This Row],[Id]],Table1[#All],4,),"") | I84: =IF(OR(Table11[[#This Row],[CAUD]]="Add", Table11[[#This Row],[CAUD]]="Update"),VLOOKUP(Table11[[#This Row],[Id]],Table1[#All],5,),"") | J84: refer to Person
A85: 45905 | B85: Delete | C85: 322 | E85: =IF(OR(Table11[[#This Row],[CAUD]]="Add", Table11[[#This Row],[CAUD]]="Update"),VLOOKUP(Table11[[#This Row],[Id]],Table1[#All],2,),"") | F85: NonResident | G85: =IF(OR(Table11[[#This Row],[CAUD]]="Add", Table11[[#This Row],[CAUD]]="Update"),VLOOKUP(Table11[[#This Row],[Id]],Table6[#All],8,),"") | H85: =IF(OR(Table11[[#This Row],[CAUD]]="Add", Table11[[#This Row],[CAUD]]="Update"),VLOOKUP(Table11[[#This Row],[Id]],Table1[#All],4,),"") | I85: =IF(OR(Table11[[#This Row],[CAUD]]="Add", Table11[[#This Row],[CAUD]]="Update"),VLOOKUP(Table11[[#This Row],[Id]],Table1[#All],5,),"") | J85: refer to Person
A86: 45905 | B86: Delete | C86: 325 | E86: =IF(OR(Table11[[#This Row],[CAUD]]="Add", Table11[[#This Row],[CAUD]]="Update"),VLOOKUP(Table11[[#This Row],[Id]],Table1[#All],2,),"") | F86: FormerResident | G86: =IF(OR(Table11[[#This Row],[CAUD]]="Add", Table11[[#This Row],[CAUD]]="Update"),VLOOKUP(Table11[[#This Row],[Id]],Table6[#All],8,),"") | H86: =IF(OR(Table11[[#This Row],[CAUD]]="Add", Table11[[#This Row],[CAUD]]="Update"),VLOOKUP(Table11[[#This Row],[Id]],Table1[#All],4,),"") | I86: =IF(OR(Table11[[#This Row],[CAUD]]="Add", Table11[[#This Row],[CAUD]]="Update"),VLOOKUP(Table11[[#This Row],[Id]],Table1[#All],5,),"") | J86: refer to Person
A87: 45905 | B87: Delete | C87: 225 | E87: =IF(OR(Table11[[#This Row],[CAUD]]="Add", Table11[[#This Row],[CAUD]]="Update"),VLOOKUP(Table11[[#This Row],[Id]],Table1[#All],2,),"") | F87: addressRegisteredOffice | G87: =IF(OR(Table11[[#This Row],[CAUD]]="Add", Table11[[#This Row],[CAUD]]="Update"),VLOOKUP(Table11[[#This Row],[Id]],Table6[#All],8,),"") | H87: =IF(OR(Table11[[#This Row],[CAUD]]="Add", Table11[[#This Row],[CAUD]]="Update"),VLOOKUP(Table11[[#This Row],[Id]],Table1[#All],4,),"") | I87: =IF(OR(Table11[[#This Row],[CAUD]]="Add", Table11[[#This Row],[CAUD]]="Update"),VLOOKUP(Table11[[#This Row],[Id]],Table1[#All],5,),"") | J87: redundant with org:hasSite and org:siteOf
A88: 45905 | B88: Delete | C88: 648 | E88: =IF(OR(Table11[[#This Row],[CAUD]]="Add", Table11[[#This Row],[CAUD]]="Update"),VLOOKUP(Table11[[#This Row],[Id]],Table1[#All],2,),"") | F88: Site | G88: =IF(OR(Table11[[#This Row],[CAUD]]="Add", Table11[[#This Row],[CAUD]]="Update"),VLOOKUP(Table11[[#This Row],[Id]],Table6[#All],8,),"") | H88: =IF(OR(Table11[[#This Row],[CAUD]]="Add", Table11[[#This Row],[CAUD]]="Update"),VLOOKUP(Table11[[#This Row],[Id]],Table1[#All],4,),"") | I88: =IF(OR(Table11[[#This Row],[CAUD]]="Add", Table11[[#This Row],[CAUD]]="Update"),VLOOKUP(Table11[[#This Row],[Id]],Table1[#All],5,),"") | J88: replaced by EstablishmentUnit
A89: 45905 | B89: Delete | C89: 720 | E89: =IF(OR(Table11[[#This Row],[CAUD]]="Add", Table11[[#This Row],[CAUD]]="Update"),VLOOKUP(Table11[[#This Row],[Id]],Table1[#All],2,),"") | F89: CbeRegisteredEntity | G89: =IF(OR(Table11[[#This Row],[CAUD]]="Add", Table11[[#This Row],[CAUD]]="Update"),VLOOKUP(Table11[[#This Row],[Id]],Table6[#All],8,),"") | H89: =IF(OR(Table11[[#This Row],[CAUD]]="Add", Table11[[#This Row],[CAUD]]="Update"),VLOOKUP(Table11[[#This Row],[Id]],Table1[#All],4,),"") | I89: =IF(OR(Table11[[#This Row],[CAUD]]="Add", Table11[[#This Row],[CAUD]]="Update"),VLOOKUP(Table11[[#This Row],[Id]],Table1[#All],5,),"") | J89: replaced by LegalEntity
A90: 45905 | B90: Update | C90: 101 | E90: =IF(OR(Table11[[#This Row],[CAUD]]="Add", Table11[[#This Row],[CAUD]]="Update"),VLOOKUP(Table11[[#This Row],[Id]],Table1[#All],2,),"") -> LegalEntity | G90: =IF(OR(Table11[[#This Row],[CAUD]]="Add", Table11[[#This Row],[CAUD]]="Update"),VLOOKUP(Table11[[#This Row],[Id]],Table6[#All],8,),"") -> Standard | H90: =IF(OR(Table11[[#This Row],[CAUD]]="Add", Table11[[#This Row],[CAUD]]="Update"),VLOOKUP(Table11[[#This Row],[Id]],Table1[#All],4,),"") -> Organization | I90: =IF(OR(Table11[[#This Row],[CAUD]]="Add", Table11[[#This Row],[CAUD]]="Update"),VLOOKUP(Table11[[#This Row],[Id]],Table1[#All],5,),"") -> Class | J90: refer to BCE
A91: 45905 | B91: Update | C91: 721 | E91: =IF(OR(Table11[[#This Row],[CAUD]]="Add", Table11[[#This Row],[CAUD]]="Update"),VLOOKUP(Table11[[#This Row],[Id]],Table1[#All],2,),"") -> EstablishmentUnit | G91: =IF(OR(Table11[[#This Row],[CAUD]]="Add", Table11[[#This Row],[CAUD]]="Update"),VLOOKUP(Table11[[#This Row],[Id]],Table6[#All],8,),"") -> Proposed standard | H91: =IF(OR(Table11[[#This Row],[CAUD]]="Add", Table11[[#This Row],[CAUD]]="Update"),VLOOKUP(Table11[[#This Row],[Id]],Table1[#All],4,),"") -> Organization | I91: =IF(OR(Table11[[#This Row],[CAUD]]="Add", Table11[[#This Row],[CAUD]]="Update"),VLOOKUP(Table11[[#This Row],[Id]],Table1[#All],5,),"") -> Class | J91: URI becomes org:Site
A92: 45905 | B92: Update | C92: 248 | E92: =IF(OR(Table11[[#This Row],[CAUD]]="Add", Table11[[#This Row],[CAUD]]="Update"),VLOOKUP(Table11[[#This Row],[Id]],Table1[#All],2,),"") -> website | G92: =IF(OR(Table11[[#This Row],[CAUD]]="Add", Table11[[#This Row],[CAUD]]="Update"),VLOOKUP(Table11[[#This Row],[Id]],Table6[#All],8,),"") -> Proposed standard | H92: =IF(OR(Table11[[#This Row],[CAUD]]="Add", Table11[[#This Row],[CAUD]]="Update"),VLOOKUP(Table11[[#This Row],[Id]],Table1[#All],4,),"") -> Organization | I92: =IF(OR(Table11[[#This Row],[CAUD]]="Add", Table11[[#This Row],[CAUD]]="Update"),VLOOKUP(Table11[[#This Row],[Id]],Table1[#All],5,),"") -> Property | J92: URI becomes foaf:homepage
A93: 45905 | B93: Update | C93: 236 | E93: =IF(OR(Table11[[#This Row],[CAUD]]="Add", Table11[[#This Row],[CAUD]]="Update"),VLOOKUP(Table11[[#This Row],[Id]],Table1[#All],2,),"") -> hasEstablishmentUnit | F93: hasSite | G93: =IF(OR(Table11[[#This Row],[CAUD]]="Add", Table11[[#This Row],[CAUD]]="Update"),VLOOKUP(Table11[[#This Row],[Id]],Table6[#All],8,),"") -> Proposed standard | H93: =IF(OR(Table11[[#This Row],[CAUD]]="Add", Table11[[#This Row],[CAUD]]="Update"),VLOOKUP(Table11[[#This Row],[Id]],Table1[#All],4,),"") -> Organization | I93: =IF(OR(Table11[[#This Row],[CAUD]]="Add", Table11[[#This Row],[CAUD]]="Update"),VLOOKUP(Table11[[#This Row],[Id]],Table1[#All],5,),"") -> Property | J93: rename
A94: 45905 | B94: Update | C94: 655 | E94: =IF(OR(Table11[[#This Row],[CAUD]]="Add", Table11[[#This Row],[CAUD]]="Update"),VLOOKUP(Table11[[#This Row],[Id]],Table1[#All],2,),"") -> establishmentUnitOf | F94: siteOf | G94: =IF(OR(Table11[[#This Row],[CAUD]]="Add", Table11[[#This Row],[CAUD]]="Update"),VLOOKUP(Table11[[#This Row],[Id]],Table6[#All],8,),"") -> Proposed standard | H94: =IF(OR(Table11[[#This Row],[CAUD]]="Add", Table11[[#This Row],[CAUD]]="Update"),VLOOKUP(Table11[[#This Row],[Id]],Table1[#All],4,),"") -> Organization | I94: =IF(OR(Table11[[#This Row],[CAUD]]="Add", Table11[[#This Row],[CAUD]]="Update"),VLOOKUP(Table11[[#This Row],[Id]],Table1[#All],5,),"") -> Property | J94: rename
A95: 45989 | B95: Add | C95: 752 | E95: =IF(OR(Table11[[#This Row],[CAUD]]="Add", Table11[[#This Row],[CAUD]]="Update"),VLOOKUP(Table11[[#This Row],[Id]],Table1[#All],2,),"") -> NaceBel2025 | G95: =IF(OR(Table11[[#This Row],[CAUD]]="Add", Table11[[#This Row],[CAUD]]="Update"),VLOOKUP(Table11[[#This Row],[Id]],Table6[#All],8,),"") -> Proposed standard | H95: =IF(OR(Table11[[#This Row],[CAUD]]="Add", Table11[[#This Row],[CAUD]]="Update"),VLOOKUP(Table11[[#This Row],[Id]],Table1[#All],4,),"") -> Organization | I95: =IF(OR(Table11[[#This Row],[CAUD]]="Add", Table11[[#This Row],[CAUD]]="Update"),VLOOKUP(Table11[[#This Row],[Id]],Table1[#All],5,),"") -> ConceptScheme
A96: 45989 | B96: Add | C96: 753 | E96: =IF(OR(Table11[[#This Row],[CAUD]]="Add", Table11[[#This Row],[CAUD]]="Update"),VLOOKUP(Table11[[#This Row],[Id]],Table1[#All],2,),"") -> NaceRev2_1Code | G96: =IF(OR(Table11[[#This Row],[CAUD]]="Add", Table11[[#This Row],[CAUD]]="Update"),VLOOKUP(Table11[[#This Row],[Id]],Table6[#All],8,),"") -> Proposed standard | H96: =IF(OR(Table11[[#This Row],[CAUD]]="Add", Table11[[#This Row],[CAUD]]="Update"),VLOOKUP(Table11[[#This Row],[Id]],Table1[#All],4,),"") -> Organization | I96: =IF(OR(Table11[[#This Row],[CAUD]]="Add", Table11[[#This Row],[CAUD]]="Update"),VLOOKUP(Table11[[#This Row],[Id]],Table1[#All],5,),"") -> DataType
A97: 45989 | B97: Add | C97: 754 | E97: =IF(OR(Table11[[#This Row],[CAUD]]="Add", Table11[[#This Row],[CAUD]]="Update"),VLOOKUP(Table11[[#This Row],[Id]],Table1[#All],2,),"") -> NaceBel2025Code | G97: =IF(OR(Table11[[#This Row],[CAUD]]="Add", Table11[[#This Row],[CAUD]]="Update"),VLOOKUP(Table11[[#This Row],[Id]],Table6[#All],8,),"") -> Proposed standard | H97: =IF(OR(Table11[[#This Row],[CAUD]]="Add", Table11[[#This Row],[CAUD]]="Update"),VLOOKUP(Table11[[#This Row],[Id]],Table1[#All],4,),"") -> Organization | I97: =IF(OR(Table11[[#This Row],[CAUD]]="Add", Table11[[#This Row],[CAUD]]="Update"),VLOOKUP(Table11[[#This Row],[Id]],Table1[#All],5,),"") -> DataType
A98: 45989 | B98: Add | C98: 755 | E98: =IF(OR(Table11[[#This Row],[CAUD]]="Add", Table11[[#This Row],[CAUD]]="Update"),VLOOKUP(Table11[[#This Row],[Id]],Table1[#All],2,),"") -> NaceBel2025Length5Code | G98: =IF(OR(Table11[[#This Row],[CAUD]]="Add", Table11[[#This Row],[CAUD]]="Update"),VLOOKUP(Table11[[#This Row],[Id]],Table6[#All],8,),"") -> Proposed standard | H98: =IF(OR(Table11[[#This Row],[CAUD]]="Add", Table11[[#This Row],[CAUD]]="Update"),VLOOKUP(Table11[[#This Row],[Id]],Table1[#All],4,),"") -> Organization | I98: =IF(OR(Table11[[#This Row],[CAUD]]="Add", Table11[[#This Row],[CAUD]]="Update"),VLOOKUP(Table11[[#This Row],[Id]],Table1[#All],5,),"") -> DataType
A99: 45989 | B99: Update | C99: 734 | E99: =IF(OR(Table11[[#This Row],[CAUD]]="Add", Table11[[#This Row],[CAUD]]="Update"),VLOOKUP(Table11[[#This Row],[Id]],Table1[#All],2,),"") -> NaceEuRev2 | G99: =IF(OR(Table11[[#This Row],[CAUD]]="Add", Table11[[#This Row],[CAUD]]="Update"),VLOOKUP(Table11[[#This Row],[Id]],Table6[#All],8,),"") -> Proposed standard | H99: =IF(OR(Table11[[#This Row],[CAUD]]="Add", Table11[[#This Row],[CAUD]]="Update"),VLOOKUP(Table11[[#This Row],[Id]],Table1[#All],4,),"") -> Organization | I99: =IF(OR(Table11[[#This Row],[CAUD]]="Add", Table11[[#This Row],[CAUD]]="Update"),VLOOKUP(Table11[[#This Row],[Id]],Table1[#All],5,),"") -> ConceptScheme
A100: 45989 | B100: Update | C100: 735 | E100: =IF(OR(Table11[[#This Row],[CAUD]]="Add", Table11[[#This Row],[CAUD]]="Update"),VLOOKUP(Table11[[#This Row],[Id]],Table1[#All],2,),"") -> NaceEuRev2_1 | G100: =IF(OR(Table11[[#This Row],[CAUD]]="Add", Table11[[#This Row],[CAUD]]="Update"),VLOOKUP(Table11[[#This Row],[Id]],Table6[#All],8,),"") -> Proposed standard | H100: =IF(OR(Table11[[#This Row],[CAUD]]="Add", Table11[[#This Row],[CAUD]]="Update"),VLOOKUP(Table11[[#This Row],[Id]],Table1[#All],4,),"") -> Organization | I100: =IF(OR(Table11[[#This Row],[CAUD]]="Add", Table11[[#This Row],[CAUD]]="Update"),VLOOKUP(Table11[[#This Row],[Id]],Table1[#All],5,),"") -> ConceptScheme
...

Sheet Government institutions
A1: Code | B1: Name in en | C1: Name in nl | D1: Name in fr | E1: Name in de | F1: Status
A2: BOSA | B2: Federal Public Service Policy and Support (BOSA) | C2: Federale Overheidsdienst Beleid en Ondersteuning (BOSA) | D2: Service Public Fédéral Stratégie et Appui | E2: Föderaler Öffentlichter Dienst Politik und Unterstützung (BOSA) | F2: Standard
A3: CBSS | B3: Crossroads Bank of Social Security (CBSS ) | C3: Kruispuntbank van de Sociale Zekerheid (KSZ) | D3: Banque-Carrefour de la Sécurité Sociale (BCSS) | E3: Zentrale Datenbank der sozialen Sicherheit (ZDSS) | F3: Standard
A4: Fedris | B4: Fedris | C4: Federaal agentschap voor beroepsrisico's (Fedris) | D4: Agence fédérale des risques professionnels (Fedris) | E4: Föderalagentur für Berufsrisiken (Fedris) | F4: Standard
A5: FPSFIN | B5: Federal Public Service Finance (FPSFIN) | C5: Federale Overheidsdienst Financiën (FODFIN) | D5: Service Public Fédéral Finances (SPFFIN) | E5: Föderaler Öffentlicher Dienst (FODFIN) | F5: Standard
A6: NEO | B6: National Employment Office (NEO) | C6: Rijksdienst voor Arbeidsvoorziening (RVA) | D6: Office National de l'Emploi (ONEM) | E6: Landesamt für Arbeitsbeschaffung (LfA) | F6: Standard
A7: NIHDI | B7: National institute for health and disability insurance (NIHDI) | C7: Rijksinstituut voor ziekte- en invaliditeitsverzekering (RIZIV) | D7: Institut national d'assurance maladie-invalidité (INAMI) | E7: Landesinstitut für Kranken- und Invalidenversicherung (LIKIV) | F7: Standard
A8: NISSE | B8: National Institute for the Social Security of the Self-employed (NISSE) | C8: Rijksinstituut voor de Sociale Verzekeringen der Zelfstandigen (RSVZ) | D8: Institut national d'assurances sociales pour travailleurs indépendants (INASTI) | E8: Landesinstitut der Sozialversicherungen für Selbständige (LISVS) | F8: Standard
A9: NOAV | B9: National Office for Annual Vacation (NOAV) | C9: Rijksdienst voor jaarlijkse vakantie (RJV) | D9: Office National des Vacances Annuelles (ONVA) | E9: Landesamt für Jahresurlaub (LJU) | F9: Standard
A10: NSSO | B10: National Social Security Office (NSSO) | C10: Rijksdienst voor Sociale Zekerheid (RSZ) | D10: Office National de Sécurité Sociale (ONSS) | E10: Landesamt für Soziale Sicherheit (LSS) | F10: Standard
A11: PCSW | B11: Public Center for Social Welfare | C11: Openbaar centrum voor maatschappelijk welzijn (OCMW) | D11: Centre public d'action sociale (CPAS) | E11: Öffentliches Sozialhilfezentrum | F11: Standard
A12: RRN | B12: National Registry | C12: Rijksregister | D12: Registre National | E12: Nationalregister | F12: Standard
... A14: Sigedis | B14: Sigedis | C14: Sociale Individuele Gegevens (Sigedis) | D14: Données Individuelles Sociales (Sigedis) | E14: Sigedis | F14: Standard
A17: Ledenlijst | Smals
A18: Liste des membres de Smals | Smals
A19: https://github.com/belgif/fedvoc | B19: Also check this list of government organizations which will be updated 2*/year by BOSA.

Sheet Vocabulary
A1: Id | B1: Name | C1: Definition | D1: Ontology | E1: Type | F1: Source | G1: Comment | H1: URIPrefix | I1: URIName | J1: URI | K1: inOpenApi | L1: publishYN
A2: 1 | B2: Address | C2: An address representing a location. | D2: Location | E2: Class | F2: EU | H2: eu | J2: =IF(I2="",IF(F2="FED",IF(AND(E2="ConceptScheme",LEFT(H2,7) <> "inspire"),CONCATENATE("<",H2,":",LOWER(IF(I2="",B2,I2)),">"),CONCATENATE("<",H2,":",IF(I2="",B2,I2),">")),CONCATENATE("<",H2,":",IF(I2="",B2,I2),">")),CONCATENATE("<",I2,">")) -> <eu:Address> | K2: no | L2: no | N2: next id: | O2: =MAX(A:A)+1 -> 757
A3: 2 | B3: AddressFullAddress | C3: The complete address with or without formatting. | D3: Location | E3: Property | F3: EU | H3: eu | J3: =IF(I3="",IF(F3="FED",IF(AND(E3="ConceptScheme",LEFT(H3,7) <> "inspire"),CONCATENATE("<",H3,":",LOWER(IF(I3="",B3,I3)),">"),CONCATENATE("<",H3,":",IF(I3="",B3,I3),">")),CONCATENATE("<",H3,":",IF(I3="",B3,I3),">")),CONCATENATE("<",I3,">")) -> <eu:AddressFullAddress> | K3: no | L3: no | N3: checksum: | O3: =SUM(A2:A662) -> 247016
A4: 3 | B4: AddressPOBox | C4: The Post Office Box number. | D4: Location | E4: Property | F4: EU | H4: eu | J4: =IF(I4="",IF(F4="FED",IF(AND(E4="ConceptScheme",LEFT(H4,7) <> "inspire"),CONCATENATE("<",H4,":",LOWER(IF(I4="",B4,I4)),">"),CONCATENATE("<",H4,":",IF(I4="",B4,I4),">")),CONCATENATE("<",H4,":",IF(I4="",B4,I4),">")),CONCATENATE("<",I4,">")) -> <eu:AddressPOBox> | K4: no | L4: no | N4: source EU: | O4: http://mapping.semic.eu/public_data/Core_Vocabularies_Mapping_Template.xlsx
A5: 4 | B5: AddressThoroughfare | C5: The name of a passage or way through from one location to another. | D5: Location | E5: Property | F5: EU | H5: eu | J5: =IF(I5="",IF(F5="FED",IF(AND(E5="ConceptScheme",LEFT(H5,7) <> "inspire"),CONCATENATE("<",H5,":",LOWER(IF(I5="",B5,I5)),">"),CONCATENATE("<",H5,":",IF(I5="",B5,I5),">")),CONCATENATE("<",H5,":",IF(I5="",B5,I5),">")),CONCATENATE("<",I5,">")) -> <eu:AddressThoroughfare> | K5: no | L5: no
A6: 5 | B6: AddressLocatorDesignator | C6: A number or a sequence of characters that uniquely identifies the locator within the relevant scope. | D6: Location | E6: Property | F6: EU | H6: eu | J6: =IF(I6="",IF(F6="FED",IF(AND(E6="ConceptScheme",LEFT(H6,7) <> "inspire"),CONCATENATE("<",H6,":",LOWER(IF(I6="",B6,I6)),">"),CONCATENATE("<",H6,":",IF(I6="",B6,I6),">")),CONCATENATE("<",H6,":",IF(I6="",B6,I6),">")),CONCATENATE("<",I6,">")) -> <eu:AddressLocatorDesignator> | K6: no | L6: no
A7: 6 | B7: AddressLocatorName | C7: A proper noun applied to the real world entity identified by the address. | D7: Location | E7: Property | F7: EU | H7: eu | J7: =IF(I7="",IF(F7="FED",IF(AND(E7="ConceptScheme",LEFT(H7,7) <> "inspire"),CONCATENATE("<",H7,":",LOWER(IF(I7="",B7,I7)),">"),CONCATENATE("<",H7,":",IF(I7="",B7,I7),">")),CONCATENATE("<",H7,":",IF(I7="",B7,I7),">")),CONCATENATE("<",I7,">")) -> <eu:AddressLocatorName> | K7: no | L7: no
A8: 7 | B8: AddressAddressArea | C8: The name of a geographic area or locality that groups a number of addressable objects for addressing purposes, without being an administrative unit. | D8: Location | E8: Property | F8: EU | H8: eu | J8: =IF(I8="",IF(F8="FED",IF(AND(E8="ConceptScheme",LEFT(H8,7) <> "inspire"),CONCATENATE("<",H8,":",LOWER(IF(I8="",B8,I8)),">"),CONCATENATE("<",H8,":",IF(I8="",B8,I8),">")),CONCATENATE("<",H8,":",IF(I8="",B8,I8),">")),CONCATENATE("<",I8,">")) -> <eu:AddressAddressArea> | K8: no | L8: no
A9: 8 | B9: AddressPostName | C9: The key postal division of the address, usually the city. | D9: Location | E9: Property | F9: EU | H9: eu | J9: =IF(I9="",IF(F9="FED",IF(AND(E9="ConceptScheme",LEFT(H9,7) <> "inspire"),CONCATENATE("<",H9,":",LOWER(IF(I9="",B9,I9)),">"),CONCATENATE("<",H9,":",IF(I9="",B9,I9),">")),CONCATENATE("<",H9,":",IF(I9="",B9,I9),">")),CONCATENATE("<",I9,">")) -> <eu:AddressPostName> | K9: no | L9: no
A10: 9 | B10: AddressAdminUnitL2 | C10: The region of the address, usually a county, state or other such area that typically encompasses several localities. | D10: Location | E10: Property | F10: EU | H10: eu | J10: =IF(I10="",IF(F10="FED",IF(AND(E10="ConceptScheme",LEFT(H10,7) <> "inspire"),CONCATENATE("<",H10,":",LOWER(IF(I10="",B10,I10)),">"),CONCATENATE("<",H10,":",IF(I10="",B10,I10),">")),CONCATENATE("<",H10,":",IF(I10="",B10,I10),">")),CONCATENATE("<",I10,">")) -> <eu:AddressAdminUnitL2> | K10: no | L10: no
A11: 10 | B11: AddressAdminUnitL1 | C11: The uppermost administrative unit for the address, almost always a country. | D11: Location | E11: Property | F11: EU | H11: eu | J11: =IF(I11="",IF(F11="FED",IF(AND(E11="ConceptScheme",LEFT(H11,7) <> "inspire"),CONCATENATE("<",H11,":",LOWER(IF(I11="",B11,I11)),">"),CONCATENATE("<",H11,":",IF(I11="",B11,I11),">")),CONCATENATE("<",H11,":",IF(I11="",B11,I11),">")),CONCATENATE("<",I11,">")) -> <eu:AddressAdminUnitL1> | K11: no | L11: no
A12: 11 | B12: AddressPostCode | C12: The post code, a.k.a. postal code, ZIP code, etc. | D12: Location | E12: Property | F12: EU | H12: eu | J12: =IF(I12="",IF(F12="FED",IF(AND(E12="ConceptScheme",LEFT(H12,7) <> "inspire"),CONCATENATE("<",H12,":",LOWER(IF(I12="",B12,I12)),">"),CONCATENATE("<",H12,":",IF(I12="",B12,I12),">")),CONCATENATE("<",H12,":",IF(I12="",B12,I12),">")),CONCATENATE("<",I12,">")) -> <eu:AddressPostCode> | K12: no | L12: no
A13: 12 | B13: AddressAddressID | C13: A globally unique identifier for this instance of the address. | D13: Location | E13: Property | F13: EU | H13: eu | J13: =IF(I13="",IF(F13="FED",IF(AND(E13="ConceptScheme",LEFT(H13,7) <> "inspire"),CONCATENATE("<",H13,":",LOWER(IF(I13="",B13,I13)),">"),CONCATENATE("<",H13,":",IF(I13="",B13,I13),">")),CONCATENATE("<",H13,":",IF(I13="",B13,I13),">")),CONCATENATE("<",I13,">")) -> <eu:AddressAddressID> | K13: no | L13: no
A14: 13 | B14: Agent | C14: An entity that is able to carry out actions. | D14: Other | E14: Class | F14: EU | H14: eu | J14: =IF(I14="",IF(F14="FED",IF(AND(E14="ConceptScheme",LEFT(H14,7) <> "inspire"),CONCATENATE("<",H14,":",LOWER(IF(I14="",B14,I14)),">"),CONCATENATE("<",H14,":",IF(I14="",B14,I14),">")),CONCATENATE("<",H14,":",IF(I14="",B14,I14),">")),CONCATENATE("<",I14,">")) -> <eu:Agent> | K14: no | L14: no
A15: 14 | B15: AgentIdentifier | C15: This property represents a formally-issued Identifier for the Agent. | D15: Other | E15: Property | F15: EU | H15: eu | J15: =IF(I15="",IF(F15="FED",IF(AND(E15="ConceptScheme",LEFT(H15,7) <> "inspire"),CONCATENATE("<",H15,":",LOWER(IF(I15="",B15,I15)),">"),CONCATENATE("<",H15,":",IF(I15="",B15,I15),">")),CONCATENATE("<",H15,":",IF(I15="",B15,I15),">")),CONCATENATE("<",I15,">")) -> <eu:AgentIdentifier> | K15: no | L15: no
A16: 15 | B16: AgentName | C16: This property represents the Name of the Agent. | D16: Other | E16: Property | F16: EU | H16: eu | J16: =IF(I16="",IF(F16="FED",IF(AND(E16="ConceptScheme",LEFT(H16,7) <> "inspire"),CONCATENATE("<",H16,":",LOWER(IF(I16="",B16,I16)),">"),CONCATENATE("<",H16,":",IF(I16="",B16,I16),">")),CONCATENATE("<",H16,":",IF(I16="",B16,I16),">")),CONCATENATE("<",I16,">")) -> <eu:AgentName> | K16: no | L16: no
... A20: 19 | B20: AgentHasAddress | C20: This property represents an Address related to an Agent. Asserting the address relationship implies that the Agent has an Address. | D20: Other | E20: Association | F20: EU | H20: eu | J20: =IF(I20="",IF(F20="FED",IF(AND(E20="ConceptScheme",LEFT(H20,7) <> "inspire"),CONCATENATE("<",H20,":",LOWER(IF(I20="",B20,I20)),">"),CONCATENATE("<",H20,":",IF(I20="",B20,I20),">")),CONCATENATE("<",H20,":",IF(I20="",B20,I20),">")),CONCATENATE("<",I20,">")) -> <eu:AgentHasAddress> | K20: no | L20: no
A21: 20 | B21: AgentSatisfiesCriterion | D21: Other | E21: Association | F21: EU | H21: eu | J21: =IF(I21="",IF(F21="FED",IF(AND(E21="ConceptScheme",LEFT(H21,7) <> "inspire"),CONCATENATE("<",H21,":",LOWER(IF(I21="",B21,I21)),">"),CONCATENATE("<",H21,":",IF(I21="",B21,I21),">")),CONCATENATE("<",H21,":",IF(I21="",B21,I21),">")),CONCATENATE("<",I21,">")) -> <eu:AgentSatisfiesCriterion> | K21: no | L21: no
A22: 21 | B22: AgentProvidesRequirementResponse | D22: Other | E22: Association | F22: EU | H22: eu | J22: =IF(I22="",IF(F22="FED",IF(AND(E22="ConceptScheme",LEFT(H22,7) <> "inspire"),CONCATENATE("<",H22,":",LOWER(IF(I22="",B22,I22)),">"),CONCATENATE("<",H22,":",IF(I22="",B22,I22),">")),CONCATENATE("<",H22,":",IF(I22="",B22,I22),">")),CONCATENATE("<",I22,">")) -> <eu:AgentProvidesRequirementResponse> | K22: no | L22: no
A23: 22 | B23: BusinessEvent | C23: This class represents a Business Event. A Business Event is a specific situation or event in the lifecycle of a business that fulfils one or more needs or (legal) obligations of that business at this specific point in time. A Business Event requires a set of public services to be delivered and consumed in order for the associated business need(s) or obligation(s) to be fulfilled. Business Events are defined within the context of a particular Member State. In other words, a Business Event groups together a number of public services that need to be delivered for completing that particular event. | D23: Organization | E23: Class | F23: EU | H23: eu | J23: =IF(I23="",IF(F23="FED",IF(AND(E23="ConceptScheme",LEFT(H23,7) <> "inspire"),CONCATENATE("<",H23,":",LOWER(IF(I23="",B23,I23)),">"),CONCATENATE("<",H23,":",IF(I23="",B23,I23),">")),CONCATENATE("<",H23,":",IF(I23="",B23,I23),">")),CONCATENATE("<",I23,">")) -> <eu:BusinessEvent> | K23: no | L23: no
A24: 23 | B24: ChangeEvent | C24: Public organizations are formed and changed in response to events. This may be the result of new legislation, new policies, taking on new obligations etc. The CPOV captures this in its Change Event class but recognises the specific case of an organization's foundation as being sufficiently distinct to require a sub class of Change Event. In the RDF release of the CPOV, ChangeEvent is bound to org:ChangeEvent, FoundationEvent is in the CPOV's own namespace, i.e. cpov:FoundationEvent. | D24: Organization | E24: Class | F24: EU | H24: eu | J24: =IF(I24="",IF(F24="FED",IF(AND(E24="ConceptScheme",LEFT(H24,7) <> "inspire"),CONCATENATE("<",H24,":",LOWER(IF(I24="",B24,I24)),">"),CONCATENATE("<",H24,":",IF(I24="",B24,I24),">")),CONCATENATE("<",H24,":",IF(I24="",B24,I24),">")),CONCATENATE("<",I24,">")) -> <eu:ChangeEvent> | K24: no | L24: no
A25: 24 | B25: ChangeEventHasFormalFramework | C25: hasFormalFramework links a Change Event or Foundation Event to a piece of legislation or a policy document that prompted the change. These concepts and properties are defined in the Core Public Service Vocabulary (CPSV). In the RDF release of the CPOV, these properties are bound to cpsv:hasFormalFramework and cpsv:implements. | D25: Organization | E25: Association | F25: EU | H25: eu | J25: =IF(I25="",IF(F25="FED",IF(AND(E25="ConceptScheme",LEFT(H25,7) <> "inspire"),CONCATENATE("<",H25,":",LOWER(IF(I25="",B25,I25)),">"),CONCATENATE("<",H25,":",IF(I25="",B25,I25),">")),CONCATENATE("<",H25,":",IF(I25="",B25,I25),">")),CONCATENATE("<",I25,">")) -> <eu:ChangeEventHasFormalFramework> | K25: no | L25: no
A26: 25 | B26: ChangeEventOriginalOrganisation | C26: The originalOrganization property links a Change Event to the organization that existed before the change. Although the Foundation Event class is defined as a sub class of Change Event, it is inappropriate to use the originalOrganization property with the Foundation Event class. In the RDF release of the CPOV, these properties are bound to org:originalOrganization and org:changedBy. | D26: Organization | E26: Association | F26: EU | H26: eu | J26: =IF(I26="",IF(F26="FED",IF(AND(E26="ConceptScheme",LEFT(H26,7) <> "inspire"),CONCATENATE("<",H26,":",LOWER(IF(I26="",B26,I26)),">"),CONCATENATE("<",H26,":",IF(I26="",B26,I26),">")),CONCATENATE("<",H26,":",IF(I26="",B26,I26),">")),CONCATENATE("<",I26,">")) -> <eu:ChangeEventOriginalOrganisation> | K26: no | L26: no
A27: 26 | B27: ChangeEventResultingOrganisation | C27: This property links a Change Event or a Foundation Event to the organization that resulted from it. In the RDF release of the CPOV, these properties are bound to org:resultingOrganization and org:resultedFrom. | D27: Organization | E27: Association | F27: EU | H27: eu | J27: =IF(I27="",IF(F27="FED",IF(AND(E27="ConceptScheme",LEFT(H27,7) <> "inspire"),CONCATENATE("<",H27,":",LOWER(IF(I27="",B27,I27)),">"),CONCATENATE("<",H27,":",IF(I27="",B27,I27),">")),CONCATENATE("<",H27,":",IF(I27="",B27,I27),">")),CONCATENATE("<",I27,">")) -> <eu:ChangeEventResultingOrganisation> | K27: no | L27: no
A28: 27 | B28: Channel | C28: A medium through which an agent provides, uses or otherwise interacts with a resource. | D28: Organization | E28: Class | F28: EU | H28: eu | J28: =IF(I28="",IF(F28="FED",IF(AND(E28="ConceptScheme",LEFT(H28,7) <> "inspire"),CONCATENATE("<",H28,":",LOWER(IF(I28="",B28,I28)),">"),CONCATENATE("<",H28,":",IF(I28="",B28,I28),">")),CONCATENATE("<",H28,":",IF(I28="",B28,I28),">")),CONCATENATE("<",I28,">")) -> <eu:Channel> | K28: no | L28: no
A29: 28 | B29: ChannelIdentifier | C29: This property represents a formally-issued Identifier for the Channel. | D29: Organization | E29: Property | F29: EU | H29: eu | J29: =IF(I29="",IF(F29="FED",IF(AND(E29="ConceptScheme",LEFT(H29,7) <> "inspire"),CONCATENATE("<",H29,":",LOWER(IF(I29="",B29,I29)),">"),CONCATENATE("<",H29,":",IF(I29="",B29,I29),">")),CONCATENATE("<",H29,":",IF(I29="",B29,I29),">")),CONCATENATE("<",I29,">")) -> <eu:ChannelIdentifier> | K29: no | L29: no
A30: 29 | B30: ChannelType | C30: This property represents the type of Channel as defined in a controlled vocabulary. Currently several ways of delivering the Public Service have been identified and thus defined as subclasses of the Channel class, for instance E-mail, Homepage, Fax, Assistant, Telephone. | D30: Organization | E30: Property | F30: EU | H30: eu | J30: =IF(I30="",IF(F30="FED",IF(AND(E30="ConceptScheme",LEFT(H30,7) <> "inspire"),CONCATENATE("<",H30,":",LOWER(IF(I30="",B30,I30)),">"),CONCATENATE("<",H30,":",IF(I30="",B30,I30),">")),CONCATENATE("<",H30,":",IF(I30="",B30,I30),">")),CONCATENATE("<",I30,">")) -> <eu:ChannelType> | K30: no | L30: no
A31: 30 | B31: ChannelHasContactPoint | C31: Links a channel to a method of contact. The actual method of contact is provided using the Contact class from the Core public Organization Vocabulary which in turn uses VCard to provide information such as phone number, homepage etc. | D31: Organization | E31: Property | F31: EU | H31: eu | J31: =IF(I31="",IF(F31="FED",IF(AND(E31="ConceptScheme",LEFT(H31,7) <> "inspire"),CONCATENATE("<",H31,":",LOWER(IF(I31="",B31,I31)),">"),CONCATENATE("<",H31,":",IF(I31="",B31,I31),">")),CONCATENATE("<",H31,":",IF(I31="",B31,I31),">")),CONCATENATE("<",I31,">")) -> <eu:ChannelHasContactPoint> | K31: no | L31: no
A32: 31 | B32: ChannelIsOwnedBy | C32: This property links the Channel class with one or more instances of the Public Organization class. This property indicates the owner of a specific Channel through which a Public Service is being delivered. | D32: Organization | E32: Association | F32: EU | H32: eu | J32: =IF(I32="",IF(F32="FED",IF(AND(E32="ConceptScheme",LEFT(H32,7) <> "inspire"),CONCATENATE("<",H32,":",LOWER(IF(I32="",B32,I32)),">"),CONCATENATE("<",H32,":",IF(I32="",B32,I32),">")),CONCATENATE("<",H32,":",IF(I32="",B32,I32),">")),CONCATENATE("<",I32,">")) -> <eu:ChannelIsOwnedBy> | K32: no | L32: no
A33: 32 | B33: ChannelAvailability | C33: Links a channel to information about when the channel is available, such as the opening hours of an office or telephone service. This is provided using the Period of Time class | D33: Organization | E33: Association | F33: EU | H33: eu | J33: =IF(I33="",IF(F33="FED",IF(AND(E33="ConceptScheme",LEFT(H33,7) <> "inspire"),CONCATENATE("<",H33,":",LOWER(IF(I33="",B33,I33)),">"),CONCATENATE("<",H33,":",IF(I33="",B33,I33),">")),CONCATENATE("<",H33,":",IF(I33="",B33,I33),">")),CONCATENATE("<",I33,">")) -> <eu:ChannelAvailability> | K33: no | L33: no
A34: 33 | B34: ChannelProcessingTime | C34: If the processing time for a Public Service varies according to which channel is used, then it should be applied at the channel level and not at the Public Service level. Either way, the actual information is provided using the Processing Time class | D34: Organization | E34: Association | F34: EU | H34: eu | J34: =IF(I34="",IF(F34="FED",IF(AND(E34="ConceptScheme",LEFT(H34,7) <> "inspire"),CONCATENATE("<",H34,":",LOWER(IF(I34="",B34,I34)),">"),CONCATENATE("<",H34,":",IF(I34="",B34,I34),">")),CONCATENATE("<",H34,":",IF(I34="",B34,I34),">")),CONCATENATE("<",I34,">")) -> <eu:ChannelProcessingTime> | K34: no | L34: no
... A101: 100 | B101: JurisdictionIdentifier | C101: The URI for the jurisdiction. | D101: Location | E101: Property | F101: EU | H101: eu | J101: =IF(I101="",IF(F101="FED",IF(AND(E101="ConceptScheme",LEFT(H101,7) <> "inspire"),CONCATENATE("<",H101,":",LOWER(IF(I101="",B101,I101)),">"),CONCATENATE("<",H101,":",IF(I101="",B101,I101),">")),CONCATENATE("<",H101,":",IF(I101="",B101,I101),">")),CONCATENATE("<",I101,">")) -> <eu:JurisdictionIdentifier> | K101: no | L101: no
A102: 101 | B102: LegalEntity | C102: A self-employed person, company, or organization that has legal rights and obligations. | D102: Organization | E102: Class | F102: EU | G102: A Legal Entity able to transact business, typically registered with a body able to confer legal status such as a national business register. It is able to trade, is legally liable for its actions, accounts, tax affairs etc. This makes Legal Entities distinct from the concept of organisations or groups. Many organisations exist that are not Legal Entities, yet to the outside world they have staff, hierarchies, locations etc. Other organisations exist that are an umbrella for several Legal Entities (universities are often good examples of this). This vocabulary is concerned solely with registered Legal Entities and does not attempt to cover all possible trading bodies. Belgian legal entities are registered in CBE and have an enterprise number. | H102: eu | J102: =IF(I102="",IF(F102="FED",IF(AND(E102="ConceptScheme",LEFT(H102,7) <> "inspire"),CONCATENATE("<",H102,":",LOWER(IF(I102="",B102,I102)),">"),CONCATENATE("<",H102,":",IF(I102="",B102,I102),">")),CONCATENATE("<",H102,":",IF(I102="",B102,I102),">")),CONCATENATE("<",I102,">")) -> <eu:LegalEntity> | K102: no | L102: yes
A103: 102 | B103: LegalEntityLegalIdentifier | C103: The identifier given to the legal entity by the authority with which it is registered. | D103: Organization | E103: Property | F103: EU | H103: eu | J103: =IF(I103="",IF(F103="FED",IF(AND(E103="ConceptScheme",LEFT(H103,7) <> "inspire"),CONCATENATE("<",H103,":",LOWER(IF(I103="",B103,I103)),">"),CONCATENATE("<",H103,":",IF(I103="",B103,I103),">")),CONCATENATE("<",H103,":",IF(I103="",B103,I103),">")),CONCATENATE("<",I103,">")) -> <eu:LegalEntityLegalIdentifier> | K103: no | L103: no
A104: 103 | B104: LegalEntityIdentifier | C104: A formally-issued identifier for the legal entity, other than the one that confers legal status upon it. | D104: Organization | E104: Property | F104: EU | H104: eu | J104: =IF(I104="",IF(F104="FED",IF(AND(E104="ConceptScheme",LEFT(H104,7) <> "inspire"),CONCATENATE("<",H104,":",LOWER(IF(I104="",B104,I104)),">"),CONCATENATE("<",H104,":",IF(I104="",B104,I104),">")),CONCATENATE("<",H104,":",IF(I104="",B104,I104),">")),CONCATENATE("<",I104,">")) -> <eu:LegalEntityIdentifier> | K104: no | L104: no
A105: 104 | B105: LegalEntityLegalName | C105: The legal name of the business. | D105: Organization | E105: Property | F105: EU | H105: eu | J105: =IF(I105="",IF(F105="FED",IF(AND(E105="ConceptScheme",LEFT(H105,7) <> "inspire"),CONCATENATE("<",H105,":",LOWER(IF(I105="",B105,I105)),">"),CONCATENATE("<",H105,":",IF(I105="",B105,I105),">")),CONCATENATE("<",H105,":",IF(I105="",B105,I105),">")),CONCATENATE("<",I105,">")) -> <eu:LegalEntityLegalName> | K105: no | L105: no
A106: 105 | B106: LegalEntityAlternativeName | C106: A recognized name other than the legal name. | D106: Organization | E106: Property | F106: EU | H106: eu | J106: =IF(I106="",IF(F106="FED",IF(AND(E106="ConceptScheme",LEFT(H106,7) <> "inspire"),CONCATENATE("<",H106,":",LOWER(IF(I106="",B106,I106)),">"),CONCATENATE("<",H106,":",IF(I106="",B106,I106),">")),CONCATENATE("<",H106,":",IF(I106="",B106,I106),">")),CONCATENATE("<",I106,">")) -> <eu:LegalEntityAlternativeName> | K106: no | L106: no
A107: 106 | B107: LegalEntityCompanyType | C107: The type of the business. | D107: Organization | E107: Property | F107: EU | H107: eu | J107: =IF(I107="",IF(F107="FED",IF(AND(E107="ConceptScheme",LEFT(H107,7) <> "inspire"),CONCATENATE("<",H107,":",LOWER(IF(I107="",B107,I107)),">"),CONCATENATE("<",H107,":",IF(I107="",B107,I107),">")),CONCATENATE("<",H107,":",IF(I107="",B107,I107),">")),CONCATENATE("<",I107,">")) -> <eu:LegalEntityCompanyType> | K107: no | L107: no
A108: 107 | B108: LegalEntityCompanyStatus | C108: The status of the business. | D108: Organization | E108: Property | F108: EU | H108: eu | J108: =IF(I108="",IF(F108="FED",IF(AND(E108="ConceptScheme",LEFT(H108,7) <> "inspire"),CONCATENATE("<",H108,":",LOWER(IF(I108="",B108,I108)),">"),CONCATENATE("<",H108,":",IF(I108="",B108,I108),">")),CONCATENATE("<",H108,":",IF(I108="",B108,I108),">")),CONCATENATE("<",I108,">")) -> <eu:LegalEntityCompanyStatus> | K108: no | L108: no
A109: 108 | B109: LegalEntityCompanyActivity | C109: The activity of the business. | D109: Organization | E109: Property | F109: EU | H109: eu | J109: =IF(I109="",IF(F109="FED",IF(AND(E109="ConceptScheme",LEFT(H109,7) <> "inspire"),CONCATENATE("<",H109,":",LOWER(IF(I109="",B109,I109)),">"),CONCATENATE("<",H109,":",IF(I109="",B109,I109),">")),CONCATENATE("<",H109,":",IF(I109="",B109,I109),">")),CONCATENATE("<",I109,">")) -> <eu:LegalEntityCompanyActivity> | K109: no | L109: no
A110: 109 | B110: LegalEntityRegisteredAddress | C110: The registered address of the business. | D110: Organization | E110: Association | F110: EU | H110: eu | J110: =IF(I110="",IF(F110="FED",IF(AND(E110="ConceptScheme",LEFT(H110,7) <> "inspire"),CONCATENATE("<",H110,":",LOWER(IF(I110="",B110,I110)),">"),CONCATENATE("<",H110,":",IF(I110="",B110,I110),">")),CONCATENATE("<",H110,":",IF(I110="",B110,I110),">")),CONCATENATE("<",I110,">")) -> <eu:LegalEntityRegisteredAddress> | K110: no | L110: no
A111: 110 | B111: LegalEntityAddress | C111: An address related to the business, other than the registered address. | D111: Organization | E111: Association | F111: EU | H111: eu | J111: =IF(I111="",IF(F111="FED",IF(AND(E111="ConceptScheme",LEFT(H111,7) <> "inspire"),CONCATENATE("<",H111,":",LOWER(IF(I111="",B111,I111)),">"),CONCATENATE("<",H111,":",IF(I111="",B111,I111),">")),CONCATENATE("<",H111,":",IF(I111="",B111,I111),">")),CONCATENATE("<",I111,">")) -> <eu:LegalEntityAddress> | K111: no | L111: no
A112: 111 | B112: LegalEntityLocation | C112: A location related to the business. | D112: Organization | E112: Association | F112: EU | H112: eu | J112: =IF(I112="",IF(F112="FED",IF(AND(E112="ConceptScheme",LEFT(H112,7) <> "inspire"),CONCATENATE("<",H112,":",LOWER(IF(I112="",B112,I112)),">"),CONCATENATE("<",H112,":",IF(I112="",B112,I112),">")),CONCATENATE("<",H112,":",IF(I112="",B112,I112),">")),CONCATENATE("<",I112,">")) -> <eu:LegalEntityLocation> | K112: no | L112: no
A113: 112 | B113: LifeEvent | C113: The Life Event class represents an important event or situations in a citizen's life where public services may be required. Note the scope: an individual will encounter any number of 'events' in the general sense of the word. In the context of the CPSV-AP, the Life Event class only represents an event for which a Public Service is related. For example, a couple becoming engaged is not a CPSV-AP Life Event, getting married is, since only the latter has any relevance to public services. | D113: Person | E113: Class | F113: EU | H113: eu | J113: =IF(I113="",IF(F113="FED",IF(AND(E113="ConceptScheme",LEFT(H113,7) <> "inspire"),CONCATENATE("<",H113,":",LOWER(IF(I113="",B113,I113)),">"),CONCATENATE("<",H113,":",IF(I113="",B113,I113),">")),CONCATENATE("<",H113,":",IF(I113="",B113,I113),">")),CONCATENATE("<",I113,">")) -> <eu:LifeEvent> | K113: no | L113: no
A114: 113 | B114: Location | C114: An identifiable geographic place. | D114: Location | E114: Class | F114: EU | H114: eu | J114: =IF(I114="",IF(F114="FED",IF(AND(E114="ConceptScheme",LEFT(H114,7) <> "inspire"),CONCATENATE("<",H114,":",LOWER(IF(I114="",B114,I114)),">"),CONCATENATE("<",H114,":",IF(I114="",B114,I114),">")),CONCATENATE("<",H114,":",IF(I114="",B114,I114),">")),CONCATENATE("<",I114,">")) -> <eu:Location> | K114: no | L114: no
... A123: 122 | B123: OutputType | C123: The type of the output. | D123: Organization | E123: Property | F123: EU | H123: eu | J123: =IF(I123="",IF(F123="FED",IF(AND(E123="ConceptScheme",LEFT(H123,7) <> "inspire"),CONCATENATE("<",H123,":",LOWER(IF(I123="",B123,I123)),">"),CONCATENATE("<",H123,":",IF(I123="",B123,I123),">")),CONCATENATE("<",H123,":",IF(I123="",B123,I123),">")),CONCATENATE("<",I123,">")) -> <eu:OutputType> | K123: no | L123: no
